Workbook

Sheet Solutions
A1: param Bud := 250; | C1: param Bud := 250; | E1: param Bud := 300; | G1: param Bud := 300; | I1: param Bud := 350; | K1: param Bud := 350;
A3: param alp := 0.85; | C3: param alp := 0.98; | E3: param alp := 0.96; | G3: param alp := 0.98; | I3: param alp := 0.98; | K3: param alp := 0.87;
A4: param bet := 0.94; | C4: param bet := 0.85; | E4: param bet := 0.85; | G4: param bet := 0.71; | I4: param bet := 0.6; | K4: param bet := 0.73;
A6: Cost_Sec = 133 | C6: Cost_Sec = 71.7 | E6: Cost_Sec = 125.2 | G6: Cost_Sec = 71.7 | I6: Cost_Sec = 71.7 | K6: Cost_Sec = 130.4
A8: Cost_Ele = 116.9 | C8: Cost_Ele = 178.1 | E8: Cost_Ele = 174.7 | G8: Cost_Ele = 228.1 | I8: Cost_Ele = 278.3 | K8: Cost_Ele = 219.6
A10: Create_Sec = 2400 | C10: Create_Sec = 1400 | E10: Create_Sec = 2100 | G10: Create_Sec = 1400 | I10: Create_Sec = 1400 | K10: Create_Sec = 2300
A12: Create_Ele = 2900 | C12: Create_Ele = 4150 | E12: Create_Ele = 3950 | G12: Create_Ele = 5400 | I12: Create_Ele = 6700 | K12: Create_Ele = 5200
A14: Overcrowd_Sec = 0.405708 | C14: Overcrowd_Sec = 0.457379 | E14: Overcrowd_Sec = 0.420821 | G14: Overcrowd_Sec = 0.457379 | I14: Overcrowd_Sec = 0.457379 | K14: Overcrowd_Sec = 0.41071
A16: Overcrowd_Ele = 0.502557 | C16: Overcrowd_Ele = 0.455099 | E16: Overcrowd_Ele = 0.46249 | G16: Overcrowd_Ele = 0.410547 | I16: Overcrowd_Ele = 0.367018 | K16: Overcrowd_Ele = 0.417491
A18: Gurobi 7.0.0: optimal solution; objective 5225.6 | C18: Gurobi 7.0.0: optimal solution; objective 5495.6 | E18: Gurobi 7.0.0: optimal solution; objective 5952.7 | G18: Gurobi 7.0.0: optimal solution; objective 6748.8 | I18: Gurobi 7.0.0: optimal solution; objective 8012.2 | K18: Gurobi 7.0.0: optimal solution; objective 7352.4
A19: 13873 simplex iterations | C19: 48305 simplex iterations | E19: 142936 simplex iterations | G19: 529184 simplex iterations | I19: 122695 simplex iterations | K19: 1650268 simplex iterations
A20: 1178 branch-and-cut nodes | C20: 6118 branch-and-cut nodes | E20: 16836 branch-and-cut nodes | G20: 55424 branch-and-cut nodes | I20: 12354 branch-and-cut nodes | K20: 217628 branch-and-cut nodes
... A25: 5 0 | C25: 5 0 | E25: 5 0 | G25: 5 0 | I25: 5 0 | K25: 5 0
A26: 42887 | C26: 6 0 | E26: 6 0 | G26: 6 0 | I26: 6 0 | K26: 6 0
A27: 7 0 | C27: 7 0 | E27: 7 0 | G27: 7 0 | I27: 7 0 | K27: 7 0
A28: 8 0 | C28: 8 0 | E28: 8 0 | G28: 8 0 | I28: 8 0 | K28: 8 0
A29: 9 0 | C29: 9 0 | E29: 9 0 | G29: 9 0 | I29: 9 0 | K29: 9 0
A30: 43010 | C30: 43009 | E30: 43009 | G30: 43009 | I30: 43009 | K30: 43010
A31: 43040 | C31: 43042 | E31: 11 0 | G31: 43042 | I31: 43042 | K31: 43040
A32: 12 0 | C32: 12 0 | E32: 12 0 | G32: 12 0 | I32: 12 0 | K32: 12 0
A33: 13 0 | C33: 13 0 | E33: 13 0 | G33: 13 0 | I33: 13 0 | K33: 13 0
A34: 14 0 | C34: 14 0 | E34: 14 0 | G34: 14 0 | I34: 14 0 | K34: 14 0
A35: 15 0 | C35: 15 0 | E35: 15 0 | G35: 15 0 | I35: 15 0 | K35: 15 0
A36: 16 0 | C36: 16 0 | E36: 16 0 | G36: 16 0 | I36: 16 0 | K36: 16 0
A37: 17 0 | C37: 17 0 | E37: 17 0 | G37: 17 0 | I37: 17 0 | K37: 17 0
A38: 18 0 | C38: 18 0 | E38: 18 0 | G38: 18 0 | I38: 18 0 | K38: 18 0
A39: 19 0 | C39: 19 0 | E39: 19 0 | G39: 19 0 | I39: 19 0 | K39: 19 0
A40: ; | C40: ; | E40: ; | G40: ; | I40: ; | K40: ;
A42: X [*] := | C42: X [*] := | E42: X [*] := | G42: X [*] := | I42: X [*] := | K42: X [*] :=
A43: 1 0 9 0 17 0 27 0 36 0 48 0 56 0 65 0 75 0 83 0 90 0 | C43: 1 0 9 0 17 0 27 0 36 0 48 0 56 0 65 0 75 0 83 0 90 0 | E43: 1 0 9 0 17 0 27 0 36 0 48 0 56 0 65 0 75 0 83 0 90 0 | G43: 1 0 9 0 17 0 27 0 36 1 48 0 56 0 65 0 75 0 83 0 90 0 | I43: 1 0 9 0 17 0 27 0 36 1 48 0 56 0 65 0 75 0 83 0 90 0 | K43: 1 0 9 0 17 0 27 0 36 1 48 0 56 0 65 0 75 0 83 0 90 0
A44: 2 0 10 0 18 0 28 0 38 0 49 0 57 0 67 0 77 0 84 2 91 0 | C44: 2 0 10 0 18 0 28 0 38 0 49 0 57 1 67 0 77 1 84 2 91 0 | E44: 2 0 10 0 18 0 28 0 38 0 49 0 57 0 67 0 77 1 84 2 91 0 | G44: 2 0 10 0 18 0 28 0 38 0 49 0 57 1 67 0 77 1 84 2 91 0 | I44: 2 0 10 0 18 0 28 0 38 0 49 0 57 1 67 0 77 1 84 3 91 0 | K44: 2 0 10 0 18 0 28 0 38 0 49 0 57 1 67 0 77 1 84 2 91 0
... A70: l = 6 | C70: k = 17 | E70: l = 6 | G70: k = 17 | I70: l = 6 | K70: i = 10
A71: h = 4 | B71: x2 | C71: V[k,l] = 387 | E71: h = 4 | G71: V[k,l] = 350 | I71: h = 4 | K71: U[i,j] = 904
A73: k = 6 | C73: k = 47 | E73: l = 6 | G73: l = 20 | I73: l = 6 | K73: l = 3
A74: V[k,l] = 700 | C74: V[k,l] = 63 | E74: h = 5 | G74: h = 2 | I74: h = 8 | K74: h = 2
A76: l = 17 | C76: l = 33 | E76: k = 6 | G76: k = 3 | I76: k = 6 | K76: k = 3
A77: h = 4 | C77: h = 2 | E77: V[k,l] = 750 | G77: V[k,l] = 74 | I77: V[k,l] = 884 | K77: V[k,l] = 85
A79: k = 17 | C79: k = 20 | E79: l = 17 | G79: k = 20 | I79: k = 22 | K79: k = 20
A80: V[k,l] = 328 | C80: V[k,l] = 30 | E80: h = 8 | G80: V[k,l] = 176 | I80: V[k,l] = 16 | K80: V[k,l] = 84
A82: k = 47 | C82: k = 33 | E82: k = 17 | G82: l = 47 | I82: l = 17 | K82: k = 46
A83: V[k,l] = 22 | C83: V[k,l] = 177 | E83: V[k,l] = 413 | G83: h = 4 | I83: h = 9 | K83: V[k,l] = 10
A85: l = 53 | C85: k = 91 | E85: k = 47 | G85: k = 5 | I85: k = 17 | K85: k = 54
A86: h = 1 | C86: V[k,l] = 43 | E86: V[k,l] = 137 | G86: V[k,l] = 28 | I86: V[k,l] = 559 | K86: V[k,l] = 71
A88: k = 53 | C88: l = 53 | E88: l = 33 | G88: k = 17 | I88: k = 47 | K88: l = 6
A89: V[k,l] = 200 | C89: h = 2 | E89: h = 1 | G89: V[k,l] = 50 | I89: V[k,l] = 26 | K89: h = 4
... A101: V[k,l] = 419 | C101: V[k,l] = 155 | E101: h = 2 | G101: V[k,l] = 4 | I101: V[k,l] = 165 | K101: V[k,l] = 350
C103: k = 65 | E103: k = 53 | G103: l = 55 | I103: k = 33 | K103: l = 33
C104: V[k,l] = 73 | E104: V[k,l] = 250 | G104: h = 5 | I104: V[k,l] = 53 | K104: h = 2
C106: l = 86 | E106: l = 55 | G106: k = 52 | I106: l = 47 | K106: k = 20
C107: h = 2 | E107: h = 1 | G107: V[k,l] = 105 | I107: h = 5 | K107: V[k,l] = 10
C109: k = 2 | E109: k = 52 | G109: k = 55 | I109: k = 5 | K109: k = 33
C110: V[k,l] = 6 | E110: V[k,l] = 22 | G110: V[k,l] = 155 | I110: V[k,l] = 92 | K110: V[k,l] = 127
C112: k = 21 | E112: k = 55 | G112: k = 65 | I112: k = 47 | K112: k = 91
C113: V[k,l] = 61 | E113: V[k,l] = 123 | G113: V[k,l] = 140 | I113: V[k,l] = 308 | K113: V[k,l] = 113
C115: k = 70 | E115: k = 65 | G115: l = 70 | I115: l = 52 | K115: l = 47
C116: V[k,l] = 61 | E116: V[k,l] = 55 | G116: h = 1 | I116: h = 1 | K116: h = 4
C118: k = 86 | E118: l = 81 | G118: k = 70 | I118: k = 52 | K118: k = 5
C119: V[k,l] = 61 | E119: h = 2 | G119: V[k,l] = 182 | I119: V[k,l] = 189 | K119: V[k,l] = 16
... C140: V[k,l] = 326 | E140: V[k,l] = 442 | G140: V[k,l] = 185 | I140: V[k,l] = 16 | K140: V[k,l] = 90
G142: k = 5 | I142: k = 70 | K142: k = 55
G143: V[k,l] = 24 | I143: V[k,l] = 165 | K143: V[k,l] = 132
G145: k = 17 | I145: k = 81 | K145: k = 65
G146: V[k,l] = 157 | I146: V[k,l] = 61 | K146: V[k,l] = 128
G148: k = 47 | I148: k = 88 | K148: l = 70
G149: V[k,l] = 169 | I149: V[k,l] = 8 | K149: h = 2
I151: l = 89 | K151: k = 70
I152: h = 9 | K152: V[k,l] = 124
I154: k = 2 | K154: k = 81
I155: V[k,l] = 8 | K155: V[k,l] = 10
I157: k = 48 | K157: k = 88
I158: V[k,l] = 14 | K158: V[k,l] = 116
I160: k = 57 | K160: l = 89
I161: V[k,l] = 8 | K161: h = 8
I163: k = 89 | K163: k = 17
I164: V[k,l] = 570 | K164: V[k,l] = 39
I166: l = 91 | K166: k = 89
I167: h = 2 | K167: V[k,l] = 511
I169: k = 33
I170: V[k,l] = 20
I172: k = 91
I173: V[k,l] = 188
I175: k = 96
I176: V[k,l] = 42

Sheet bud=250
A1: Bud := 250; | B1: alp := 0.98; | C1: bet := 0.85;
A2: Gurobi 7.0.0: optimal solution; objective 5495.6
A3: 48305 simplex iterations
A4: 6118 branch-and-cut nodes
A5: i | B5: W [*] := | C5: Secondary expansion | G5: Cost_Sec = | H5: 71.7 | I5: $
A6: 1 | D6: Clayton Heights Secondary | G6: Cost_Ele = | H6: 178.1 | I6: $
A7: 2 | D7: Ecole Earl Marriott
A8: 3 | D8: Ecole Elgin Park | G8: Create_Sec = | H8: 1400 | I8: seats
A9: 4 | D9: Ecole Fraser Heights | G9: Create_Ele = | H9: 4150 | I9: seats
A10: 5 | D10: Ecole Kwantlen Park
A11: 6 | D11: Ecole Lord Tweedsmuir | G11: Overcrowd_Sec | H11: =0.457379*100 -> 45.7379 | I11: %
A12: 7 | D12: Ecole Panorama Ridge | G12: Overcrowd_Ele | H12: =0.455099*100 -> 45.5099 | I12: %
A13: 8 | D13: Enver Creek Secondary
A14: 9 | D14: Fleetwood Park Secondary
A15: 10 | B15: 1 | C15: 100 | D15: Frank Hurt Secondary
A16: 11 | B16: 3 | C16: 300 | D16: Guildford Park Secondary
A17: 12 | D17: Johnston Heights Secondary
A18: 13 | D18: L. A. Matheson Secondary
A19: 14 | D19: North Surrey Secondary
A20: 15 | D20: Princess Margaret Secondary
A21: 16 | D21: Queen Elizabeth Secondary
A22: 17 | D22: Semiahmoo Secondary
A23: 18 | D23: Sullivan Heights Secondary
A24: 19 | D24: Tamanawis Secondary
A25: ; | C25: =SUM(C6:C24) -> 400 | E25: Cost: | F25: =C25*2.9/100 -> 11.6
A27: k | B27: X [*] := | C27: Elementary expansion in hundreds
A28: 1 | D28: A. H. P. Matthew Elementary
A29: 2 | D29: A. J. McLellan Elementary
A30: 3 | D30: Adams Road Elementary
A31: 4 | D31: Bayridge Elementary
A32: 5 | D32: Bear Creek Elementary
A33: 6 | D33: Beaver Creek Elementary
A34: 7 | D34: Berkshire Park Elementary
A35: 8 | D35: Betty Huff Elementary
A36: 9 | D36: Bonaccord Elementary
A37: 10 | D37: Bothwell Elementary
A38: 11 | D38: Boundary Park Elementary
A39: 12 | D39: Bridgeview Elementary
... A46: 19 | D46: Clayton Elementary
A47: 20 | B47: 2 | C47: =B47*100 -> 200 | D47: Coast Meridian Elementary
A48: 21 | B48: 1 | C48: =B48*100 -> 100 | D48: Colebrook Elementary
A49: 22 | D49: Cougar Creek Elementary
A50: 23 | D50: Coyote Creek Elementary
A51: 24 | D51: Creekside Elementary
A52: 25 | D52: David Brankin Elementary
A53: 26 | D53: Dogwood Elementary
A54: 27 | D54: Don Christian Elementary
A55: 28 | D55: Dr. F. D. Sinclair Elementary
A56: 29 | D56: East Kensington Elementary
A57: 30 | D57: École Crescent Park
A58: 31 | D58: École Erma Stephenson
A59: 32 | D59: École Fraser Wood
A60: 33 | D60: École Frost Road
... A70: 43 | D70: École Woodward Hill
A71: 44 | B71: 1 | C71: =B71*100 -> 100 | D71: Ellendale Elementary
A72: 45 | D72: Forsyth Road Elementary
A73: 46 | D73: George Greenaway Elementary
A74: 47 | D74: Georges Vanier Elementary
A75: 48 | D75: Goldstone Park Elementary
A76: 49 | D76: Green Timbers Elementary
A77: 50 | B77: 1 | C77: =B77*100 -> 100 | D77: H. T. Thrift Elementary
A78: 51 | D78: Hall's Prairie Elementary
A79: 52 | D79: Harold Bishop Elementary
A80: 53 | D80: Hazelgrove Elementary
A81: 54 | B81: 1 | C81: 100 | D81: Hillcrest Elementary
A82: 55 | D82: Hjorth Road Elementary
A83: 56 | D83: Holly Elementary
A84: 57 | B84: 1 | C84: =B84*100 -> 100 | D84: Hyland Elementary
A85: 58 | D85: J. T. Brown Elementary
A86: 59 | D86: James Ardiel Elementary
A87: 60 | D87: Janice Churchill Elementary
A88: 61 | D88: Katzie Elementary
A89: 62 | D89: Kennedy Trail Elementary
A90: 63 | D90: Kirkbride Elementary
A91: 64 | D91: Latimer Road Elementary
A92: 65 | D92: Lena Shaw Elementary
A93: 66 | D93: M. B. Sanford Elementary
A94: 67 | D94: Maple Green Elementary
A95: 68 | D95: Martha Jane Norris Elementary
A96: 69 | D96: Mary Jane Shannon Elementary
... A103: 76 | D103: Port Kells Elementary
A104: 77 | B104: 1 | C104: =B104*100 -> 100 | D104: Prince Charles Elementary
A105: 78 | B105: 1 | C105: 100 | D105: Ray Shepherd Elementary
A106: 79 | D106: Rosemary Heights Elementary
A107: 80 | D107: Royal Heights Elementary
A108: 81 | B108: 1 | C108: =B108*100 -> 100 | D108: Semiahmoo Trail Elementary
A109: 82 | D109: Senator Reid Elementary
A110: 83 | D110: Serpentine Heights Elementary
A111: 84 | B111: 2 | C111: =B111*100 -> 200 | D111: South Meridian Elementary
A112: 85 | D112: Strawberry Hill Elementary
A113: 86 | D113: Sullivan Elementary
A114: 87 | D114: Sunnyside Elementary
A115: 88 | B115: 1 | C115: =B115*100 -> 100 | D115: Surrey Centre Elementary
A116: 89 | B116: 1 | C116: =B116*100 -> 100 | D116: T. E. Scott Elementary
A117: 90 | D117: W. E. Kinvig Elementary
A118: 91 | D118: Walnut Road Elementary
A119: 92 | D119: Westerman Elementary
A120: 93 | D120: White Rock Elementary
A121: 94 | D121: William F. Davidson Elementary
A122: 95 | D122: William Watson Elementary
...

Sheet bud=300
A1: Bud := 300; | B1: alp := 0.98; | C1: bet := 0.71;
A2: Gurobi 7.0.0: optimal solution; objective 6748.8
A3: 529184 simplex iterations
A4: 55424 branch-and-cut nodes
A5: i | B5: W [*] := | C5: Secondary expansion | G5: Cost_Sec = | H5: 71.7 | I5: $
A6: 1 | D6: Clayton Heights Secondary | G6: Cost_Ele = | H6: 228.1 | I6: $
A7: 2 | D7: Ecole Earl Marriott
A8: 3 | D8: Ecole Elgin Park | G8: Create_Sec = | H8: 1400 | I8: seats
A9: 4 | D9: Ecole Fraser Heights | G9: Create_Ele = | H9: 5400 | I9: seats
A10: 5 | D10: Ecole Kwantlen Park
A11: 6 | D11: Ecole Lord Tweedsmuir | G11: Overcrowd_Sec | H11: =0.457379*100 -> 45.7379 | I11: %
A12: 7 | D12: Ecole Panorama Ridge | G12: Overcrowd_Ele | H12: =0.410547*100 -> 41.0547 | I12: %
A13: 8 | D13: Enver Creek Secondary
A14: 9 | D14: Fleetwood Park Secondary
A15: 10 | B15: 1 | C15: 100 | D15: Frank Hurt Secondary
A16: 11 | B16: 3 | C16: 300 | D16: Guildford Park Secondary
A17: 12 | D17: Johnston Heights Secondary
A18: 13 | D18: L. A. Matheson Secondary
A19: 14 | D19: North Surrey Secondary
A20: 15 | D20: Princess Margaret Secondary
A21: 16 | D21: Queen Elizabeth Secondary
A22: 17 | D22: Semiahmoo Secondary
A23: 18 | D23: Sullivan Heights Secondary
A24: 19 | D24: Tamanawis Secondary
A25: ; | C25: =SUM(C6:C24) -> 400 | E25: Cost: | F25: =C25*2.9/100 -> 11.6
A27: k | B27: X [*] := | C27: Elementary expansion in hundreds
A28: 1 | D28: A. H. P. Matthew Elementary
A29: 2 | D29: A. J. McLellan Elementary
A30: 3 | D30: Adams Road Elementary
A31: 4 | D31: Bayridge Elementary
A32: 5 | D32: Bear Creek Elementary
A33: 6 | D33: Beaver Creek Elementary
A34: 7 | D34: Berkshire Park Elementary
A35: 8 | D35: Betty Huff Elementary
A36: 9 | D36: Bonaccord Elementary
A37: 10 | D37: Bothwell Elementary
A38: 11 | D38: Boundary Park Elementary
A39: 12 | D39: Bridgeview Elementary
... A46: 19 | D46: Clayton Elementary
A47: 20 | B47: 2 | C47: =B47*100 -> 200 | D47: Coast Meridian Elementary
A48: 21 | B48: 2 | C48: =B48*100 -> 200 | D48: Colebrook Elementary
A49: 22 | D49: Cougar Creek Elementary
A50: 23 | D50: Coyote Creek Elementary
A51: 24 | D51: Creekside Elementary
A52: 25 | D52: David Brankin Elementary
A53: 26 | D53: Dogwood Elementary
A54: 27 | D54: Don Christian Elementary
A55: 28 | D55: Dr. F. D. Sinclair Elementary
A56: 29 | D56: East Kensington Elementary
A57: 30 | D57: École Crescent Park
A58: 31 | D58: École Erma Stephenson
A59: 32 | D59: École Fraser Wood
A60: 33 | D60: École Frost Road
... A62: 35 | D62: École Jessie Lee
A63: 36 | B63: 1 | C63: 100 | D63: École K.B. Woodward
A64: 37 | D64: École Martha Currie
A65: 38 | D65: École Ocean Cliff
A66: 39 | D66: École Peace Arch
A67: 40 | D67: École Riverdale
A68: 41 | D68: École Simon Cunningham
A69: 42 | D69: École Sunrise Ridge
A70: 43 | D70: École Woodward Hill
A71: 44 | B71: 1 | C71: =B71*100 -> 100 | D71: Ellendale Elementary
A72: 45 | D72: Forsyth Road Elementary
A73: 46 | B73: 1 | C73: 100 | D73: George Greenaway Elementary
A74: 47 | D74: Georges Vanier Elementary
A75: 48 | D75: Goldstone Park Elementary
A76: 49 | D76: Green Timbers Elementary
A77: 50 | B77: 1 | C77: =B77*100 -> 100 | D77: H. T. Thrift Elementary
A78: 51 | D78: Hall's Prairie Elementary
A79: 52 | D79: Harold Bishop Elementary
A80: 53 | D80: Hazelgrove Elementary
A81: 54 | B81: 1 | C81: 100 | D81: Hillcrest Elementary
A82: 55 | D82: Hjorth Road Elementary
A83: 56 | D83: Holly Elementary
A84: 57 | B84: 1 | C84: =B84*100 -> 100 | D84: Hyland Elementary
A85: 58 | D85: J. T. Brown Elementary
A86: 59 | D86: James Ardiel Elementary
A87: 60 | D87: Janice Churchill Elementary
A88: 61 | D88: Katzie Elementary
A89: 62 | D89: Kennedy Trail Elementary
A90: 63 | D90: Kirkbride Elementary
A91: 64 | D91: Latimer Road Elementary
A92: 65 | D92: Lena Shaw Elementary
A93: 66 | D93: M. B. Sanford Elementary
A94: 67 | D94: Maple Green Elementary
A95: 68 | D95: Martha Jane Norris Elementary
A96: 69 | D96: Mary Jane Shannon Elementary
... A98: 71 | D98: Newton Elementary
A99: 72 | B99: 1 | C99: =B99*100 -> 100 | D99: North Ridge Elementary
A100: 73 | D100: Old Yale Road Elementary
A101: 74 | D101: Pacific Heights Elementary
A102: 75 | D102: Panorama Park Elementary
A103: 76 | D103: Port Kells Elementary
A104: 77 | B104: 1 | C104: =B104*100 -> 100 | D104: Prince Charles Elementary
A105: 78 | B105: 2 | C105: 200 | D105: Ray Shepherd Elementary
A106: 79 | D106: Rosemary Heights Elementary
A107: 80 | D107: Royal Heights Elementary
A108: 81 | B108: 1 | C108: =B108*100 -> 100 | D108: Semiahmoo Trail Elementary
A109: 82 | D109: Senator Reid Elementary
...

Sheet bud=350
A1: Bud := 350; | B1: alp := 0.87; | C1: bet := 0.73;
A2: Gurobi 7.0.0: optimal solution; objective 7352.4
A3: 1650268 simplex iterations
A4: 217628 branch-and-cut nodes
A5: i | B5: W [*] := | C5: Secondary expansion | G5: Cost_Sec = | H5: 130.4 | I5: $
A6: 1 | D6: Clayton Heights Secondary | G6: Cost_Ele = | H6: 219.6 | I6: $
A7: 2 | D7: Ecole Earl Marriott
A8: 3 | D8: Ecole Elgin Park | G8: Create_Sec = | H8: 2300 | I8: seats
A9: 4 | D9: Ecole Fraser Heights | G9: Create_Ele = | H9: 5200 | I9: seats
A10: 5 | D10: Ecole Kwantlen Park
A11: 6 | D11: Ecole Lord Tweedsmuir | G11: Overcrowd_Sec | H11: =0.41071*100 -> 41.071 | I11: %
A12: 7 | D12: Ecole Panorama Ridge | G12: Overcrowd_Ele | H12: =0.417491*100 -> 41.7491 | I12: %
A13: 8 | D13: Enver Creek Secondary
A14: 9 | D14: Fleetwood Park Secondary
A15: 10 | B15: 2 | C15: =B15*100 -> 200 | D15: Frank Hurt Secondary
A16: 11 | B16: 1 | C16: =B16*100 -> 100 | D16: Guildford Park Secondary
A17: 12 | D17: Johnston Heights Secondary
A18: 13 | D18: L. A. Matheson Secondary
A19: 14 | D19: North Surrey Secondary
A20: 15 | D20: Princess Margaret Secondary
A21: 16 | D21: Queen Elizabeth Secondary
A22: 17 | D22: Semiahmoo Secondary
A23: 18 | D23: Sullivan Heights Secondary
A24: 19 | D24: Tamanawis Secondary
A25: ; | C25: =SUM(C6:C24) -> 300 | E25: Cost: | F25: =C25*2.9/100 -> 8.7
A27: k | B27: X [*] := | C27: Elementary expansion in hundreds
A28: 1 | D28: A. H. P. Matthew Elementary
A29: 2 | D29: A. J. McLellan Elementary
A30: 3 | D30: Adams Road Elementary
A31: 4 | D31: Bayridge Elementary
A32: 5 | D32: Bear Creek Elementary
A33: 6 | D33: Beaver Creek Elementary
A34: 7 | D34: Berkshire Park Elementary
A35: 8 | D35: Betty Huff Elementary
A36: 9 | D36: Bonaccord Elementary
A37: 10 | D37: Bothwell Elementary
A38: 11 | D38: Boundary Park Elementary
A39: 12 | D39: Bridgeview Elementary
... A46: 19 | D46: Clayton Elementary
A47: 20 | B47: 2 | C47: =B47*100 -> 200 | D47: Coast Meridian Elementary
A48: 21 | B48: 2 | C48: =B48*100 -> 200 | D48: Colebrook Elementary
A49: 22 | D49: Cougar Creek Elementary
A50: 23 | D50: Coyote Creek Elementary
A51: 24 | D51: Creekside Elementary
A52: 25 | D52: David Brankin Elementary
A53: 26 | D53: Dogwood Elementary
A54: 27 | D54: Don Christian Elementary
A55: 28 | D55: Dr. F. D. Sinclair Elementary
A56: 29 | D56: East Kensington Elementary
A57: 30 | D57: École Crescent Park
A58: 31 | D58: École Erma Stephenson
A59: 32 | D59: École Fraser Wood
A60: 33 | D60: École Frost Road
... A62: 35 | D62: École Jessie Lee
A63: 36 | B63: 1 | C63: 100 | D63: École K.B. Woodward
A64: 37 | D64: École Martha Currie
A65: 38 | D65: École Ocean Cliff
A66: 39 | D66: École Peace Arch
A67: 40 | D67: École Riverdale
A68: 41 | D68: École Simon Cunningham
A69: 42 | D69: École Sunrise Ridge
A70: 43 | D70: École Woodward Hill
A71: 44 | B71: 1 | C71: =B71*100 -> 100 | D71: Ellendale Elementary
A72: 45 | D72: Forsyth Road Elementary
A73: 46 | D73: George Greenaway Elementary
A74: 47 | D74: Georges Vanier Elementary
A75: 48 | D75: Goldstone Park Elementary
A76: 49 | D76: Green Timbers Elementary
A77: 50 | B77: 1 | C77: =B77*100 -> 100 | D77: H. T. Thrift Elementary
A78: 51 | D78: Hall's Prairie Elementary
A79: 52 | D79: Harold Bishop Elementary
A80: 53 | D80: Hazelgrove Elementary
A81: 54 | D81: Hillcrest Elementary
A82: 55 | D82: Hjorth Road Elementary
A83: 56 | D83: Holly Elementary
A84: 57 | B84: 1 | C84: =B84*100 -> 100 | D84: Hyland Elementary
A85: 58 | D85: J. T. Brown Elementary
A86: 59 | D86: James Ardiel Elementary
A87: 60 | D87: Janice Churchill Elementary
A88: 61 | D88: Katzie Elementary
A89: 62 | D89: Kennedy Trail Elementary
A90: 63 | D90: Kirkbride Elementary
A91: 64 | D91: Latimer Road Elementary
A92: 65 | D92: Lena Shaw Elementary
A93: 66 | D93: M. B. Sanford Elementary
A94: 67 | D94: Maple Green Elementary
A95: 68 | D95: Martha Jane Norris Elementary
A96: 69 | D96: Mary Jane Shannon Elementary
... A98: 71 | D98: Newton Elementary
A99: 72 | B99: 1 | C99: =B99*100 -> 100 | D99: North Ridge Elementary
A100: 73 | D100: Old Yale Road Elementary
A101: 74 | D101: Pacific Heights Elementary
A102: 75 | D102: Panorama Park Elementary
A103: 76 | D103: Port Kells Elementary
A104: 77 | B104: 1 | C104: =B104*100 -> 100 | D104: Prince Charles Elementary
A105: 78 | B105: 2 | C105: 200 | D105: Ray Shepherd Elementary
A106: 79 | D106: Rosemary Heights Elementary
A107: 80 | D107: Royal Heights Elementary
A108: 81 | B108: 1 | C108: =B108*100 -> 100 | D108: Semiahmoo Trail Elementary
A109: 82 | D109: Senator Reid Elementary
...

Sheet AMPL .mod file
A1: set J; | C1: # | D1: Secondary school catchment zones
A2: set L; | C2: # | D2: Elementary school catchment zones
A3: set G; | C3: # | D3: Choices of capacity for a new secondary school
A4: set H; | C4: # | D4: Choices of capacity for a new elementary school
A6: param S {J} >= 0; | C6: # | D6: Secondary students population
A7: param c {J} >= 0; | C7: # | D7: Secondary school capacity
A8: param sig {J} >= 0; | C8: # | D8: Number of 100 seats expanding for secondary
A9: param tau {L} >= 0; | C9: # | D9: Number of 100 seats expanding for elementary
A10: param phi >= 0; | C10: # | D10: Cost for Expanding 100 seats for secondary
A11: param lam >= 0; | C11: # | D11: Cost for Expanding 100 seats for elementary
A12: param gam {G} >= 0; | C12: # | D12: Capacity for a new secondary school
A13: param a {J,J} >= 0; | C13: # | D13: Adjacencies for secondary catchment zones
... A20: param Bud >=0; | C20: # | D20: Total Budget
A21: param P {j in J} = S[j]-c[j];
A22: param Q {l in L} = E[l]-d[l];
A23: param alp >= 0;
A24: param bet >=0;
A26: set I := {j in J: P[j] > 0}; | C26: # | D26: Secondary zones that have overcap
A27: set K := {l in L: Q[l] > 0}; | C27: # | D27: Elementary zones that have overcap
A29: var W {j in I} integer >= 0; | C29: # | D29: Expansion for secondary
A30: var X {l in K} integer >=0; | C30: # | D30: Expansion for elementary
A31: var Y {j in I, g in G} integer >= 0; | C31: # | D31: Locations for new secondary
A32: var Z {l in K, h in H} integer >= 0; | C32: # | D32: Locations for new elementary
A33: var U {i in I, j in I} integer >= 0; | C33: # | D33: Transfers for new secondary
A34: var V {k in K, l in K} integer >= 0; | C34: # | D34: Transfers for new elementary
A36: maximize Crowdedness:
B37: sum {i in I} 100*W[i] + 0.9*sum {i in I,j in I} U[i,j] + 0.1*sum {i in I} U[i,i] + sum {k in K} 100*X[k] + 0.9*sum {k in K,l in K} V[k,l] + 0.1*sum {k in K} V[k,k];
A39: subject to Lowerbd_Sec {i in I}:
B40: sum {j in I} U[i,j] <= P[i] - 100*W[i];
A41: subject to Lowerbd_Ele {k in K}:
B42: sum {l in K} V[k,l] <= Q[k] - 100*X[k];
A44: subject to Upperbd_Sec {i in I}:
B45: S[i] - sum {j in I} U[i,j] <= (1+alp)*(c[i] + 100*W[i]);
A46: subject to Upperbd_Ele {k in K}:
B47: E[k] - sum {l in K} V[k,l] <= (1+bet)*(d[k] + 100*X[k]);
A49: subject to Expan_Sec {i in I}:
B50: 100*W[i] <= sig[i]-c[i];
A51: subject to Expan_Ele {k in K}:
B52: 100*X[k] <= tau[k]-d[k];
A54: subject to Adjacent_Sec {i in I, j in I}:
B55: U[i,j] <= a[i,j]* sum {g in G} gam[g]*Y[j,g];
A56: subject to Transfer_Sec {j in I}:
B57: sum {i in I} U[i,j] <= sum {g in G} gam[g]*Y[j,g];
A58: subject to Focus_Sec {j in I, i in I:i<>j}:
B59: U[i,j] <= U[j,j];
A61: subject to Adjacent_Ele {k in K, l in K}:
B62: V[k,l] <= b[k,l]* sum{h in H} del[h]*Z[l,h];
A63: subject to Transfer_Ele {l in K}:
B64: sum {k in K} V[k,l] <= sum{h in H} del[h]*Z[l,h];
A65: subject to Focus_Ele {l in K, k in K:k<>l}:
B66: V[k,l] <= V[l,l];
A68: subject to Budget:
B69: sum {i in I} phi*W[i] + sum {k in K} lam*X[k] + sum {j in I, g in G} the[g]*Y[j,g] + sum {l in K,h in H} psi[h]*Z[l,h] <= Bud;

Sheet All data
A2: Secondary School | B2: Index | C2: Population 2025 | D2: Capacity | E2: Max Capacity | H2: {=TRANSPOSE(G3:G21)} -> Clayton Heights Secondary | I2: Ecole Earl Marriott | J2: Ecole Elgin Park | K2: Ecole Fraser Heights | L2: Ecole Kwantlen Park | M2: Ecole Lord Tweedsmuir | N2: Ecole Panorama Ridge | O2: Enver Creek Secondary | P2: Fleetwood Park Secondary | Q2: Frank Hurt Secondary | R2: Guildford Park Secondary | S2: Johnston Heights Secondary | T2: L. A. Matheson Secondary | U2: North Surrey Secondary | V2: Princess Margaret Secondary | W2: Queen Elizabeth Secondary | X2: Semiahmoo Secondary | Y2: Sullivan Heights Secondary | Z2: Tamanawis Secondary
A3: Clayton Heights Secondary | B3: 1 | C3: 3049 | D3: 2580 | E3: 3000 | G3: Clayton Heights Secondary | H3: 1 | I3: 0 | J3: 0 | K3: 0 | L3: 0 | M3: 1 | N3: 0 | O3: 0 | P3: 0 | Q3: 0 | R3: 0 | S3: 0 | T3: 0 | U3: 0 | V3: 0 | W3: 0 | X3: 0 | Y3: 0 | Z3: 0
A4: Ecole Earl Marriott | B4: 2 | C4: 2826 | D4: 3000 | E4: 3000 | G4: Ecole Earl Marriott | H4: 0 | I4: 1 | J4: 0 | K4: 0 | L4: 0 | M4: 0 | N4: 0 | O4: 0 | P4: 0 | Q4: 0 | R4: 0 | S4: 0 | T4: 0 | U4: 0 | V4: 0 | W4: 0 | X4: 1 | Y4: 0 | Z4: 0
A5: Ecole Elgin Park | B5: 3 | C5: 1504 | D5: 1200 | E5: 1500 | G5: Ecole Elgin Park | H5: 0 | I5: 0 | J5: 1 | K5: 0 | L5: 0 | M5: 0 | N5: 1 | O5: 0 | P5: 0 | Q5: 0 | R5: 0 | S5: 0 | T5: 0 | U5: 0 | V5: 0 | W5: 0 | X5: 1 | Y5: 1 | Z5: 0
A6: Ecole Fraser Heights | B6: 4 | C6: 2115 | D6: 1300 | E6: 1300 | G6: Ecole Fraser Heights | H6: 0 | I6: 0 | J6: 0 | K6: 1 | L6: 0 | M6: 0 | N6: 0 | O6: 0 | P6: 0 | Q6: 0 | R6: 1 | S6: 1 | T6: 0 | U6: 1 | V6: 0 | W6: 0 | X6: 0 | Y6: 0 | Z6: 0
A7: Ecole Kwantlen Park | B7: 5 | C7: 1947 | D7: 1200 | E7: 1500 | G7: Ecole Kwantlen Park | H7: 0 | I7: 0 | J7: 0 | K7: 0 | L7: 1 | M7: 0 | N7: 0 | O7: 0 | P7: 0 | Q7: 0 | R7: 1 | S7: 0 | T7: 1 | U7: 0 | V7: 0 | W7: 1 | X7: 0 | Y7: 0 | Z7: 0
A8: Ecole Lord Tweedsmuir | B8: 6 | C8: 2714 | D8: 1400 | E8: 1500 | G8: Ecole Lord Tweedsmuir | H8: 1 | I8: 0 | J8: 0 | K8: 0 | L8: 0 | M8: 1 | N8: 0 | O8: 0 | P8: 1 | Q8: 1 | R8: 0 | S8: 0 | T8: 0 | U8: 1 | V8: 0 | W8: 0 | X8: 0 | Y8: 1 | Z8: 0
A9: Ecole Panorama Ridge | B9: 7 | C9: 1771 | D9: 1525 | E9: 1525 | G9: Ecole Panorama Ridge | H9: 0 | I9: 0 | J9: 1 | K9: 0 | L9: 0 | M9: 0 | N9: 1 | O9: 0 | P9: 0 | Q9: 1 | R9: 0 | S9: 0 | T9: 0 | U9: 0 | V9: 1 | W9: 0 | X9: 0 | Y9: 1 | Z9: 1
A10: Enver Creek Secondary | B10: 8 | C10: 1771 | D10: 1400 | E10: 1500 | G10: Enver Creek Secondary | H10: 0 | I10: 0 | J10: 0 | K10: 0 | L10: 0 | M10: 0 | N10: 0 | O10: 1 | P10: 1 | Q10: 1 | R10: 1 | S10: 1 | T10: 0 | U10: 0 | V10: 0 | W10: 1 | X10: 0 | Y10: 0 | Z10: 0
A11: Fleetwood Park Secondary | B11: 9 | C11: 1477 | D11: 1200 | E11: 1500 | G11: Fleetwood Park Secondary | H11: 0 | I11: 0 | J11: 0 | K11: 0 | L11: 0 | M11: 1 | N11: 0 | O11: 1 | P11: 1 | Q11: 1 | R11: 0 | S11: 1 | T11: 0 | U11: 1 | V11: 0 | W11: 0 | X11: 0 | Y11: 0 | Z11: 0
A12: Frank Hurt Secondary | B12: 10 | C12: 3501 | D12: 1200 | E12: 1500 | F12: =C12-D12 -> 2301 | G12: Frank Hurt Secondary | H12: 0 | I12: 0 | J12: 0 | K12: 0 | L12: 0 | M12: 1 | N12: 1 | O12: 1 | P12: 1 | Q12: 1 | R12: 0 | S12: 0 | T12: 0 | U12: 0 | V12: 1 | W12: 1 | X12: 0 | Y12: 1 | Z12: 0
A13: Guildford Park Secondary | B13: 11 | C13: 2532 | D13: 1050 | E13: 1500 | G13: Guildford Park Secondary | H13: 0 | I13: 0 | J13: 0 | K13: 1 | L13: 1 | M13: 0 | N13: 0 | O13: 1 | P13: 0 | Q13: 0 | R13: 1 | S13: 1 | T13: 0 | U13: 0 | V13: 0 | W13: 1 | X13: 0 | Y13: 0 | Z13: 0
A14: Johnston Heights Secondary | B14: 12 | C14: 1866 | D14: 1450 | E14: 1500 | G14: Johnston Heights Secondary | H14: 0 | I14: 0 | J14: 0 | K14: 1 | L14: 0 | M14: 0 | N14: 0 | O14: 1 | P14: 1 | Q14: 0 | R14: 1 | S14: 1 | T14: 0 | U14: 1 | V14: 0 | W14: 0 | X14: 0 | Y14: 0 | Z14: 0
A15: L. A. Matheson Secondary | B15: 13 | C15: 2223 | D15: 1400 | E15: 1500 | G15: L. A. Matheson Secondary | H15: 0 | I15: 0 | J15: 0 | K15: 0 | L15: 1 | M15: 0 | N15: 0 | O15: 0 | P15: 0 | Q15: 0 | R15: 0 | S15: 0 | T15: 1 | U15: 0 | V15: 1 | W15: 1 | X15: 0 | Y15: 0 | Z15: 0
A16: North Surrey Secondary | B16: 14 | C16: 2961 | D16: 1500 | E16: 1500 | G16: North Surrey Secondary | H16: 0 | I16: 0 | J16: 0 | K16: 1 | L16: 0 | M16: 1 | N16: 0 | O16: 0 | P16: 1 | Q16: 0 | R16: 0 | S16: 1 | T16: 0 | U16: 1 | V16: 0 | W16: 0 | X16: 0 | Y16: 0 | Z16: 0
A17: Princess Margaret Secondary | B17: 15 | C17: 2220 | D17: 1500 | E17: 1500 | G17: Princess Margaret Secondary | H17: 0 | I17: 0 | J17: 0 | K17: 0 | L17: 0 | M17: 0 | N17: 1 | O17: 0 | P17: 0 | Q17: 1 | R17: 0 | S17: 0 | T17: 1 | U17: 0 | V17: 1 | W17: 1 | X17: 0 | Y17: 1 | Z17: 1
A18: Queen Elizabeth Secondary | B18: 16 | C18: 2539 | D18: 1400 | E18: 1500 | G18: Queen Elizabeth Secondary | H18: 0 | I18: 0 | J18: 0 | K18: 0 | L18: 1 | M18: 0 | N18: 0 | O18: 1 | P18: 0 | Q18: 1 | R18: 1 | S18: 0 | T18: 1 | U18: 0 | V18: 1 | W18: 1 | X18: 0 | Y18: 0 | Z18: 0
A19: Semiahmoo Secondary | B19: 17 | C19: 1320 | D19: 1300 | E19: 1500 | G19: Semiahmoo Secondary | H19: 0 | I19: 1 | J19: 1 | K19: 0 | L19: 0 | M19: 0 | N19: 0 | O19: 0 | P19: 0 | Q19: 0 | R19: 0 | S19: 0 | T19: 0 | U19: 0 | V19: 0 | W19: 0 | X19: 1 | Y19: 1 | Z19: 0
A20: Sullivan Heights Secondary | B20: 18 | C20: 1732 | D20: 1700 | E20: 1700 | G20: Sullivan Heights Secondary | H20: 0 | I20: 0 | J20: 1 | K20: 0 | L20: 0 | M20: 1 | N20: 1 | O20: 0 | P20: 0 | Q20: 1 | R20: 0 | S20: 0 | T20: 0 | U20: 0 | V20: 1 | W20: 0 | X20: 1 | Y20: 1 | Z20: 0
A21: Tamanawis Secondary | B21: 19 | C21: 2406 | D21: 1500 | E21: 1500 | G21: Tamanawis Secondary | H21: 0 | I21: 0 | J21: 0 | K21: 0 | L21: 0 | M21: 0 | N21: 1 | O21: 0 | P21: 0 | Q21: 0 | R21: 0 | S21: 0 | T21: 0 | U21: 0 | V21: 1 | W21: 0 | X21: 0 | Y21: 0 | Z21: 1
C22: =SUM(C3:C21) -> 42474 | D22: =SUM(D3:D21) -> 28805
A23: Elementary School | B23: Index | C23: Population 2025 | D23: Capacity | E23: Max Capacity | H23: {=TRANSPOSE(G24:G119)} -> A. H. P. Matthew Elementary | I23: A. J. McLellan Elementary | J23: Adams Road Elementary | K23: Bayridge Elementary | L23: Bear Creek Elementary | M23: Beaver Creek Elementary | N23: Berkshire Park Elementary | O23: Betty Huff Elementary | P23: Bonaccord Elementary | Q23: Bothwell Elementary | R23: Boundary Park Elementary | S23: Bridgeview Elementary | T23: Brookside Elementary | U23: Cambridge Elementary | V23: Cedar Hills Elementary | W23: Chantrell Creek Elementary | X23: Chimney Hill Elementary | Y23: Cindrich Elementary | Z23: Clayton Elementary | AA23: Coast Meridian Elementary | AB23: Colebrook Elementary | AC23: Cougar Creek Elementary | AD23: Coyote Creek Elementary | AE23: Creekside Elementary | AF23: David Brankin Elementary | AG23: Dogwood Elementary | AH23: Don Christian Elementary | AI23: Dr. F. D. Sinclair Elementary | AJ23: East Kensington Elementary | AK23: École Crescent Park | AL23: École Erma Stephenson | AM23: École Fraser Wood | AN23: École Frost Road | AO23: École Henry Bose | AP23: École Jessie Lee | AQ23: École K.B. Woodward | AR23: École Martha Currie | AS23: École Ocean Cliff | AT23: École Peace Arch | AU23: École Riverdale | AV23: École Simon Cunningham | AW23: École Sunrise Ridge | AX23: École Woodward Hill | AY23: Ellendale Elementary | AZ23: Forsyth Road Elementary | BA23: George Greenaway Elementary | BB23: Georges Vanier Elementary | BC23: Goldstone Park Elementary | BD23: Green Timbers Elementary | BE23: H. T. Thrift Elementary | BF23: Hall's Prairie Elementary | BG23: Harold Bishop Elementary | BH23: Hazelgrove Elementary | BI23: Hillcrest Elementary | BJ23: Hjorth Road Elementary | BK23: Holly Elementary | BL23: Hyland Elementary | BM23: J. T. Brown Elementary | BN23: James Ardiel Elementary | BO23: Janice Churchill Elementary | BP23: Katzie Elementary | BQ23: Kennedy Trail Elementary | BR23: Kirkbride Elementary | BS23: Latimer Road Elementary | BT23: Lena Shaw Elementary | BU23: M. B. Sanford Elementary | BV23: Maple Green Elementary | BW23: Martha Jane Norris Elementary | BX23: Mary Jane Shannon Elementary | BY23: Morgan Elementary | BZ23: Newton Elementary | CA23: North Ridge Elementary | CB23: Old Yale Road Elementary | CC23: Pacific Heights Elementary | CD23: Panorama Park Elementary | CE23: Port Kells Elementary | CF23: Prince Charles Elementary | CG23: Ray Shepherd Elementary | CH23: Rosemary Heights Elementary | CI23: Royal Heights Elementary | CJ23: Semiahmoo Trail Elementary | CK23: Senator Reid Elementary | CL23: Serpentine Heights Elementary | CM23: South Meridian Elementary | CN23: Strawberry Hill Elementary | CO23: Sullivan Elementary | CP23: Sunnyside Elementary | CQ23: Surrey Centre Elementary | CR23: T. E. Scott Elementary | CS23: W. E. Kinvig Elementary | CT23: Walnut Road Elementary | CU23: Westerman Elementary | CV23: White Rock Elementary | CW23: William F. Davidson Elementary | CX23: William Watson Elementary | CY23: Woodland Park Elementary
A24: A. H. P. Matthew Elementary | B24: 1 | C24: 640 | D24: 410 | E24: 600 | G24: A. H. P. Matthew Elementary | H24: 1 | I24: 0 | J24: 0 | K24: 0 | L24: 0 | M24: 0 | N24: 0 | O24: 1 | P24: 0 | Q24: 0 | R24: 0 | S24: 0 | T24: 0 | U24: 0 | V24: 1 | W24: 0 | X24: 0 | Y24: 1 | Z24: 0 | AA24: 0 | AB24: 0 | AC24: 0 | AD24: 0 | AE24: 0 | AF24: 0 | AG24: 0 | AH24: 0 | AI24: 0 | AJ24: 0 | AK24: 0 | AL24: 0 | AM24: 0 | AN24: 0 | AO24: 0 | AP24: 0 | AQ24: 0 | AR24: 0 | AS24: 0 | AT24: 0 | AU24: 0 | AV24: 1 | AW24: 0 | AX24: 0 | AY24: 0 | AZ24: 0 | BA24: 0 | BB24: 0 | BC24: 0 | BD24: 0 | BE24: 0 | BF24: 0 | BG24: 0 | BH24: 0 | BI24: 0 | BJ24: 0 | BK24: 0 | BL24: 0 | BM24: 0 | BN24: 0 | BO24: 0 | BP24: 0 | BQ24: 0 | BR24: 0 | BS24: 0 | BT24: 1 | BU24: 0 | BV24: 0 | BW24: 0 | BX24: 0 | BY24: 0 | BZ24: 0 | CA24: 0 | CB24: 1 | CC24: 0 | CD24: 0 | CE24: 0 | CF24: 1 | CG24: 0 | CH24: 0 | CI24: 0 | CJ24: 0 | CK24: 1 | CL24: 0 | CM24: 0 | CN24: 0 | CO24: 0 | CP24: 0 | CQ24: 0 | CR24: 0 | CS24: 0 | CT24: 0 | CU24: 0 | CV24: 0 | CW24: 0 | CX24: 0 | CY24: 0
A25: A. J. McLellan Elementary | B25: 2 | C25: 816 | D25: 505 | E25: 600 | G25: A. J. McLellan Elementary | H25: 0 | I25: 1 | J25: 0 | K25: 0 | L25: 0 | M25: 0 | N25: 0 | O25: 0 | P25: 0 | Q25: 0 | R25: 0 | S25: 0 | T25: 0 | U25: 0 | V25: 0 | W25: 0 | X25: 0 | Y25: 0 | Z25: 0 | AA25: 0 | AB25: 0 | AC25: 0 | AD25: 1 | AE25: 0 | AF25: 0 | AG25: 0 | AH25: 0 | AI25: 0 | AJ25: 0 | AK25: 0 | AL25: 0 | AM25: 0 | AN25: 0 | AO25: 0 | AP25: 0 | AQ25: 0 | AR25: 0 | AS25: 0 | AT25: 0 | AU25: 0 | AV25: 0 | AW25: 0 | AX25: 0 | AY25: 0 | AZ25: 0 | BA25: 1 | BB25: 0 | BC25: 0 | BD25: 0 | BE25: 0 | BF25: 0 | BG25: 0 | BH25: 0 | BI25: 0 | BJ25: 0 | BK25: 0 | BL25: 0 | BM25: 0 | BN25: 0 | BO25: 0 | BP25: 0 | BQ25: 0 | BR25: 0 | BS25: 0 | BT25: 0 | BU25: 0 | BV25: 0 | BW25: 0 | BX25: 0 | BY25: 0 | BZ25: 0 | CA25: 0 | CB25: 0 | CC25: 0 | CD25: 0 | CE25: 0 | CF25: 0 | CG25: 0 | CH25: 0 | CI25: 0 | CJ25: 0 | CK25: 0 | CL25: 0 | CM25: 0 | CN25: 0 | CO25: 1 | CP25: 0 | CQ25: 1 | CR25: 1 | CS25: 0 | CT25: 0 | CU25: 0 | CV25: 0 | CW25: 0 | CX25: 1 | CY25: 0
A26: Adams Road Elementary | B26: 3 | C26: 980 | D26: 530 | E26: 530 | G26: Adams Road Elementary | H26: 0 | I26: 0 | J26: 1 | K26: 0 | L26: 0 | M26: 0 | N26: 0 | O26: 0 | P26: 0 | Q26: 0 | R26: 0 | S26: 0 | T26: 0 | U26: 0 | V26: 0 | W26: 0 | X26: 0 | Y26: 0 | Z26: 1 | AA26: 1 | AB26: 0 | AC26: 0 | AD26: 0 | AE26: 0 | AF26: 0 | AG26: 0 | AH26: 1 | AI26: 0 | AJ26: 0 | AK26: 0 | AL26: 0 | AM26: 0 | AN26: 0 | AO26: 0 | AP26: 0 | AQ26: 0 | AR26: 0 | AS26: 0 | AT26: 0 | AU26: 0 | AV26: 0 | AW26: 0 | AX26: 0 | AY26: 0 | AZ26: 0 | BA26: 1 | BB26: 0 | BC26: 0 | BD26: 0 | BE26: 0 | BF26: 0 | BG26: 0 | BH26: 0 | BI26: 1 | BJ26: 0 | BK26: 0 | BL26: 0 | BM26: 0 | BN26: 0 | BO26: 0 | BP26: 0 | BQ26: 0 | BR26: 0 | BS26: 0 | BT26: 0 | BU26: 0 | BV26: 0 | BW26: 0 | BX26: 0 | BY26: 0 | BZ26: 0 | CA26: 0 | CB26: 0 | CC26: 0 | CD26: 0 | CE26: 0 | CF26: 0 | CG26: 0 | CH26: 0 | CI26: 0 | CJ26: 0 | CK26: 0 | CL26: 0 | CM26: 0 | CN26: 0 | CO26: 0 | CP26: 0 | CQ26: 0 | CR26: 0 | CS26: 0 | CT26: 0 | CU26: 0 | CV26: 0 | CW26: 0 | CX26: 1 | CY26: 0
A27: Bayridge Elementary | B27: 4 | C27: 427 | D27: 320 | E27: 600 | G27: Bayridge Elementary | H27: 0 | I27: 0 | J27: 0 | K27: 1 | L27: 0 | M27: 0 | N27: 0 | O27: 0 | P27: 0 | Q27: 0 | R27: 0 | S27: 0 | T27: 0 | U27: 0 | V27: 0 | W27: 1 | X27: 0 | Y27: 0 | Z27: 0 | AA27: 0 | AB27: 0 | AC27: 0 | AD27: 0 | AE27: 0 | AF27: 0 | AG27: 0 | AH27: 0 | AI27: 0 | AJ27: 0 | AK27: 0 | AL27: 0 | AM27: 0 | AN27: 0 | AO27: 0 | AP27: 0 | AQ27: 0 | AR27: 0 | AS27: 0 | AT27: 0 | AU27: 0 | AV27: 0 | AW27: 0 | AX27: 0 | AY27: 0 | AZ27: 0 | BA27: 0 | BB27: 0 | BC27: 0 | BD27: 0 | BE27: 1 | BF27: 0 | BG27: 0 | BH27: 0 | BI27: 0 | BJ27: 0 | BK27: 0 | BL27: 0 | BM27: 0 | BN27: 0 | BO27: 0 | BP27: 0 | BQ27: 0 | BR27: 0 | BS27: 0 | BT27: 0 | BU27: 0 | BV27: 0 | BW27: 0 | BX27: 0 | BY27: 0 | BZ27: 0 | CA27: 0 | CB27: 0 | CC27: 0 | CD27: 0 | CE27: 0 | CF27: 0 | CG27: 1 | CH27: 0 | CI27: 0 | CJ27: 1 | CK27: 0 | CL27: 0 | CM27: 0 | CN27: 0 | CO27: 0 | CP27: 0 | CQ27: 0 | CR27: 0 | CS27: 0 | CT27: 0 | CU27: 0 | CV27: 0 | CW27: 0 | CX27: 0 | CY27: 0
A28: Bear Creek Elementary | B28: 5 | C28: 1036 | D28: 590 | E28: 600 | G28: Bear Creek Elementary | H28: 0 | I28: 0 | J28: 0 | K28: 0 | L28: 1 | M28: 0 | N28: 0 | O28: 0 | P28: 0 | Q28: 0 | R28: 0 | S28: 0 | T28: 1 | U28: 0 | V28: 0 | W28: 0 | X28: 0 | Y28: 1 | Z28: 0 | AA28: 0 | AB28: 0 | AC28: 0 | AD28: 0 | AE28: 1 | AF28: 1 | AG28: 0 | AH28: 0 | AI28: 0 | AJ28: 0 | AK28: 0 | AL28: 0 | AM28: 0 | AN28: 0 | AO28: 0 | AP28: 0 | AQ28: 0 | AR28: 0 | AS28: 0 | AT28: 0 | AU28: 0 | AV28: 1 | AW28: 0 | AX28: 0 | AY28: 0 | AZ28: 0 | BA28: 0 | BB28: 1 | BC28: 0 | BD28: 0 | BE28: 0 | BF28: 0 | BG28: 0 | BH28: 0 | BI28: 0 | BJ28: 0 | BK28: 0 | BL28: 0 | BM28: 0 | BN28: 0 | BO28: 0 | BP28: 0 | BQ28: 0 | BR28: 0 | BS28: 0 | BT28: 0 | BU28: 1 | BV28: 0 | BW28: 0 | BX28: 0 | BY28: 0 | BZ28: 1 | CA28: 0 | CB28: 0 | CC28: 0 | CD28: 0 | CE28: 0 | CF28: 0 | CG28: 0 | CH28: 0 | CI28: 0 | CJ28: 0 | CK28: 0 | CL28: 0 | CM28: 0 | CN28: 0 | CO28: 0 | CP28: 0 | CQ28: 0 | CR28: 0 | CS28: 1 | CT28: 0 | CU28: 0 | CV28: 0 | CW28: 0 | CX28: 0 | CY28: 0
A29: Beaver Creek Elementary | B29: 6 | C29: 1697 | D29: 515 | E29: 600 | G29: Beaver Creek Elementary | H29: 0 | I29: 0 | J29: 0 | K29: 0 | L29: 0 | M29: 1 | N29: 0 | O29: 0 | P29: 0 | Q29: 0 | R29: 1 | S29: 0 | T29: 0 | U29: 1 | V29: 0 | W29: 0 | X29: 0 | Y29: 0 | Z29: 0 | AA29: 0 | AB29: 0 | AC29: 1 | AD29: 0 | AE29: 0 | AF29: 0 | AG29: 0 | AH29: 0 | AI29: 0 | AJ29: 0 | AK29: 0 | AL29: 0 | AM29: 0 | AN29: 0 | AO29: 0 | AP29: 0 | AQ29: 0 | AR29: 0 | AS29: 0 | AT29: 0 | AU29: 0 | AV29: 0 | AW29: 0 | AX29: 0 | AY29: 0 | AZ29: 0 | BA29: 0 | BB29: 0 | BC29: 0 | BD29: 0 | BE29: 0 | BF29: 0 | BG29: 0 | BH29: 0 | BI29: 0 | BJ29: 0 | BK29: 0 | BL29: 0 | BM29: 1 | BN29: 0 | BO29: 0 | BP29: 0 | BQ29: 0 | BR29: 0 | BS29: 0 | BT29: 0 | BU29: 0 | BV29: 0 | BW29: 1 | BX29: 0 | BY29: 0 | BZ29: 0 | CA29: 0 | CB29: 0 | CC29: 0 | CD29: 0 | CE29: 0 | CF29: 0 | CG29: 0 | CH29: 0 | CI29: 0 | CJ29: 0 | CK29: 0 | CL29: 0 | CM29: 0 | CN29: 0 | CO29: 0 | CP29: 0 | CQ29: 0 | CR29: 0 | CS29: 0 | CT29: 0 | CU29: 0 | CV29: 0 | CW29: 0 | CX29: 0 | CY29: 0
A30: Berkshire Park Elementary | B30: 7 | C30: 503 | D30: 540 | E30: 600 | G30: Berkshire Park Elementary | H30: 0 | I30: 0 | J30: 0 | K30: 0 | L30: 0 | M30: 0 | N30: 1 | O30: 0 | P30: 1 | Q30: 0 | R30: 0 | S30: 0 | T30: 0 | U30: 0 | V30: 0 | W30: 0 | X30: 0 | Y30: 0 | Z30: 0 | AA30: 0 | AB30: 0 | AC30: 0 | AD30: 1 | AE30: 0 | AF30: 0 | AG30: 0 | AH30: 0 | AI30: 0 | AJ30: 0 | AK30: 0 | AL30: 0 | AM30: 0 | AN30: 0 | AO30: 0 | AP30: 0 | AQ30: 0 | AR30: 0 | AS30: 0 | AT30: 0 | AU30: 0 | AV30: 0 | AW30: 0 | AX30: 0 | AY30: 0 | AZ30: 0 | BA30: 0 | BB30: 0 | BC30: 0 | BD30: 1 | BE30: 0 | BF30: 0 | BG30: 0 | BH30: 0 | BI30: 0 | BJ30: 0 | BK30: 0 | BL30: 0 | BM30: 0 | BN30: 0 | BO30: 0 | BP30: 0 | BQ30: 0 | BR30: 0 | BS30: 0 | BT30: 0 | BU30: 0 | BV30: 0 | BW30: 0 | BX30: 0 | BY30: 0 | BZ30: 0 | CA30: 0 | CB30: 0 | CC30: 0 | CD30: 0 | CE30: 0 | CF30: 0 | CG30: 0 | CH30: 0 | CI30: 0 | CJ30: 0 | CK30: 0 | CL30: 0 | CM30: 0 | CN30: 0 | CO30: 0 | CP30: 0 | CQ30: 0 | CR30: 0 | CS30: 0 | CT30: 1 | CU30: 0 | CV30: 0 | CW30: 1 | CX30: 0 | CY30: 1
A31: Betty Huff Elementary | B31: 8 | C31: 664 | D31: 540 | E31: 600 | G31: Betty Huff Elementary | H31: 1 | I31: 0 | J31: 0 | K31: 0 | L31: 0 | M31: 0 | N31: 0 | O31: 1 | P31: 0 | Q31: 0 | R31: 0 | S31: 0 | T31: 0 | U31: 0 | V31: 1 | W31: 0 | X31: 0 | Y31: 1 | Z31: 0 | AA31: 0 | AB31: 0 | AC31: 0 | AD31: 0 | AE31: 0 | AF31: 1 | AG31: 0 | AH31: 0 | AI31: 0 | AJ31: 0 | AK31: 0 | AL31: 0 | AM31: 0 | AN31: 0 | AO31: 0 | AP31: 0 | AQ31: 0 | AR31: 0 | AS31: 0 | AT31: 0 | AU31: 0 | AV31: 0 | AW31: 0 | AX31: 0 | AY31: 0 | AZ31: 0 | BA31: 0 | BB31: 0 | BC31: 0 | BD31: 0 | BE31: 0 | BF31: 0 | BG31: 0 | BH31: 0 | BI31: 0 | BJ31: 0 | BK31: 0 | BL31: 0 | BM31: 0 | BN31: 0 | BO31: 0 | BP31: 0 | BQ31: 0 | BR31: 0 | BS31: 0 | BT31: 0 | BU31: 0 | BV31: 0 | BW31: 0 | BX31: 0 | BY31: 0 | BZ31: 0 | CA31: 0 | CB31: 0 | CC31: 0 | CD31: 0 | CE31: 0 | CF31: 0 | CG31: 0 | CH31: 0 | CI31: 0 | CJ31: 0 | CK31: 1 | CL31: 0 | CM31: 0 | CN31: 0 | CO31: 0 | CP31: 0 | CQ31: 0 | CR31: 0 | CS31: 0 | CT31: 0 | CU31: 0 | CV31: 0 | CW31: 0 | CX31: 0 | CY31: 0
A32: Bonaccord Elementary | B32: 9 | C32: 694 | D32: 590 | E32: 600 | G32: Bonaccord Elementary | H32: 0 | I32: 0 | J32: 0 | K32: 0 | L32: 0 | M32: 0 | N32: 1 | O32: 0 | P32: 1 | Q32: 0 | R32: 0 | S32: 0 | T32: 0 | U32: 0 | V32: 0 | W32: 0 | X32: 0 | Y32: 0 | Z32: 0 | AA32: 0 | AB32: 0 | AC32: 0 | AD32: 0 | AE32: 0 | AF32: 0 | AG32: 0 | AH32: 0 | AI32: 0 | AJ32: 0 | AK32: 0 | AL32: 0 | AM32: 0 | AN32: 0 | AO32: 0 | AP32: 0 | AQ32: 0 | AR32: 0 | AS32: 0 | AT32: 0 | AU32: 0 | AV32: 0 | AW32: 0 | AX32: 0 | AY32: 0 | AZ32: 0 | BA32: 0 | BB32: 0 | BC32: 0 | BD32: 1 | BE32: 0 | BF32: 0 | BG32: 1 | BH32: 0 | BI32: 0 | BJ32: 1 | BK32: 0 | BL32: 0 | BM32: 0 | BN32: 0 | BO32: 0 | BP32: 0 | BQ32: 0 | BR32: 0 | BS32: 0 | BT32: 1 | BU32: 0 | BV32: 0 | BW32: 0 | BX32: 0 | BY32: 0 | BZ32: 0 | CA32: 0 | CB32: 0 | CC32: 0 | CD32: 0 | CE32: 0 | CF32: 0 | CG32: 0 | CH32: 0 | CI32: 0 | CJ32: 0 | CK32: 0 | CL32: 0 | CM32: 0 | CN32: 0 | CO32: 0 | CP32: 0 | CQ32: 0 | CR32: 0 | CS32: 0 | CT32: 0 | CU32: 0 | CV32: 0 | CW32: 1 | CX32: 0 | CY32: 0
A33: Bothwell Elementary | B33: 10 | C33: 484 | D33: 315 | E33: 600 | G33: Bothwell Elementary | H33: 0 | I33: 0 | J33: 0 | K33: 0 | L33: 0 | M33: 0 | N33: 0 | O33: 0 | P33: 0 | Q33: 1 | R33: 0 | S33: 0 | T33: 0 | U33: 0 | V33: 0 | W33: 0 | X33: 0 | Y33: 0 | Z33: 0 | AA33: 0 | AB33: 0 | AC33: 0 | AD33: 0 | AE33: 0 | AF33: 0 | AG33: 0 | AH33: 0 | AI33: 0 | AJ33: 0 | AK33: 0 | AL33: 0 | AM33: 1 | AN33: 0 | AO33: 0 | AP33: 0 | AQ33: 0 | AR33: 0 | AS33: 0 | AT33: 0 | AU33: 0 | AV33: 0 | AW33: 0 | AX33: 0 | AY33: 0 | AZ33: 0 | BA33: 0 | BB33: 0 | BC33: 0 | BD33: 0 | BE33: 0 | BF33: 0 | BG33: 0 | BH33: 0 | BI33: 0 | BJ33: 0 | BK33: 0 | BL33: 0 | BM33: 0 | BN33: 0 | BO33: 0 | BP33: 0 | BQ33: 0 | BR33: 0 | BS33: 0 | BT33: 0 | BU33: 0 | BV33: 0 | BW33: 0 | BX33: 0 | BY33: 0 | BZ33: 0 | CA33: 0 | CB33: 0 | CC33: 0 | CD33: 0 | CE33: 1 | CF33: 0 | CG33: 0 | CH33: 0 | CI33: 0 | CJ33: 0 | CK33: 0 | CL33: 1 | CM33: 0 | CN33: 0 | CO33: 0 | CP33: 0 | CQ33: 0 | CR33: 0 | CS33: 0 | CT33: 0 | CU33: 0 | CV33: 0 | CW33: 0 | CX33: 0 | CY33: 0
A34: Boundary Park Elementary | B34: 11 | C34: 341 | D34: 340 | E34: 600 | G34: Boundary Park Elementary | H34: 0 | I34: 0 | J34: 0 | K34: 0 | L34: 0 | M34: 1 | N34: 0 | O34: 0 | P34: 0 | Q34: 0 | R34: 1 | S34: 0 | T34: 0 | U34: 0 | V34: 0 | W34: 0 | X34: 0 | Y34: 0 | Z34: 0 | AA34: 0 | AB34: 1 | AC34: 0 | AD34: 0 | AE34: 0 | AF34: 0 | AG34: 0 | AH34: 0 | AI34: 0 | AJ34: 0 | AK34: 0 | AL34: 0 | AM34: 0 | AN34: 0 | AO34: 0 | AP34: 0 | AQ34: 0 | AR34: 0 | AS34: 0 | AT34: 0 | AU34: 0 | AV34: 0 | AW34: 0 | AX34: 0 | AY34: 0 | AZ34: 0 | BA34: 0 | BB34: 0 | BC34: 0 | BD34: 0 | BE34: 0 | BF34: 0 | BG34: 0 | BH34: 0 | BI34: 0 | BJ34: 0 | BK34: 0 | BL34: 0 | BM34: 1 | BN34: 0 | BO34: 0 | BP34: 0 | BQ34: 0 | BR34: 0 | BS34: 0 | BT34: 0 | BU34: 0 | BV34: 0 | BW34: 0 | BX34: 0 | BY34: 0 | BZ34: 0 | CA34: 0 | CB34: 0 | CC34: 0 | CD34: 0 | CE34: 0 | CF34: 0 | CG34: 0 | CH34: 0 | CI34: 0 | CJ34: 0 | CK34: 0 | CL34: 0 | CM34: 0 | CN34: 0 | CO34: 0 | CP34: 0 | CQ34: 0 | CR34: 0 | CS34: 0 | CT34: 0 | CU34: 0 | CV34: 0 | CW34: 0 | CX34: 0 | CY34: 0
A35: Bridgeview Elementary | B35: 12 | C35: 277 | D35: 220 | E35: 600 | G35: Bridgeview Elementary | H35: 0 | I35: 0 | J35: 0 | K35: 0 | L35: 0 | M35: 0 | N35: 0 | O35: 0 | P35: 0 | Q35: 0 | R35: 0 | S35: 1 | T35: 0 | U35: 0 | V35: 0 | W35: 0 | X35: 0 | Y35: 0 | Z35: 0 | AA35: 0 | AB35: 0 | AC35: 0 | AD35: 0 | AE35: 0 | AF35: 0 | AG35: 0 | AH35: 0 | AI35: 0 | AJ35: 0 | AK35: 0 | AL35: 0 | AM35: 0 | AN35: 0 | AO35: 0 | AP35: 0 | AQ35: 1 | AR35: 0 | AS35: 0 | AT35: 0 | AU35: 0 | AV35: 0 | AW35: 0 | AX35: 0 | AY35: 0 | AZ35: 0 | BA35: 0 | BB35: 0 | BC35: 0 | BD35: 0 | BE35: 0 | BF35: 0 | BG35: 0 | BH35: 0 | BI35: 0 | BJ35: 0 | BK35: 0 | BL35: 0 | BM35: 0 | BN35: 1 | BO35: 0 | BP35: 0 | BQ35: 0 | BR35: 0 | BS35: 0 | BT35: 0 | BU35: 0 | BV35: 0 | BW35: 0 | BX35: 0 | BY35: 0 | BZ35: 0 | CA35: 0 | CB35: 0 | CC35: 0 | CD35: 0 | CE35: 0 | CF35: 1 | CG35: 0 | CH35: 0 | CI35: 0 | CJ35: 0 | CK35: 0 | CL35: 0 | CM35: 0 | CN35: 0 | CO35: 0 | CP35: 0 | CQ35: 0 | CR35: 0 | CS35: 0 | CT35: 0 | CU35: 0 | CV35: 0 | CW35: 0 | CX35: 0 | CY35: 0
... A119: Woodland Park Elementary | B119: 96 | C119: 826 | D119: 490 | E119: 600 | G119: Woodland Park Elementary | H119: 0 | I119: 0 | J119: 0 | K119: 0 | L119: 0 | M119: 0 | N119: 1 | O119: 0 | P119: 0 | Q119: 0 | R119: 0 | S119: 0 | T119: 0 | U119: 0 | V119: 0 | W119: 0 | X119: 0 | Y119: 0 | Z119: 0 | AA119: 0 | AB119: 0 | AC119: 0 | AD119: 1 | AE119: 0 | AF119: 0 | AG119: 0 | AH119: 0 | AI119: 0 | AJ119: 0 | AK119: 0 | AL119: 0 | AM119: 0 | AN119: 1 | AO119: 0 | AP119: 0 | AQ119: 0 | AR119: 0 | AS119: 0 | AT119: 0 | AU119: 0 | AV119: 0 | AW119: 0 | AX119: 0 | AY119: 0 | AZ119: 0 | BA119: 0 | BB119: 0 | BC119: 0 | BD119: 0 | BE119: 0 | BF119: 0 | BG119: 0 | BH119: 0 | BI119: 0 | BJ119: 0 | BK119: 0 | BL119: 0 | BM119: 0 | BN119: 0 | BO119: 0 | BP119: 0 | BQ119: 0 | BR119: 0 | BS119: 0 | BT119: 0 | BU119: 0 | BV119: 0 | BW119: 0 | BX119: 0 | BY119: 0 | BZ119: 0 | CA119: 0 | CB119: 0 | CC119: 0 | CD119: 0 | CE119: 0 | CF119: 0 | CG119: 0 | CH119: 0 | CI119: 0 | CJ119: 0 | CK119: 0 | CL119: 1 | CM119: 0 | CN119: 0 | CO119: 0 | CP119: 0 | CQ119: 0 | CR119: 0 | CS119: 0 | CT119: 1 | CU119: 0 | CV119: 0 | CW119: 1 | CX119: 0 | CY119: 1
D120: =SUM(D24:D119) -> 49264
B121: tract | C121: proportion | D121: population | E121: tract | F121: proportion | G121: population | H121: tract | I121: proportion | J121: population | K121: tract | L121: proportion | M121: population
A122: A. H. P. Matthew Elementary | B122: 191.03 | C122: 0.5 | D122: 333 | E122: 191.04 | F122: 0.5 | G122: 307 | J122: 0 | M122: 0
A123: A. J. McLellan Elementary | B123: 182.02 | C123: 0.5 | D123: 816 | G123: 0 | J123: 0 | M123: 0
A124: Adams Road Elementary | B124: 183.05 | C124: 0.5 | D124: 980 | G124: 0 | J124: 0 | M124: 0
A125: Bayridge Elementary | B125: 181.1 | C125: 0.5 | D125: 167 | E125: 170.04 | F125: 0.75 | G125: 260 | J125: 0 | M125: 0
A126: Bear Creek Elementary | B126: 184.02 | C126: 1 | D126: 869 | E126: 184.16 | F126: 0.25 | G126: 167 | J126: 0 | M126: 0
A127: Beaver Creek Elementary | B127: 185.19 | C127: 1 | D127: 874 | E127: 185.2 | F127: 1 | G127: 823 | J127: 0 | M127: 0
A128: Berkshire Park Elementary | B128: 187.12 | C128: 1 | D128: 503 | G128: 0 | J128: 0 | M128: 0
A129: Betty Huff Elementary | B129: 186.05 | C129: 0.5 | D129: 527 | E129: 186.06 | F129: 0.25 | G129: 137 | J129: 0 | M129: 0
A130: Bonaccord Elementary | B130: 187.03 | C130: 0.25 | D130: 224 | E130: 189.05 | F130: 0.667 | G130: 470 | J130: 0 | M130: 0
A131: Bothwell Elementary | B131: 188.05 | C131: 1 | D131: 332 | E131: 188.06 | F131: 0.8 | G131: 152 | J131: 0 | M131: 0
A132: Boundary Park Elementary | B132: 185.17 | C132: 1 | D132: 341 | G132: 0 | J132: 0 | M132: 0
A133: Bridgeview Elementary | B133: 192 | C133: 0.667 | D133: 277 | G133: 0 | J133: 0 | M133: 0
A134: Brookside Elementary | B134: 184.16 | C134: 0.15 | D134: 100 | E134: 184.15 | F134: 1 | G134: 347 | H134: 184.09 | I134: 0.5 | J134: 291 | M134: 0
A135: Cambridge Elementary | B135: 184.14 | C135: 0.8 | D135: 1276 | E135: 184.13 | F135: 0.2 | G135: 132 | J135: 0 | M135: 0
A136: Cedar Hills Elementary | B136: 186.01 | C136: 0.25 | D136: 202 | E136: 186.02 | F136: 0.25 | G136: 163 | J136: 0 | M136: 0
A137: Chantrell Creek Elementary | B137: 181.12 | C137: 0.5 | D137: 156 | E137: 181.03 | F137: 0.5 | G137: 244 | J137: 0 | M137: 0
A138: Chimney Hill Elementary | B138: 184.11 | C138: 1 | D138: 1598 | G138: 0 | J138: 0 | M138: 0
A139: Cindrich Elementary | B139: 186.08 | C139: 0.5 | D139: 448 | E139: 186.07 | F139: 0.5 | G139: 403 | J139: 0 | M139: 0
A140: Clayton Elementary | B140: 183.09 | C140: 0.5 | D140: 1187 | G140: 0 | J140: 0 | M140: 0
A141: Coast Meridian Elementary | B141: 182.05 | C141: 1 | D141: 1010 | G141: 0 | J141: 0 | M141: 0
A142: Colebrook Elementary | B142: 185.18 | C142: 0.333 | D142: 184 | E142: 185.08 | F142: 1 | G142: 147 | H142: 185.07 | I142: 0.333 | J142: 459 | M142: 0
A143: Cougar Creek Elementary | B143: 185.21 | C143: 1 | D143: 466 | E143: 185.22 | F143: 1 | G143: 494 | J143: 0 | M143: 0
A144: Coyote Creek Elementary | B144: 187.13 | C144: 1 | D144: 262 | E144: 182.03 | F144: 0.4 | G144: 144 | J144: 0 | M144: 0
A145: Creekside Elementary | B145: 187.05 | C145: 0.5 | D145: 481 | G145: 0 | J145: 0 | M145: 0
A146: David Brankin Elementary | B146: 186.06 | C146: 0.25 | D146: 137 | E146: 185.09 | F146: 0.333 | G146: 182 | H146: 186.07 | I146: 0.5 | J146: 403 | K146: 185.15 | L146: 0.333 | M146: 90
A147: Dogwood Elementary | B147: 188.01 | C147: 1 | D147: 436 | E147: 188.02 | F147: 0.75 | G147: 311 | J147: 0 | M147: 0
A148: Don Christian Elementary | B148: 183.03 | C148: 0.5 | D148: 287 | E148: 183.07 | F148: 0.2 | G148: 129 | J148: 0 | M148: 0
A149: Dr. F. D. Sinclair Elementary | B149: 185.16 | C149: 0.5 | D149: 332 | E149: 185.1 | F149: 0.5 | G149: 423 | J149: 0 | M149: 0
A150: East Kensington Elementary | B150: 180.03 | C150: 0.25 | D150: 247 | G150: 0 | J150: 0 | M150: 0
A151: École Crescent Park | B151: 181.03 | C151: 0.5 | D151: 244 | G151: 0 | J151: 0 | M151: 0
A152: École Erma Stephenson | B152: 188.02 | C152: 0.25 | D152: 104 | E152: 188.08 | F152: 0.5 | G152: 303 | H152: 188.07 | I152: 0.25 | J152: 119 | M152: 0
A153: École Fraser Wood | B153: 188.07 | C153: 0.75 | D153: 356 | E153: 188.08 | F153: 0.5 | G153: 303 | J153: 0 | M153: 0
A154: École Frost Road | B154: 187.11 | C154: 0.667 | D154: 674 | E154: 187.07 | F154: 1 | G154: 247 | J154: 0 | M154: 0
A155: École Henry Bose | B155: 185.12 | C155: 0.5 | D155: 433 | E155: 185.05 | F155: 0.2 | G155: 161 | J155: 0 | M155: 0
A156: École Jessie Lee | B156: 181.14 | C156: 0.5 | D156: 196 | E156: 181.05 | F156: 1 | G156: 524 | J156: 0 | M156: 0
A157: École K.B. Woodward | B157: 191.05 | C157: 1 | D157: 400 | E157: 191.07 | F157: 1 | G157: 311 | H157: 191.06 | I157: 0.5 | J157: 95 | M157: 0
A158: École Martha Currie | B158: 183.03 | C158: 0.5 | D158: 287 | E158: 183.07 | F158: 0.1 | G158: 65 | H158: 182.01 | I158: 0.25 | J158: 163 | M158: 0
A159: École Ocean Cliff | B159: 181.07 | C159: 1 | D159: 336 | G159: 0 | J159: 0 | M159: 0
A160: École Peace Arch | B160: 170.07 | C160: 0.5 | D160: 167 | E160: 170.08 | F160: 0.5 | G160: 102 | J160: 0 | M160: 0
A161: École Riverdale | B161: 189.03 | C161: 0.75 | D161: 280 | G161: 0 | J161: 0 | M161: 0
A162: École Simon Cunningham | B162: 187.04 | C162: 1 | D162: 186 | E162: 187.05 | F162: 0.25 | G162: 240 | H162: 190.01 | I162: 0.25 | J162: 204 | M162: 0
A163: École Sunrise Ridge | B163: 182.01 | C163: 0.25 | D163: 163 | E163: 183.07 | F163: 0.3 | G163: 194 | J163: 0 | M163: 0
A164: École Woodward Hill | B164: 184.13 | C164: 0.3 | D164: 198 | E164: 184.12 | F164: 0.3 | G164: 310 | J164: 0 | M164: 0
A165: Ellendale Elementary | B165: 190.04 | C165: 0.3 | D165: 225 | E165: 189.03 | F165: 0.25 | G165: 93 | J165: 0 | M165: 0
A166: Forsyth Road Elementary | B166: 191.06 | C166: 0.5 | D166: 95 | E166: 190.05 | F166: 1 | G166: 202 | H166: 190.03 | I166: 0.333 | J166: 267 | M166: 0
A167: George Greenaway Elementary | B167: 183.01 | C167: 1 | D167: 771 | G167: 0 | J167: 0 | M167: 0
A168: Georges Vanier Elementary | B168: 184.06 | C168: 0.333 | D168: 716 | E168: 184.07 | F168: 1 | G168: 562 | J168: 0 | M168: 0
A169: Goldstone Park Elementary | B169: 184.12 | C169: 0.5 | D169: 517 | E169: 184.13 | F169: 0.1 | G169: 66 | H169: 184.14 | I169: 0.2 | J169: 319 | M169: 0
A170: Green Timbers Elementary | B170: 187.03 | C170: 0.5 | D170: 447 | E170: 187.05 | F170: 0.25 | G170: 240 | J170: 0 | M170: 0
A171: H. T. Thrift Elementary | B171: 170.03 | C171: 0.25 | D171: 21 | E171: 170.04 | F171: 0.25 | G171: 87 | H171: 181.11 | I171: 1 | J171: 226 | K171: 181.1 | L171: 0.5 | M171: 167
A172: Hall's Prairie Elementary | B172: 180.03 | C172: 0.25 | D172: 247 | G172: 0 | J172: 0 | M172: 0
A173: Harold Bishop Elementary | B173: 189.07 | C173: 1 | D173: 393 | E173: 189.1 | F173: 0.5 | G173: 452 | H173: 189.09 | I173: 0.5 | J173: 222 | M173: 0
A174: Hazelgrove Elementary | B174: 183.09 | C174: 0.5 | D174: 1187 | G174: 0 | J174: 0 | M174: 0
A175: Hillcrest Elementary | B175: 183.05 | C175: 0.5 | D175: 980 | G175: 0 | J175: 0 | M175: 0
A176: Hjorth Road Elementary | B176: 189.05 | C176: 0.333 | D176: 234 | E176: 190.03 | F176: 0.2 | G176: 161 | J176: 0 | M176: 0
A177: Holly Elementary | B177: 189.08 | C177: 1 | D177: 826 | G177: 0 | J177: 0 | M177: 0
A178: Hyland Elementary | B178: 184.08 | C178: 1 | D178: 872 | G178: 0 | J178: 0 | M178: 0
A179: J. T. Brown Elementary | B179: 185.18 | C179: 0.667 | D179: 370 | G179: 0 | J179: 0 | M179: 0
A180: James Ardiel Elementary | B180: 190.04 | C180: 0.6 | D180: 450 | G180: 0 | J180: 0 | M180: 0
A181: Janice Churchill Elementary | B181: 184.1 | C181: 0.5 | D181: 389 | G181: 0 | J181: 0 | M181: 0
A182: Katzie Elementary | B182: 183.08 | C182: 1 | D182: 1038 | G182: 0 | J182: 0 | M182: 0
A183: Kennedy Trail Elementary | B183: 185.09 | C183: 0.667 | D183: 402 | G183: 0 | J183: 0 | M183: 0
A184: Kirkbride Elementary | B184: 186.05 | C184: 0.5 | D184: 527 | E184: 186.06 | F184: 0.5 | G184: 273 | J184: 0 | M184: 0
...

Sheet 2025
A1: Census \ Age | B1: 0-4 | C1: 42864 | D1: 43022 | E1: 15-19 | F1: 15-17 | G1: Elementary | H1: Secondary | M1: 0-4 | N1: 42864 | O1: 43022 | P1: 15-19 | Q1: Elem | R1: Sec
A2: 9330192 | B2: 227 | C2: 282 | D2: 216 | E2: 309 | F2: 185 | G2: 412 | H2: 271 | M2: 225 | N2: 268 | O2: 245 | P2: 300 | Q2: =ROUND(N2+O2*0.6,0) -> 415 | R2: =ROUND(O2*0.4+P2*0.6,0) -> 278
A3: 9330186 | B3: 472 | C3: 378 | D3: 329 | E3: 592 | F3: 355 | G3: 575 | H3: 487 | M3: 528 | N3: 501 | O3: 513 | P3: 573 | Q3: =ROUND(N3+O3*0.6,0) -> 809 | R3: =ROUND(O3*0.4+P3*0.6,0) -> 549
A4: 186.02 | B4: 566 | C4: 268 | D4: 23 | E4: 601 | F4: 361 | G4: 282 | H4: 370 | M4: 411 | N4: 406 | O4: 412 | P4: 453 | Q4: =ROUND(N4+O4*0.6,0) -> 653 | R4: =ROUND(O4*0.4+P4*0.6,0) -> 437
A5: 186.05 | B5: 507 | C5: 558 | D5: 809 | E5: 799 | F5: 479 | G5: 1043 | H5: 803 | M5: 571 | N5: 647 | O5: 677 | P5: 665 | Q5: =ROUND(N5+O5*0.6,0) -> 1053 | R5: =ROUND(O5*0.4+P5*0.6,0) -> 670
A6: 186.06 | B6: 91 | C6: 200 | D6: 465 | E6: 378 | F6: 227 | G6: 479 | H6: 413 | M6: 352 | N6: 340 | O6: 344 | P6: 299 | Q6: =ROUND(N6+O6*0.6,0) -> 546 | R6: =ROUND(O6*0.4+P6*0.6,0) -> 317
A7: 185.09 | B7: 546 | C7: 295 | D7: 383 | E7: 366 | F7: 220 | G7: 525 | H7: 373 | M7: 475 | N7: 373 | O7: 381 | P7: 339 | Q7: =ROUND(N7+O7*0.6,0) -> 602 | R7: =ROUND(O7*0.4+P7*0.6,0) -> 356
A8: 185.11 | B8: 498 | C8: 679 | D8: 622 | E8: 574 | F8: 344 | G8: 1052 | H8: 593 | M8: 693 | N8: 718 | O8: 642 | P8: 554 | Q8: =ROUND(N8+O8*0.6,0) -> 1103 | R8: =ROUND(O8*0.4+P8*0.6,0) -> 589
A9: 185.1 | B9: 52 | C9: 195 | D9: 272 | E9: 549 | F9: 329 | G9: 358 | H9: 438 | M9: 554 | N9: 556 | O9: 482 | P9: 473 | Q9: =ROUND(N9+O9*0.6,0) -> 845 | R9: =ROUND(O9*0.4+P9*0.6,0) -> 477
A10: 185.21 | B10: 441 | C10: 403 | D10: 245 | E10: 248 | F10: 149 | G10: 550 | H10: 247 | M10: 270 | N10: 287 | O10: 299 | P10: 264 | Q10: =ROUND(N10+O10*0.6,0) -> 466 | R10: =ROUND(O10*0.4+P10*0.6,0) -> 278
A11: 185.22 | B11: 383 | C11: 310 | D11: 288 | E11: 324 | F11: 194 | G11: 483 | H11: 309 | M11: 375 | N11: 320 | O11: 290 | P11: 310 | Q11: =ROUND(N11+O11*0.6,0) -> 494 | R11: =ROUND(O11*0.4+P11*0.6,0) -> 302
A12: 185.17 | B12: 199 | C12: 138 | D12: 172 | E12: 258 | F12: 155 | G12: 241 | H12: 224 | M12: 218 | N12: 202 | O12: 232 | P12: 291 | Q12: =ROUND(N12+O12*0.6,0) -> 341 | R12: =ROUND(O12*0.4+P12*0.6,0) -> 267
A13: 185.18 | B13: 237 | C13: 313 | D13: 357 | E13: 383 | F13: 230 | G13: 527 | H13: 373 | M13: 334 | N13: 339 | O13: 359 | P13: 403 | Q13: =ROUND(N13+O13*0.6,0) -> 554 | R13: =ROUND(O13*0.4+P13*0.6,0) -> 385
... A33: 187.04 | B33: 110 | C33: 113 | D33: 120 | E33: 108 | F33: 65 | G33: 185 | H33: 113 | M33: 109 | N33: 113 | O33: 121 | P33: 108 | Q33: =ROUND(N33+O33*0.6,0) -> 186 | R33: =ROUND(O33*0.4+P33*0.6,0) -> 113
A34: 187.05 | B34: 633 | C34: 526 | D34: 394 | E34: 672 | F34: 403 | G34: 762 | H34: 561 | I34: =H34*0.75 -> 420.75 | M34: 698 | N34: 612 | O34: 582 | P34: 573 | Q34: =ROUND(N34+O34*0.6,0) -> 961 | R34: =ROUND(O34*0.4+P34*0.6,0) -> 577
A35: 184.02 | B35: 676 | C35: 691 | D35: 395 | E35: 515 | F35: 309 | G35: 928 | H35: 467 | M35: 565 | N35: 570 | O35: 499 | P35: 535 | Q35: =ROUND(N35+O35*0.6,0) -> 869 | R35: =ROUND(O35*0.4+P35*0.6,0) -> 521
A36: 184.15 | B36: 142 | C36: 122 | D36: 191 | E36: 334 | F36: 200 | G36: 237 | H36: 276 | M36: 186 | N36: 192 | O36: 259 | P36: 336 | Q36: =ROUND(N36+O36*0.6,0) -> 347 | R36: =ROUND(O36*0.4+P36*0.6,0) -> 305
A37: 184.16 | B37: 419 | C37: 457 | D37: 322 | E37: 205 | F37: 123 | G37: 650 | H37: 252 | M37: 360 | N37: 399 | O37: 447 | P37: 463 | Q37: =ROUND(N37+O37*0.6,0) -> 667 | R37: =ROUND(O37*0.4+P37*0.6,0) -> 457
A38: 184.07 | B38: 354 | C38: 246 | D38: 26 | E38: 210 | F38: 126 | G38: 262 | H38: 136 | M38: 341 | N38: 339 | O38: 372 | P38: 350 | Q38: =ROUND(N38+O38*0.6,0) -> 562 | R38: =ROUND(O38*0.4+P38*0.6,0) -> 359
A39: 184.08 | B39: 510 | C39: 450 | D39: 521 | E39: 560 | F39: 336 | G39: 763 | H39: 544 | M39: 480 | N39: 516 | O39: 593 | P39: 555 | Q39: =ROUND(N39+O39*0.6,0) -> 872 | R39: =ROUND(O39*0.4+P39*0.6,0) -> 570
A40: 184.06 | B40: 1395 | C40: 1446 | D40: 1096 | E40: 1109 | F40: 665 | G40: 2104 | H40: 1103 | M40: 1479 | N40: 1408 | O40: 1235 | P40: 1086 | Q40: =ROUND(N40+O40*0.6,0) -> 2149 | R40: =ROUND(O40*0.4+P40*0.6,0) -> 1146
A41: 184.12 | B41: 865 | C41: 1032 | D41: 747 | E41: 786 | F41: 472 | G41: 1480 | H41: 771 | M41: 936 | N41: 633 | O41: 669 | P41: 676 | Q41: =ROUND(N41+O41*0.6,0) -> 1034 | R41: =ROUND(O41*0.4+P41*0.6,0) -> 673
A42: 184.13 | B42: 473 | C42: 193 | D42: 225 | E42: 429 | F42: 257 | G42: 328 | H42: 347 | M42: 473 | N42: 419 | O42: 400 | P42: 429 | Q42: =ROUND(N42+O42*0.6,0) -> 659 | R42: =ROUND(O42*0.4+P42*0.6,0) -> 417
A43: 184.14 | B43: 1529 | C43: 1203 | D43: 768 | E43: 621 | F43: 373 | G43: 1664 | H43: 680 | M43: 1352 | N43: 1137 | O43: 764 | P43: 685 | Q43: =ROUND(N43+O43*0.6,0) -> 1595 | R43: =ROUND(O43*0.4+P43*0.6,0) -> 717
A44: 182.03 | B44: 365 | C44: 103 | D44: 29 | E44: 252 | F44: 151 | G44: 120 | H44: 163 | M44: 206 | N44: 195 | O44: 277 | P44: 410 | Q44: =ROUND(N44+O44*0.6,0) -> 361 | R44: =ROUND(O44*0.4+P44*0.6,0) -> 357
A45: 184.11 | B45: 869 | C45: 530 | D45: 948 | E45: 1113 | F45: 668 | G45: 1099 | H45: 1047 | M45: 1002 | N45: 961 | O45: 1061 | P45: 986 | Q45: =ROUND(N45+O45*0.6,0) -> 1598 | R45: =ROUND(O45*0.4+P45*0.6,0) -> 1016
A46: 184.1 | B46: 50 | C46: 464 | D46: 407 | E46: 743 | F46: 446 | G46: 708 | H46: 609 | M46: 389 | N46: 464 | O46: 523 | P46: 609 | Q46: =ROUND(N46+O46*0.6,0) -> 778 | R46: =ROUND(O46*0.4+P46*0.6,0) -> 575
... A102: 185.05 | B102: 426 | C102: 127 | D102: 424 | E102: 764 | F102: 458 | G102: 381 | H102: 628 | M102: 448 | N102: 464 | O102: 568 | P102: 600 | Q102: =ROUND(N102+O102*0.6,0) -> 805 | R102: =ROUND(O102*0.4+P102*0.6,0) -> 587
G103: =SUM(G2:G102) -> 59893 | H103: =SUM(H2:H102) -> 41180 | Q103: =SUM(Q2:Q102) -> 66081 | R103: =SUM(R2:R102) -> 43855
A104: 9330192 | B104: 1 | C104: 1 | D104: 1 | E104: 1 | M104: 0.058341715 | N104: 0.060977123 | O104: 0.067469408 | P104: 0.070623273 | Q104: =N104+0.6*O104 -> 0.10145877 | R104: =0.6*P104+0.4*O104 -> 0.069361727
A105: 9330186 | B105: 1 | C105: 1 | D105: 2 | E105: 1 | Q105: =Q103/Q104 -> 651308.92 | R105: =R103/R104 -> 632265.11
A106: 186.02 | B106: 1 | C106: 2 | D106: 18 | E106: 1
A107: 186.05 | B107: 1 | C107: 1 | D107: 1 | E107: 1
A108: 186.06 | B108: 4 | C108: 2 | D108: 1 | E108: 1
A109: 185.09 | B109: 1 | C109: 1 | D109: 1 | E109: 1
A110: 185.11 | B110: 1 | C110: 1 | D110: 1 | E110: 1
A111: 185.1 | B111: 11 | C111: 3 | D111: 2 | E111: 1
A112: 185.21 | B112: 1 | C112: 1 | D112: 1 | E112: 1
A113: 185.22 | B113: 1 | C113: 1 | D113: 1 | E113: 1
A114: 185.17 | B114: 1 | C114: 1 | D114: 1 | E114: 1
A115: 185.18 | B115: 1 | C115: 1 | D115: 1 | E115: 1
A116: 185.19 | B116: 1 | C116: 1 | D116: 1 | E116: 1
A117: 185.2 | B117: 1 | C117: 1 | D117: 1 | E117: 1
... A167: 187.15 | B167: 1 | C167: 1 | D167: 1 | E167: 1
A168: 187.14 | B168: 1 | C168: 1 | D168: 1 | E168: #DIV/0!
A169: 187.16 | B169: 1 | C169: 1 | D169: 1 | E169: 1
A170: 182.04 | B170: 1 | C170: 1 | D170: 1 | E170: 1
A171: 182.05 | B171: 1 | C171: 1 | D171: 1 | E171: 1
A172: 182.02 | B172: 1 | C172: 1 | D172: 1 | E172: 1
A173: 183.01 | B173: 1 | C173: 1 | D173: 1 | E173: 1
A174: 183.03 | B174: 1 | C174: 1 | D174: 2 | E174: 1
A175: 183.05 | B175: 1 | C175: 1 | D175: 1 | E175: 1
A176: 183.07 | B176: 1 | C176: 1 | D176: 1 | E176: 1
A177: 183.06 | B177: 1 | C177: 1 | D177: 1 | E177: 1
A178: 183.08 | B178: 1 | C178: 1 | D178: 1 | E178: 1
A179: 183.09 | B179: 1 | C179: 1 | D179: 2 | E179: 3
A180: 182.06 | B180: 1 | C180: 1 | D180: 1 | E180: 1
... A204: 185.05 | B204: 1 | C204: 4 | D204: 1 | E204: 1

Sheet 2021
A1: Census \ Age | B1: 0-4 | C1: 42864 | D1: 43022 | E1: 15-19 | F1: 15-17 | G1: Elementary | H1: Secondary
A2: 9330192 | B2: 224 | C2: 276 | D2: 221 | E2: 304 | F2: 182 | G2: 409 | H2: 270
A3: 9330186 | B3: 462 | C3: 388 | D3: 356 | E3: 560 | F3: 336 | G3: 602 | H3: 478
A4: 186.02 | B4: 512 | C4: 283 | D4: 63 | E4: 546 | F4: 328 | G4: 321 | H4: 353
A5: 186.05 | B5: 492 | C5: 546 | D5: 734 | E5: 724 | F5: 434 | G5: 986 | H5: 728
A6: 186.06 | B6: 152 | C6: 227 | D6: 416 | E6: 344 | F6: 206 | G6: 477 | H6: 372
A7: 185.09 | B7: 497 | C7: 295 | D7: 359 | E7: 338 | F7: 203 | G7: 510 | H7: 347
A8: 185.11 | B8: 532 | C8: 663 | D8: 604 | E8: 546 | F8: 328 | G8: 1025 | H8: 570
A9: 185.1 | B9: 180 | C9: 280 | D9: 315 | E9: 511 | F9: 307 | G9: 469 | H9: 433
A10: 185.21 | B10: 395 | C10: 370 | D10: 252 | E10: 246 | F10: 148 | G10: 521 | H10: 249
A11: 185.22 | B11: 366 | C11: 310 | D11: 282 | E11: 304 | F11: 182 | G11: 479 | H11: 295
A12: 185.17 | B12: 187 | C12: 141 | D12: 171 | E12: 244 | F12: 146 | G12: 244 | H12: 214
A13: 185.18 | B13: 249 | C13: 311 | D13: 350 | E13: 378 | F13: 227 | G13: 521 | H13: 367
... A101: 181.15 | B101: 74 | C101: 119 | D101: 103 | E101: 162 | F101: 97 | G101: 181 | H101: 138

Sheet 2016
A1: Census \ Age | B1: 0-4 | C1: 42864 | D1: 43022 | E1: 15-19 | F1: Total | G1: 15-17
A2: 9330192 | B2: 221 | C2: 257 | D2: 256 | E2: 291 | F2: 4194 | G2: 175 | J2: 0.052766247 | K2: 0.061393041 | L2: 0.061009367 | M2: 0.069489853 | N2: 411 | O2: 277
A3: 9330186 | B3: 475 | C3: 460 | D3: 479 | E3: 505 | F3: 7494 | G3: 303 | J3: 0.063427302 | K3: 0.061325578 | L3: 0.063977185 | M3: 0.067346993 | N3: 747 | O3: 495
A4: 186.02 | B4: 370 | C4: 379 | D4: 399 | E4: 409 | F4: 6106 | G4: 245 | J4: 0.060571392 | K4: 0.06203031 | L4: 0.065340411 | M4: 0.067050533 | N4: 618 | O4: 405
A5: 186.05 | B5: 503 | C5: 573 | D5: 567 | E5: 556 | F5: 7592 | G5: 334 | J5: 0.06624341 | K5: 0.075534112 | L5: 0.07468327 | M5: 0.073200416 | N5: 913 | O5: 560
A6: 186.06 | B6: 333 | C6: 315 | D6: 301 | E6: 264 | F6: 4206 | G6: 158 | J6: 0.07923151 | K6: 0.07481826 | L6: 0.071589807 | M6: 0.062886289 | N6: 496 | O6: 279
A7: 185.09 | B7: 387 | C7: 333 | D7: 322 | E7: 282 | F7: 5127 | G7: 169 | J7: 0.075415148 | K7: 0.065021811 | L7: 0.06280516 | M7: 0.054988243 | N7: 526 | O7: 298
A8: 185.11 | B8: 646 | C8: 644 | D8: 574 | E8: 489 | F8: 7844 | G8: 293 | J8: 0.082347043 | K8: 0.082155766 | L8: 0.073228873 | M8: 0.062296973 | N8: 988 | O8: 523
A9: 185.1 | B9: 502 | C9: 499 | D9: 430 | E9: 404 | F9: 5894 | G9: 242 | J9: 0.085120227 | K9: 0.084672241 | L9: 0.072879553 | M9: 0.068469602 | N9: 757 | O9: 414
A10: 185.21 | B10: 280 | C10: 289 | D10: 279 | E10: 250 | F10: 3845 | G10: 150 | J10: 0.072864504 | K10: 0.075216187 | L10: 0.072452995 | M10: 0.065008172 | N10: 456 | O10: 262
A11: 185.22 | B11: 323 | C11: 293 | D11: 258 | E11: 261 | F11: 3771 | G11: 157 | J11: 0.085633783 | K11: 0.077657682 | L11: 0.068362265 | M11: 0.069284698 | N11: 448 | O11: 260
A12: 185.17 | B12: 175 | C12: 175 | D12: 197 | E12: 235 | F12: 3520 | G12: 141 | J12: 0.049609843 | K12: 0.049693019 | L12: 0.056042591 | M12: 0.066892743 | N12: 293 | O12: 220
A13: 185.18 | B13: 308 | C13: 325 | D13: 348 | E13: 388 | F13: 5295 | G13: 233 | J13: 0.058231362 | K13: 0.061315181 | L13: 0.065809093 | M13: 0.073211071 | N13: 534 | O13: 372
... A101: 181.15 | B101: 100 | C101: 110 | D101: 235 | E101: 155 | F101: 2600 | G101: 93 | J101: 0.035397126 | K101: 0.040863741 | L101: 0.050003188 | M101: 0.057226928 | N101: 251 | O101: 187
A102: 185.05 | B102: 402 | C102: 449 | D102: 522 | E102: 518 | F102: 5943 | G102: 311 | J102: =(0.06826568266+'2011'!H102)/2 -> 0.067611102 | K102: =(0.0857933579335793+'2011'!I102)/2 -> 0.075505375 | L102: =(0.0922509225092251+'2011'!J102)/2 -> 0.087864592 | M102: =(0.0821033210332103+'2011'!K102)/2 -> 0.087138617 | N102: 762 | O102: 520
J103: =SUM(J2:J102)/101 -> 0.058341715 | K103: =SUM(K2:K102)/101 -> 0.060977123 | L103: =SUM(L2:L102)/101 -> 0.067469408 | M103: =SUM(M2:M102)/101 -> 0.070623273 | N103: =K103+0.6*L103 -> 0.10145877 | O103: =0.6*M103+0.4*L103 -> 0.069361727
M104: Total | N104: =SUM(N2:N102) -> 55797 | O104: =SUM(O2:O102) -> 36949
M105: Enroll | N105: 40016 | O105: 27300

Sheet 2011
A1: Census \ Age | B1: 0-4 | C1: 42864 | D1: 43022 | E1: 15-19 | F1: Total | H1: 0-4 % | I1: 5-9 % | J1: 10-14 % | K1: 15-19%
A2: 9330192 | B2: 220 | C2: 265 | D2: 230 | E2: 295 | F2: 4145 | H2: =B2/$F2 -> 0.053075995 | I2: =C2/$F2 -> 0.063932449 | J2: =D2/$F2 -> 0.05548854 | K2: =E2/$F2 -> 0.071170084
A3: 9330186 | B3: 440 | C3: 410 | D3: 415 | E3: 485 | F3: 7137 | H3: =B3/F3 -> 0.061650553 | I3: =C3/$F3 -> 0.057447107 | J3: =D3/$F3 -> 0.058147681 | K3: =E3/$F3 -> 0.067955724
A4: 186.02 | B4: 345 | C4: 330 | D4: 325 | E4: 380 | F4: 5495 | H4: =B4/F4 -> 0.062784349 | I4: =C4/$F4 -> 0.060054595 | J4: =D4/$F4 -> 0.059144677 | K4: =E4/$F4 -> 0.069153776
A5: 186.05 | B5: 460 | C5: 520 | D5: 570 | E5: 560 | F5: 7187 | H5: =B5/F5 -> 0.064004452 | I5: =C5/$F5 -> 0.072352859 | J5: =D5/$F5 -> 0.079309865 | K5: =E5/$F5 -> 0.077918464
A6: 186.06 | B6: 295 | C6: 290 | D6: 305 | E6: 265 | F6: 4079 | H6: =B6/F6 -> 0.072321647 | I6: =C6/$F6 -> 0.071095857 | J6: =D6/$F6 -> 0.074773229 | K6: =E6/$F6 -> 0.064966904
A7: 185.09 | B7: 405 | C7: 295 | D7: 315 | E7: 285 | F7: 5002 | H7: =B7/F7 -> 0.080967613 | I7: =C7/$F7 -> 0.058976409 | J7: =D7/$F7 -> 0.06297481 | K7: =E7/$F7 -> 0.056977209
A8: 185.11 | B8: 595 | C8: 635 | D8: 570 | E8: 495 | F8: 7856 | H8: =B8/F8 -> 0.075738289 | I8: =C8/$F8 -> 0.080829939 | J8: =D8/$F8 -> 0.072556008 | K8: =E8/$F8 -> 0.063009165
A9: 185.1 | B9: 465 | C9: 470 | D9: 410 | E9: 415 | F9: 5781 | H9: =B9/F9 -> 0.080435911 | I9: =C9/$F9 -> 0.081300813 | J9: =D9/$F9 -> 0.070921986 | K9: =E9/$F9 -> 0.071786888
A10: 185.21 | B10: 230 | C10: 250 | D10: 275 | E10: 240 | F10: 3640 | H10: =B10/F10 -> 0.063186813 | I10: =C10/$F10 -> 0.068681319 | J10: =D10/$F10 -> 0.075549451 | K10: =E10/$F10 -> 0.065934066
A11: 185.22 | B11: 375 | C11: 310 | D11: 285 | E11: 315 | F11: 4214 | H11: =B11/F11 -> 0.088989084 | I11: =C11/$F11 -> 0.073564309 | J11: =D11/$F11 -> 0.067631704 | K11: =E11/$F11 -> 0.074750831
A12: 185.17 | B12: 170 | C12: 145 | D12: 170 | E12: 225 | F12: 3649 | H12: =B12/F12 -> 0.046588106 | I12: =C12/$F12 -> 0.039736914 | J12: =D12/$F12 -> 0.046588106 | K12: =E12/$F12 -> 0.061660729
A13: 185.18 | B13: 305 | C13: 300 | D13: 315 | E13: 355 | F13: 4779 | H13: =B13/F13 -> 0.063820883 | I13: =C13/$F13 -> 0.062774639 | J13: =D13/$F13 -> 0.065913371 | K13: =E13/$F13 -> 0.074283323
A14: 185.19 | B14: 410 | C14: 355 | D14: 365 | E14: 375 | F14: 5418 | H14: =B14/F14 -> 0.07567368 | I14: =C14/$F14 -> 0.065522333 | J14: =D14/$F14 -> 0.067368032 | K14: =E14/$F14 -> 0.069213732
... A75: 183.06 | B75: 150 | C75: 130 | D75: 140 | E75: 135 | F75: 2356 | H75: =B75/F75 -> 0.063667233 | I75: =C75/$F75 -> 0.055178268 | J75: =D75/$F75 -> 0.05942275 | K75: =E75/$F75 -> 0.057300509
A76: 183.08 | B76: 750 | C76: 445 | D76: 360 | E76: 323 | F76: 7017 | H76: =B76/F76 -> 0.10688328 | I76: =C76/$F76 -> 0.063417415 | J76: =D76/$F76 -> 0.051303976 | K76: =E76/$F76 -> 0.046031067 | L76: =SUM(B76:D76) -> 1555
A77: 183.09 | B77: 750 | C77: 445 | D77: 360 | E77: 322 | F77: 7017 | H77: =B77/F77 -> 0.10688328 | I77: =C77/$F77 -> 0.063417415 | J77: =D77/$F77 -> 0.051303976 | K77: =E77/$F77 -> 0.045888556
A78: 182.06 | B78: 45 | C78: 70 | D78: 90 | E78: 100 | F78: 1180 | H78: =B78/F78 -> 0.038135593 | I78: =C78/$F78 -> 0.059322034 | J78: =D78/$F78 -> 0.076271186 | K78: =E78/$F78 -> 0.084745763
A79: 188.06 | B79: 65 | C79: 70 | D79: 95 | E79: 90 | F79: 1184 | H79: =B79/F79 -> 0.054898649 | I79: =C79/$F79 -> 0.059121622 | J79: =D79/$F79 -> 0.080236486 | K79: =E79/$F79 -> 0.076013514
A80: 188.05 | B80: 115 | C80: 160 | D80: 205 | E80: 275 | F80: 2687 | H80: =B80/F80 -> 0.04279866 | I80: =C80/$F80 -> 0.059545962 | J80: =D80/$F80 -> 0.076293264 | K80: =E80/$F80 -> 0.10234462
A81: 182.01 | B81: 210 | C81: 245 | D81: 275 | E81: 295 | F81: 4160 | H81: =B81/F81 -> 0.050480769 | I81: =C81/$F81 -> 0.058894231 | J81: =D81/$F81 -> 0.066105769 | K81: =E81/$F81 -> 0.070913462
A82: 180.01 | B82: 490 | C82: 535 | D82: 455 | E82: 435 | F82: 6910 | H82: =B82/F82 -> 0.070911722 | I82: =C82/$F82 -> 0.077424023 | J82: =D82/$F82 -> 0.065846599 | K82: =E82/$F82 -> 0.062952243
A83: 180.04 | B83: 325 | C83: 280 | D83: 343 | E83: 368 | F83: 6004 | H83: =B83/F83 -> 0.05413058 | I83: =C83/$F83 -> 0.046635576 | J83: =D83/$F83 -> 0.057128581 | K83: =E83/$F83 -> 0.061292472
A84: 180.03 | B84: 325 | C84: 280 | D84: 342 | E84: 367 | F84: 6003 | H84: =B84/F84 -> 0.054139597 | I84: =C84/$F84 -> 0.046643345 | J84: =D84/$F84 -> 0.056971514 | K84: =E84/$F84 -> 0.061136099
A85: 181.13 | B85: 110 | C85: 125 | D85: 175 | E85: 210 | F85: 3274 | H85: =B85/F85 -> 0.033598045 | I85: =C85/$F85 -> 0.038179597 | J85: =D85/$F85 -> 0.053451436 | K85: =E85/$F85 -> 0.064141723
A86: 181.12 | B86: 100 | C86: 155 | D86: 215 | E86: 225 | F86: 2884 | H86: =B86/F86 -> 0.034674064 | I86: =C86/$F86 -> 0.053744799 | J86: =D86/$F86 -> 0.074549237 | K86: =E86/$F86 -> 0.078016644
A87: 181.14 | B87: 205 | C87: 170 | D87: 190 | E87: 215 | F87: 3706 | H87: =B87/F87 -> 0.055315704 | I87: =C87/$F87 -> 0.04587156 | J87: =D87/$F87 -> 0.051268214 | K87: =E87/$F87 -> 0.058014031
A88: 181.1 | B88: 145 | C88: 220 | D88: 280 | E88: 410 | F88: 5189 | H88: =B88/F88 -> 0.027943727 | I88: =C88/$F88 -> 0.042397379 | J88: =D88/$F88 -> 0.053960301 | K88: =E88/$F88 -> 0.079013297
... A101: 181.15 | B101: 82 | C101: 110 | D101: 115 | E101: 152 | F101: 2561 | H101: =B101/F101 -> 0.032018743 | I101: =C101/$F101 -> 0.042951972 | J101: =D101/$F101 -> 0.044904334 | K101: =E101/$F101 -> 0.059351816
A102: 185.05 | B102: 385 | C102: 375 | D102: 480 | E102: 530 | F102: 5750 | H102: =B102/$F$102 -> 0.066956522 | I102: =C102/$F$102 -> 0.065217391 | J102: =D102/$F$102 -> 0.083478261 | K102: =E102/$F$102 -> 0.092173913
H103: =SUM(H2:H102)/101 -> 0.057738114 | I103: =SUM(I2:I102)/101 -> 0.058259341 | J103: =SUM(J2:J102)/101 -> 0.064161221 | K103: =SUM(K2:K102)/101 -> 0.070564582 | L103: =I103+0.6*J103 -> 0.096756074 | M103: =0.6*K103+0.4*J103 -> 0.068003238

Sheet 2006
A1: Census \ Age | B1: 0-4 | C1: 42864 | D1: 43022 | E1: 15-19 | F1: total | H1: 0-4 % | I1: 5-9 % | J1: 10-14 % | K1: 15-19%
A2: 9330192 | B2: 205 | C2: 230 | D2: 260 | E2: 265 | F2: 3908 | H2: =B2/$F2 -> 0.052456499 | I2: =C2/$F2 -> 0.058853634 | J2: =D2/$F2 -> 0.066530194 | K2: =E2/$F2 -> 0.067809621
A3: 9330186 | B3: 425 | C3: 425 | D3: 455 | E3: 435 | F3: 6518 | H3: =B3/F3 -> 0.06520405 | I3: =C3/$F3 -> 0.06520405 | J3: =D3/$F3 -> 0.069806689 | K3: =E3/$F3 -> 0.066738263
A4: 186.02 | B4: 310 | C4: 340 | D4: 380 | E4: 345 | F4: 5312 | H4: =B4/F4 -> 0.058358434 | I4: =C4/$F4 -> 0.064006024 | J4: =D4/$F4 -> 0.071536145 | K4: =E4/$F4 -> 0.064947289
A5: 186.05 | B5: 435 | C5: 500 | D5: 445 | E5: 435 | F5: 6352 | H5: =B5/F5 -> 0.068482368 | I5: =C5/$F5 -> 0.078715365 | J5: =D5/$F5 -> 0.070056675 | K5: =E5/$F5 -> 0.068482368
A6: 186.06 | B6: 340 | C6: 310 | D6: 270 | E6: 240 | F6: 3947 | H6: =B6/F6 -> 0.086141373 | I6: =C6/$F6 -> 0.078540664 | J6: =D6/$F6 -> 0.068406385 | K6: =E6/$F6 -> 0.060805675
A7: 185.09 | B7: 290 | C7: 295 | D7: 260 | E7: 220 | F7: 4151 | H7: =B7/F7 -> 0.069862684 | I7: =C7/$F7 -> 0.071067213 | J7: =D7/$F7 -> 0.06263551 | K7: =E7/$F7 -> 0.052999277
A8: 185.11 | B8: 650 | C8: 610 | D8: 540 | E8: 450 | F8: 7307 | H8: =B8/F8 -> 0.088955796 | I8: =C8/$F8 -> 0.083481593 | J8: =D8/$F8 -> 0.073901738 | K8: =E8/$F8 -> 0.061584782
A9: 185.1 | B9: 510 | C9: 500 | D9: 425 | E9: 370 | F9: 5679 | H9: =B9/F9 -> 0.089804543 | I9: =C9/$F9 -> 0.08804367 | J9: =D9/$F9 -> 0.074837119 | K9: =E9/$F9 -> 0.065152316
A10: 185.21 | B10: 313 | C10: 310 | D10: 263 | E10: 243 | F10: 3792 | H10: =B10/F10 -> 0.082542194 | I10: =C10/$F10 -> 0.081751055 | J10: =D10/$F10 -> 0.06935654 | K10: =E10/$F10 -> 0.064082278
A11: 185.22 | B11: 312 | C11: 310 | D11: 262 | E11: 242 | F11: 3792 | H11: =B11/F11 -> 0.082278481 | I11: =C11/$F11 -> 0.081751055 | J11: =D11/$F11 -> 0.069092827 | K11: =E11/$F11 -> 0.063818565
A12: 185.17 | B12: 135 | C12: 153 | D12: 168 | E12: 185 | F12: 2565 | H12: =B12/F12 -> 0.052631579 | I12: =C12/$F12 -> 0.059649123 | J12: =D12/$F12 -> 0.065497076 | K12: =E12/$F12 -> 0.072124756
A13: 185.18 | B13: 270 | C13: 307 | D13: 337 | E13: 370 | F13: 5129 | H13: =B13/F13 -> 0.052641841 | I13: =C13/$F13 -> 0.059855722 | J13: =D13/$F13 -> 0.065704816 | K13: =E13/$F13 -> 0.072138818
A14: 185.19 | B14: 380 | C14: 315 | D14: 317.5 | E14: 272.5 | F14: 4235 | H14: =B14/F14 -> 0.089728453 | I14: =C14/$F14 -> 0.074380165 | J14: =D14/$F14 -> 0.074970484 | K14: =E14/$F14 -> 0.064344746
... A101: 181.15 | B101: 95 | C101: 95 | D101: 135 | E101: 135 | F101: 2450 | H101: =B101/F101 -> 0.03877551 | I101: =C101/$F101 -> 0.03877551 | J101: =D101/$F101 -> 0.055102041 | K101: =E101/$F101 -> 0.055102041
A102: 185.05 | B102: 370 | C102: 465 | D102: 500 | E102: 445 | F102: 5420 | H102: 0.068265683 | I102: =C102/$F102 -> 0.085793358 | J102: =D102/$F102 -> 0.092250923 | K102: =E102/$F102 -> 0.082103321
H103: =SUM(H2:H102)/101 -> 0.058945316 | I103: =SUM(I2:I102)/101 -> 0.063694904 | J103: =SUM(J2:J102)/101 -> 0.070777595 | K103: =SUM(K2:K102)/101 -> 0.070681964 | L103: =I103+0.6*J103 -> 0.10616146 | M103: =0.6*K103+0.4*J103 -> 0.070720216

Sheet 2001
A1: Census \ Age | B1: 0-4 | C1: 42864 | D1: 43022 | E1: 15 | F1: total
A2: 9330192 | B2: 216 | C2: 251 | D2: 250 | E2: 285 | F2: 4096 | H2: 0.052766247 | I2: 0.061393041 | J2: 0.061009367 | K2: 0.069489853
A3: 9330186 | B3: 382 | C3: 369 | D3: 385 | E3: 405 | F3: 6015 | H3: 0.063427302 | I3: 0.061325578 | J3: 0.063977185 | K3: 0.067346993
A4: 186.02 | B4: 301 | C4: 309 | D4: 325 | E4: 334 | F4: 4977 | H4: 0.060571392 | I4: 0.06203031 | J4: 0.065340411 | K4: 0.067050533
A5: 186.05 | B5: 385 | C5: 439 | D5: 434 | E5: 425 | F5: 5806 | H5: 0.06624341 | I5: 0.075534112 | J5: 0.07468327 | K5: 0.073200416
A6: 186.06 | B6: 277 | C6: 262 | D6: 250 | E6: 220 | F6: 3496 | H6: 0.07923151 | I6: 0.07481826 | J6: 0.071589807 | K6: 0.062886289
A7: 185.09 | B7: 293 | C7: 253 | D7: 244 | E7: 214 | F7: 3890 | H7: 0.075415148 | I7: 0.065021811 | J7: 0.06280516 | K7: 0.054988243
A8: 185.11 | B8: 542 | C8: 541 | D8: 482 | E8: 410 | F8: 6585 | H8: 0.082347043 | I8: 0.082155766 | J8: 0.073228873 | K8: 0.062296973
A9: 185.1 | B9: 402 | C9: 399 | D9: 344 | E9: 323 | F9: 4717 | H9: 0.085120227 | I9: 0.084672241 | J9: 0.072879553 | K9: 0.068469602
A10: 185.21 | B10: 251 | C10: 259 | D10: 250 | E10: 224 | F10: =6891/2 -> 3445.5 | H10: 0.072864504 | I10: 0.075216187 | J10: 0.072452995 | K10: 0.065008172
A11: 185.22 | B11: 295 | C11: 268 | D11: 236 | E11: 239 | F11: =6891/2 -> 3445.5 | H11: 0.085633783 | I11: 0.077657682 | J11: 0.068362265 | K11: 0.069284698
A12: 185.17 | B12: 117 | C12: 117 | D12: 132 | E12: 157 | F12: 2351 | H12: 0.049609843 | I12: 0.049693019 | J12: 0.056042591 | K12: 0.066892743
A13: 185.18 | B13: 274 | C13: 288 | D13: 309 | E13: 344 | F13: 4701 | H13: 0.058231362 | I13: 0.061315181 | J13: 0.065809093 | K13: 0.073211071
A14: 185.19 | B14: 250 | C14: 212 | D14: 215 | E14: 202 | F14: =6051/2 -> 3025.5 | H14: 0.082701067 | I14: 0.069951249 | J14: 0.071169258 | K14: 0.066779239
A15: 185.2 | B15: 258 | C15: 235 | D15: 227 | E15: 214 | F15: =6051/2 -> 3025.5 | H15: 0.085421631 | I15: 0.077747487 | J15: 0.074922846 | K15: 0.070649911
A16: 185.08 | B16: 50 | C16: 61 | D16: 75 | E16: 103 | F16: 1209 | H16: 0.041688786 | I16: 0.050696955 | J16: 0.061730053 | K16: 0.085262941
A17: 185.07 | B17: 375 | C17: 409 | D17: 428 | E17: 434 | F17: 5548 | H17: 0.067669867 | I17: 0.073640259 | J17: 0.07710561 | K17: 0.078154026
A18: 185.12 | B18: 411 | C18: 453 | D18: 480 | E18: 434 | F18: 6133 | H18: 0.06703485 | I18: 0.073860576 | J18: 0.078345136 | K18: 0.07072437
A19: 185.16 | B19: 343 | C19: 350 | D19: 350 | E19: 321 | F19: 4425 | H19: 0.077553348 | I19: 0.079091059 | J19: 0.07906712 | K19: 0.072469537
A20: 185.15 | B20: 419 | C20: 365 | D20: 319 | E20: 286 | F20: 5086 | H20: 0.082473048 | I20: 0.07168113 | J20: 0.062747503 | K20: 0.056243026
A21: 186.07 | B21: 342 | C21: 346 | D21: 336 | E21: 306 | F21: 4547 | H21: 0.075124028 | I21: 0.076050912 | J21: 0.073918462 | K21: 0.067383829
A22: 186.08 | B22: 369 | C22: 398 | D22: 405 | E22: 392 | F22: 5259 | H22: 0.070150311 | I22: 0.075656088 | J22: 0.077001666 | K22: 0.074511225
A23: 191.03 | B23: 312 | C23: 302 | D23: 295 | E23: 326 | F23: 4484 | H23: 0.069536325 | I23: 0.067256453 | J23: 0.065771934 | K23: 0.072639897
A24: 191.04 | B24: 248 | C24: 220 | D24: 229 | E24: 234 | F24: 4603 | H24: 0.053895746 | I24: 0.047886979 | J24: 0.049707832 | K24: 0.050861147
A25: 191.05 | B25: 206 | C25: 203 | D25: 241 | E25: 256 | F25: 3739 | H25: 0.055164271 | I25: 0.054158926 | J25: 0.064483754 | K25: 0.068393058
A26: 191.06 | B26: 99 | C26: 75 | D26: 85 | E26: 96 | F26: 1869 | H26: 0.05303484 | I26: 0.039940638 | J26: 0.045491556 | K26: 0.051274131
A27: 191.07 | B27: 105 | C27: 73 | D27: 85 | E27: 99 | F27: 1869 | H27: 0.056022784 | I27: 0.038934253 | J27: 0.045645389 | K27: 0.052717525
... A35: 184.02 | B35: 436 | C35: 438 | D35: 409 | E35: 427 | F35: 6832 | H35: 0.063768414 | I35: 0.064101347 | J35: 0.059876811 | K35: 0.062540281
A36: 184.15 | B36: 133 | C36: 141 | D36: 185 | E36: 228 | F36: =7844/3 -> 2614.6667 | H36: 0.050804175 | I36: 0.053975154 | J36: 0.070905739 | K36: 0.087189709
A37: 184.16 | B37: 301 | C37: 334 | D37: 392 | E37: 417 | F37: =7844-F36 -> 5229.3333 | H37: 0.05753618 | I37: 0.063898283 | J37: 0.074879129 | K37: 0.079775133
A38: 184.07 | B38: 295 | C38: 313 | D38: 332 | E38: 308 | F38: 4954 | H38: 0.059610977 | I38: 0.063098213 | J38: 0.067021863 | K38: 0.062083246
A39: 184.08 | B39: 242 | C39: 271 | D39: 311 | E39: 282 | F39: 3508 | H39: 0.068955473 | I39: 0.07717801 | J39: 0.088582681 | K39: 0.080517329
A40: 184.06 | B40: 118 | C40: 110 | D40: 100 | E40: 85 | F40: 1371 | H40: 0.086084214 | I40: 0.080373521 | J40: 0.07284424 | K40: 0.06206548
A41: 184.12 | B41: 105 | C41: 67 | D41: 74 | E41: 74 | F41: =2523/2 -> 1261.5 | H41: 0.082901294 | I41: 0.05293192 | J41: 0.05835231 | K41: 0.058737614
A42: 184.13 | B42: 179 | C42: 147 | D42: 140 | E42: 147 | F42: =5045/2 -> 2522.5 | H42: 0.07107942 | I42: 0.058377846 | J42: 0.055597149 | K42: 0.058367772
A43: 184.14 | B43: 121 | C43: 104 | D43: 70 | E43: 65 | F43: =5045-F41-F42 -> 1261 | H43: 0.095943815 | I43: 0.082134281 | J43: 0.055841885 | K43: 0.051189232
A44: 182.03 | B44: 148 | C44: 165 | D44: 247 | E44: 344 | F44: 3432 | H44: 0.043046997 | I44: 0.048132857 | J44: 0.072017295 | K44: 0.10028873
A45: 184.11 | B45: 236 | C45: 236 | D45: 249 | E45: 225 | F45: 3281 | H45: 0.071958717 | I45: 0.07178616 | J45: 0.075884202 | K45: 0.068552192
A46: 184.1 | B46: 200 | C46: 215 | D46: 249 | E46: 275 | F46: 3150 | H46: 0.063584591 | I46: 0.068390685 | J46: 0.079196351 | K46: 0.087208944
A47: 184.09 | B47: 271 | C47: 327 | D47: 333 | E47: 366 | F47: 4471 | H47: 0.060635933 | I47: 0.073064375 | J47: 0.074570654 | K47: 0.081820969
A48: 187.03 | B48: 433 | C48: 433 | D48: 437 | E48: 468 | F48: 6468 | H48: 0.066973693 | I48: 0.066946125 | J48: 0.067594109 | K48: 0.072365227
A49: 189.05 | B49: 330 | C49: 322 | D49: 337 | E49: 375 | F49: 6982 | H49: 0.047251405 | I49: 0.04614359 | J49: 0.048258815 | K49: 0.053770139
A50: 189.08 | B50: 463 | C50: 440 | D50: 416 | E50: 425 | F50: 6119 | H50: 0.075633374 | I50: 0.071896918 | J50: 0.067952005 | K50: 0.069504955
A51: 189.03 | B51: 185 | C51: 221 | D51: 254 | E51: 244 | F51: 3248 | H51: 0.057072349 | I51: 0.067957905 | J51: 0.078048549 | K51: 0.075128728
A52: 188.01 | B52: 103 | C52: 141 | D52: 167 | E52: 194 | F52: 2059 | H52: 0.049921833 | I52: 0.068680191 | J52: 0.081085309 | K52: 0.094049179
A53: 188.02 | B53: 114 | C53: 139 | D53: 184 | E53: 201 | F53: 2089 | H53: 0.054490089 | I53: 0.066424403 | J53: 0.087920158 | K53: 0.0961518
A54: 189.07 | B54: 138 | C54: 162 | D54: 145 | E54: 150 | F54: 2353 | H54: 0.058753752 | I54: 0.068946908 | J54: 0.061628549 | K54: 0.063685965
A55: 189.1 | B55: 282 | C55: 315 | D55: 397 | E55: 430 | F55: 4833 | H55: 0.058389398 | I55: 0.065163155 | J55: 0.082182938 | K55: 0.089042087
... A64: 187.07 | B64: 75 | C64: 101 | D64: 135 | E64: 150 | F64: 1588 | H64: 0.047114795 | I64: 0.06371624 | J64: 0.084849572 | K64: 0.09444429
A65: 187.15 | B65: 124 | C65: 151 | D65: 172 | E65: 187 | F65: =7450/3 -> 2483.3333 | H65: 0.049845237 | I65: 0.060737969 | J65: 0.069338963 | K65: 0.075361751
A66: 187.14 | B66: 140 | C66: 147 | D66: 163 | E66: 149 | F66: =7450/3 -> 2483.3333 | H66: 0.05621668 | I66: 0.059133277 | J66: 0.065633577 | K66: 0.06000808
A67: 187.16 | B67: 126 | C67: 161 | D67: 193 | E67: 207 | F67: =7450/3 -> 2483.3333 | H67: 0.050712903 | I67: 0.06487231 | J67: 0.077581163 | K67: 0.083505888
A68: 182.04 | B68: 46 | C68: 83 | D68: 126 | E68: 150 | F68: 1477 | H68: 0.030926878 | I68: 0.056076748 | J68: 0.085559373 | K68: 0.10136312
A69: 182.05 | B69: 161 | C69: 167 | D69: 175 | E69: 192 | F69: 2794 | H69: 0.057786961 | I69: 0.059757256 | J69: 0.062639198 | K69: 0.068726714
A70: 182.02 | B70: 32 | C70: 30 | D70: 22 | E70: 18 | F70: 307 | H70: 0.10427466 | I70: 0.098850025 | J70: 0.073211465 | K70: 0.057305073
A71: 183.01 | B71: 399 | C71: 431 | D71: 505 | E71: 490 | F71: 5959 | H71: 0.066913098 | I71: 0.072348057 | J71: 0.084768434 | K71: 0.082173923
A72: 183.03 | B72: 334 | C72: 331 | D72: 349 | E72: 396 | F72: 5853 | H72: 0.057004085 | I72: 0.056508429 | J72: 0.059586014 | K72: 0.067655954
A73: 183.05 | B73: 476 | C73: 428 | D73: 388 | E73: 329 | F73: 5115 | H73: 0.093099623 | I73: 0.08359664 | J73: 0.075865751 | K73: 0.064407099
A74: 183.07 | B74: 302 | C74: 373 | D74: 460 | E74: 514 | F74: 6445 | H74: 0.046820445 | I74: 0.057918878 | J74: 0.071343816 | K74: 0.079762988
A75: 183.06 | B75: 143 | C75: 149 | D75: 152 | E75: 136 | F75: 2400 | H75: 0.059772821 | I75: 0.062233747 | J75: 0.06323842 | K75: 0.056589459
A76: 183.08 | B76: 0 | C76: 0 | D76: 0 | E76: 0 | F76: 0 | H76: 0.067720441 | I76: 0.04211529 | J76: 0.037268639 | K76: 0.034390171
A77: 183.09 | B77: 0 | C77: 0 | D77: 0 | E77: 0 | F77: 0 | H77: 0.12507765 | I77: 0.083015581 | J77: 0.0830092 | K77: 0.079333436
A78: 182.06 | B78: 48 | C78: 70 | D78: 91 | E78: 98 | F78: 1203 | H78: 0.039694859 | I78: 0.058538905 | J78: 0.075264306 | K78: 0.0815643
A79: 188.06 | B79: 54 | C79: 56 | D79: 80 | E79: 73 | F79: 942 | H79: 0.057211229 | I79: 0.059322716 | J79: 0.0847611 | K79: 0.077689296
... A82: 180.01 | B82: 121 | C82: 118 | D82: 101 | E82: 97 | F82: 1589 | H82: 0.075840149 | I82: 0.074420224 | J82: 0.063530339 | K82: 0.060807868
A83: 180.04 | B83: 150 | C83: 159 | D83: 205 | E83: 224 | F83: =6610/2 -> 3305 | H83: 0.045535331 | I83: 0.048041465 | J83: 0.062013971 | K83: 0.067731751
A84: 180.03 | B84: 151 | C84: 159 | D84: 205 | E84: 224 | F84: =6610-F83 -> 3305 | H84: 0.045685273 | I84: 0.048045349 | J84: 0.061935437 | K84: 0.067653564
A85: 181.13 | B85: 92 | C85: 108 | D85: 135 | E85: 152 | F85: =6993/3 -> 2331 | H85: 0.03936783 | I85: 0.046245762 | J85: 0.058101865 | K85: 0.065281871
A86: 181.12 | B86: 93 | C86: 126 | D86: 160 | E86: 169 | F86: =6993/3 -> 2331 | H86: 0.039905839 | I86: 0.054028363 | J86: 0.068834252 | K86: 0.072402817
A87: 181.14 | B87: 117 | C87: 117 | D87: 133 | E87: 145 | F87: =6993-F85-F86 -> 2331 | H87: 0.050401799 | I87: 0.0502652 | J87: 0.057182163 | K87: 0.062389261
A88: 181.1 | B88: 174 | C88: 246 | D88: 350 | E88: 463 | F88: =7368/6*5 -> 6140 | H88: 0.02831495 | I88: 0.040105486 | J88: 0.056970241 | K88: 0.075364365
A89: 181.11 | B89: 37 | C89: 42 | D89: 63 | E89: 84 | F89: =7368-F88 -> 1228 | H89: 0.030294472 | I89: 0.033862107 | J89: 0.051458319 | K89: 0.068631215
A90: 181.09 | B90: 189 | C90: 332 | D90: 522 | E90: 561 | F90: 6253 | H90: 0.03029239 | I90: 0.053154649 | J90: 0.083447038 | K90: 0.089693311
A91: 181.03 | B91: 217 | C91: 286 | D91: 415 | E91: 459 | F91: 5419 | H91: 0.040123429 | I91: 0.052830944 | J91: 0.076540242 | K91: 0.084759113
A92: 181.07 | B92: 137 | C92: 197 | D92: 263 | E92: 296 | F92: 3597 | H92: 0.037957488 | I92: 0.054830382 | J92: 0.073107966 | K92: 0.082246462
A93: 181.08 | B93: 111 | C93: 140 | D93: 153 | E93: 175 | F93: 2476 | H93: 0.044717378 | I93: 0.056618973 | J93: 0.061892807 | K93: 0.07070256
A94: 170.04 | B94: 161 | C94: 198 | D94: 235 | E94: 264 | F94: 5245 | H94: 0.03062623 | I94: 0.037693031 | J94: 0.044728984 | K94: 0.050337181
A95: 170.03 | B95: 42 | C95: 31 | D95: 60 | E95: 69 | F95: 3240 | H95: 0.013013559 | I95: 0.0096921936 | J95: 0.018584294 | K95: 0.021256478
A96: 170.05 | B96: 45 | C96: 33 | D96: 36 | E96: 47 | F96: 2269 | H96: 0.019876035 | I96: 0.014613793 | J96: 0.015647706 | K96: 0.020909948
A97: 170.08 | B97: 136 | C97: 136 | D97: 160 | E97: 177 | F97: =7496/2 -> 3748 | H97: 0.036417891 | I97: 0.036338072 | J97: 0.042559511 | K97: 0.047352702
A98: 170.07 | B98: 174 | C98: 169 | D98: 192 | E98: 190 | F98: =7496-F97 -> 3748 | H98: 0.04635236 | I98: 0.045185468 | J98: 0.051321896 | K98: 0.050644764
A99: 181.05 | B99: 282 | C99: 285 | D99: 330 | E99: 376 | F99: 7148 | H99: 0.039495248 | I99: 0.039830368 | J99: 0.046189854 | K99: 0.052550685
A100: 181.16 | B100: 89 | C100: 102 | D100: 125 | E100: 144 | F100: =5011/2 -> 2505.5 | H100: 0.035592363 | I100: 0.040863741 | J100: 0.050003188 | K100: 0.057422164
A101: 181.15 | B101: 89 | C101: 102 | D101: 125 | E101: 143 | F101: =5011-2506 -> 2505 | H101: =(0.0387755102+'2011'!H101)/2 -> 0.035397126 | I101: 0.040863741 | J101: 0.050003188 | K101: 0.057226928
A102: 185.05 | B102: 330 | C102: 369 | D102: 429 | E102: 425 | F102: 4883 | H102: =(0.06826568266+'2011'!H102)/2 -> 0.067611102 | I102: =(0.0857933579335793+'2011'!I102)/2 -> 0.075505375 | J102: =(0.0922509225092251+'2011'!J102)/2 -> 0.087864592 | K102: =(0.0821033210332103+'2011'!K102)/2 -> 0.087138617
H103: =SUM(H2:H102)/101 -> 0.058341715 | I103: =SUM(I2:I102)/101 -> 0.060977123 | J103: =SUM(J2:J102)/101 -> 0.067469408 | K103: =SUM(K2:K102)/101 -> 0.070623273 | L103: =I103+0.6*J103 -> 0.10145877 | M103: =0.6*K103+0.4*J103 -> 0.069361727

Sheet Cost estimate
F1: COST OF NEW SCHOOL BY CAPACITY | P1: COST OF EXPANSION PER 100 STUDENTS
A2: SECONDARY SCHOOL | B2: 1000 | C2: 1100 | D2: 1200 | E2: 1300 | F2: 1400 | G2: 1500 | H2: 1600 | I2: 1700 | J2: 1800 | K2: 1900 | L2: 2000 | M2: 2100 | N2: 2200 | Q2: TOTAL BUDGET FOR 2020-2025: | R2: 150
A3: Ecole Lord Tweedsmuir | B3: =ROUND(5*$R$8*($R$5+$R$6)*$R$10^$R$11,1) -> 61.3 | C3: =ROUND(5.3*$R$8*($R$5+$R$6)*$R$10^$R$11,1) -> 65 | D3: =ROUND(5.6*$R$8*($R$5+$R$6)*$R$10^$R$11,1) -> 68.6 | E3: =ROUND(5.8*$R$8*($R$5+$R$6)*$R$10^$R$11,1) -> 71.1 | F3: =ROUND(6.1*$R$8*($R$5+$R$6)*$R$10^$R$11,1) -> 74.8 | G3: =ROUND(6.3*$R$8*($R$5+$R$6)*$R$10^$R$11,1) -> 77.2 | H3: =ROUND(6.6*$R$8*($R$5+$R$6)*$R$10^$R$11,1) -> 80.9 | I3: =ROUND(6.8*$R$8*($R$5+$R$6)*$R$10^$R$11,1) -> 83.3 | J3: =ROUND(7.1*$R$8*($R$5+$R$6)*$R$10^$R$11,1) -> 87 | K3: =ROUND(7.4*$R$8*($R$5+$R$6)*$R$10^$R$11,1) -> 90.7 | L3: =ROUND(7.7*$R$8*($R$5+$R$6)*$R$10^$R$11,1) -> 94.4 | M3: =ROUND(7.9*$R$8*($R$5+$R$6)*$R$10^$R$11,1) -> 96.8 | N3: =ROUND(8.2*$R$8*($R$5+$R$6)*$R$10^$R$11,1) -> 100.5 | P3: =ROUND(((2321842.77+2995668+2056861.6)/3)*$R$10^5/1000000,1) -> 2.6
A4: Sullivan Heights Secondary | B4: =ROUND(5*$R$8*($R$5+$R$6)*$R$10^$R$11,1) -> 61.3 | C4: =ROUND(5.3*$R$8*($R$5+$R$6)*$R$10^$R$11,1) -> 65 | D4: =ROUND(5.6*$R$8*($R$5+$R$6)*$R$10^$R$11,1) -> 68.6 | E4: =ROUND(5.8*$R$8*($R$5+$R$6)*$R$10^$R$11,1) -> 71.1 | F4: =ROUND(6.1*$R$8*($R$5+$R$6)*$R$10^$R$11,1) -> 74.8 | G4: =ROUND(6.3*$R$8*($R$5+$R$6)*$R$10^$R$11,1) -> 77.2 | H4: =ROUND(6.6*$R$8*($R$5+$R$6)*$R$10^$R$11,1) -> 80.9 | I4: =ROUND(6.8*$R$8*($R$5+$R$6)*$R$10^$R$11,1) -> 83.3 | J4: =ROUND(7.1*$R$8*($R$5+$R$6)*$R$10^$R$11,1) -> 87 | K4: =ROUND(7.4*$R$8*($R$5+$R$6)*$R$10^$R$11,1) -> 90.7 | L4: =ROUND(7.7*$R$8*($R$5+$R$6)*$R$10^$R$11,1) -> 94.4 | M4: =ROUND(7.9*$R$8*($R$5+$R$6)*$R$10^$R$11,1) -> 96.8 | N4: =ROUND(8.2*$R$8*($R$5+$R$6)*$R$10^$R$11,1) -> 100.5 | P4: =ROUND(((2321842.77+2995668+2056861.6)/3)*$R$10^4/1000000,1) -> 2.6 | Q4: ESTIMATION MADE IN 2014 (IN MILLIONS)
A5: Ecole Earl Marriott | B5: =ROUND(5*$R$8*($R$5+$R$6)*$R$10^$R$11,1) -> 61.3 | C5: =ROUND(5.3*$R$8*($R$5+$R$6)*$R$10^$R$11,1) -> 65 | D5: =ROUND(5.6*$R$8*($R$5+$R$6)*$R$10^$R$11,1) -> 68.6 | E5: =ROUND(5.8*$R$8*($R$5+$R$6)*$R$10^$R$11,1) -> 71.1 | F5: =ROUND(6.1*$R$8*($R$5+$R$6)*$R$10^$R$11,1) -> 74.8 | G5: =ROUND(6.3*$R$8*($R$5+$R$6)*$R$10^$R$11,1) -> 77.2 | H5: =ROUND(6.6*$R$8*($R$5+$R$6)*$R$10^$R$11,1) -> 80.9 | I5: =ROUND(6.8*$R$8*($R$5+$R$6)*$R$10^$R$11,1) -> 83.3 | J5: =ROUND(7.1*$R$8*($R$5+$R$6)*$R$10^$R$11,1) -> 87 | K5: =ROUND(7.4*$R$8*($R$5+$R$6)*$R$10^$R$11,1) -> 90.7 | L5: =ROUND(7.7*$R$8*($R$5+$R$6)*$R$10^$R$11,1) -> 94.4 | M5: =ROUND(7.9*$R$8*($R$5+$R$6)*$R$10^$R$11,1) -> 96.8 | N5: =ROUND(8.2*$R$8*($R$5+$R$6)*$R$10^$R$11,1) -> 100.5 | P5: =ROUND(((2321842.77+2995668+2056861.6)/3)*$R$10^4/1000000,1) -> 2.6 | Q5: Cost of Site Purchase Per Hectare: | R5: =((6/6.2+15/15)/2)*2.47105 -> 2.4311944
A6: Ecole Kwantlen Park | B6: =ROUND(5*$R$8*($R$5+$R$6)*$R$10^$R$11,1) -> 61.3 | C6: =ROUND(5.3*$R$8*($R$5+$R$6)*$R$10^$R$11,1) -> 65 | D6: =ROUND(5.6*$R$8*($R$5+$R$6)*$R$10^$R$11,1) -> 68.6 | E6: =ROUND(5.8*$R$8*($R$5+$R$6)*$R$10^$R$11,1) -> 71.1 | F6: =ROUND(6.1*$R$8*($R$5+$R$6)*$R$10^$R$11,1) -> 74.8 | G6: =ROUND(6.3*$R$8*($R$5+$R$6)*$R$10^$R$11,1) -> 77.2 | H6: =ROUND(6.6*$R$8*($R$5+$R$6)*$R$10^$R$11,1) -> 80.9 | I6: =ROUND(6.8*$R$8*($R$5+$R$6)*$R$10^$R$11,1) -> 83.3 | J6: =ROUND(7.1*$R$8*($R$5+$R$6)*$R$10^$R$11,1) -> 87 | K6: =ROUND(7.4*$R$8*($R$5+$R$6)*$R$10^$R$11,1) -> 90.7 | L6: =ROUND(7.7*$R$8*($R$5+$R$6)*$R$10^$R$11,1) -> 94.4 | M6: =ROUND(7.9*$R$8*($R$5+$R$6)*$R$10^$R$11,1) -> 96.8 | N6: =ROUND(8.2*$R$8*($R$5+$R$6)*$R$10^$R$11,1) -> 100.5 | P6: =ROUND(((2321842.77+2995668+2056861.6)/3)*$R$10^4/1000000,1) -> 2.6 | Q6: Construction Cost Per Hectare (Secondary School): | R6: =(41.5/15)*2.47105 -> 6.8365717
A7: Semiahmoo Secondary | B7: =ROUND(5*$R$8*($R$5+$R$6)*$R$10^$R$11,1) -> 61.3 | C7: =ROUND(5.3*$R$8*($R$5+$R$6)*$R$10^$R$11,1) -> 65 | D7: =ROUND(5.6*$R$8*($R$5+$R$6)*$R$10^$R$11,1) -> 68.6 | E7: =ROUND(5.8*$R$8*($R$5+$R$6)*$R$10^$R$11,1) -> 71.1 | F7: =ROUND(6.1*$R$8*($R$5+$R$6)*$R$10^$R$11,1) -> 74.8 | G7: =ROUND(6.3*$R$8*($R$5+$R$6)*$R$10^$R$11,1) -> 77.2 | H7: =ROUND(6.6*$R$8*($R$5+$R$6)*$R$10^$R$11,1) -> 80.9 | I7: =ROUND(6.8*$R$8*($R$5+$R$6)*$R$10^$R$11,1) -> 83.3 | J7: =ROUND(7.1*$R$8*($R$5+$R$6)*$R$10^$R$11,1) -> 87 | K7: =ROUND(7.4*$R$8*($R$5+$R$6)*$R$10^$R$11,1) -> 90.7 | L7: =ROUND(7.7*$R$8*($R$5+$R$6)*$R$10^$R$11,1) -> 94.4 | M7: =ROUND(7.9*$R$8*($R$5+$R$6)*$R$10^$R$11,1) -> 96.8 | N7: =ROUND(8.2*$R$8*($R$5+$R$6)*$R$10^$R$11,1) -> 100.5 | P7: =ROUND(((2321842.77+2995668+2056861.6)/3)*$R$10^4/1000000,1) -> 2.6 | Q7: Construction Cost Per Hectare (Elementary School): | R7: =(14/6.2)*2.47105 -> 5.5797903
A8: Tamanawis Secondary | B8: =ROUND(5*$R$8*($R$5+$R$6)*$R$10^$R$11,1) -> 61.3 | C8: =ROUND(5.3*$R$8*($R$5+$R$6)*$R$10^$R$11,1) -> 65 | D8: =ROUND(5.6*$R$8*($R$5+$R$6)*$R$10^$R$11,1) -> 68.6 | E8: =ROUND(5.8*$R$8*($R$5+$R$6)*$R$10^$R$11,1) -> 71.1 | F8: =ROUND(6.1*$R$8*($R$5+$R$6)*$R$10^$R$11,1) -> 74.8 | G8: =ROUND(6.3*$R$8*($R$5+$R$6)*$R$10^$R$11,1) -> 77.2 | H8: =ROUND(6.6*$R$8*($R$5+$R$6)*$R$10^$R$11,1) -> 80.9 | I8: =ROUND(6.8*$R$8*($R$5+$R$6)*$R$10^$R$11,1) -> 83.3 | J8: =ROUND(7.1*$R$8*($R$5+$R$6)*$R$10^$R$11,1) -> 87 | K8: =ROUND(7.4*$R$8*($R$5+$R$6)*$R$10^$R$11,1) -> 90.7 | L8: =ROUND(7.7*$R$8*($R$5+$R$6)*$R$10^$R$11,1) -> 94.4 | M8: =ROUND(7.9*$R$8*($R$5+$R$6)*$R$10^$R$11,1) -> 96.8 | N8: =ROUND(8.2*$R$8*($R$5+$R$6)*$R$10^$R$11,1) -> 100.5 | P8: =ROUND(((2321842.77+2995668+2056861.6)/3)*$R$10^4/1000000,1) -> 2.6 | Q8: Typical purchased site size factor (Secondary): | R8: 1.21
A9: Clayton Heights Secondary | B9: =ROUND(5*$R$8*($R$5+$R$6)*$R$10^$R$11,1) -> 61.3 | C9: =ROUND(5.3*$R$8*($R$5+$R$6)*$R$10^$R$11,1) -> 65 | D9: =ROUND(5.6*$R$8*($R$5+$R$6)*$R$10^$R$11,1) -> 68.6 | E9: =ROUND(5.8*$R$8*($R$5+$R$6)*$R$10^$R$11,1) -> 71.1 | F9: =ROUND(6.1*$R$8*($R$5+$R$6)*$R$10^$R$11,1) -> 74.8 | G9: =ROUND(6.3*$R$8*($R$5+$R$6)*$R$10^$R$11,1) -> 77.2 | H9: =ROUND(6.6*$R$8*($R$5+$R$6)*$R$10^$R$11,1) -> 80.9 | I9: =ROUND(6.8*$R$8*($R$5+$R$6)*$R$10^$R$11,1) -> 83.3 | J9: =ROUND(7.1*$R$8*($R$5+$R$6)*$R$10^$R$11,1) -> 87 | K9: =ROUND(7.4*$R$8*($R$5+$R$6)*$R$10^$R$11,1) -> 90.7 | L9: =ROUND(7.7*$R$8*($R$5+$R$6)*$R$10^$R$11,1) -> 94.4 | M9: =ROUND(7.9*$R$8*($R$5+$R$6)*$R$10^$R$11,1) -> 96.8 | N9: =ROUND(8.2*$R$8*($R$5+$R$6)*$R$10^$R$11,1) -> 100.5 | P9: =ROUND(((2321842.77+2995668+2056861.6)/3)*$R$10^4/1000000,1) -> 2.6 | Q9: Typical purchased site size factor (Elementary): | R9: 1.06
A10: Fleetwood Park Secondary | B10: =ROUND(5*$R$8*($R$5+$R$6)*$R$10^$R$11,1) -> 61.3 | C10: =ROUND(5.3*$R$8*($R$5+$R$6)*$R$10^$R$11,1) -> 65 | D10: =ROUND(5.6*$R$8*($R$5+$R$6)*$R$10^$R$11,1) -> 68.6 | E10: =ROUND(5.8*$R$8*($R$5+$R$6)*$R$10^$R$11,1) -> 71.1 | F10: =ROUND(6.1*$R$8*($R$5+$R$6)*$R$10^$R$11,1) -> 74.8 | G10: =ROUND(6.3*$R$8*($R$5+$R$6)*$R$10^$R$11,1) -> 77.2 | H10: =ROUND(6.6*$R$8*($R$5+$R$6)*$R$10^$R$11,1) -> 80.9 | I10: =ROUND(6.8*$R$8*($R$5+$R$6)*$R$10^$R$11,1) -> 83.3 | J10: =ROUND(7.1*$R$8*($R$5+$R$6)*$R$10^$R$11,1) -> 87 | K10: =ROUND(7.4*$R$8*($R$5+$R$6)*$R$10^$R$11,1) -> 90.7 | L10: =ROUND(7.7*$R$8*($R$5+$R$6)*$R$10^$R$11,1) -> 94.4 | M10: =ROUND(7.9*$R$8*($R$5+$R$6)*$R$10^$R$11,1) -> 96.8 | N10: =ROUND(8.2*$R$8*($R$5+$R$6)*$R$10^$R$11,1) -> 100.5 | P10: =ROUND(((2321842.77+2995668+2056861.6)/3)*$R$10^4/1000000,1) -> 2.6 | Q10: Average inflation rate (2011-2016): | R10: =(((2.3+0.83+1.24+1.47+1.61+1.5)/6)/100)+1 -> 1.0149167
A11: Guildford Park Secondary | B11: =ROUND(5*$R$8*($R$5+$R$6)*$R$10^$R$11,1) -> 61.3 | C11: =ROUND(5.3*$R$8*($R$5+$R$6)*$R$10^$R$11,1) -> 65 | D11: =ROUND(5.6*$R$8*($R$5+$R$6)*$R$10^$R$11,1) -> 68.6 | E11: =ROUND(5.8*$R$8*($R$5+$R$6)*$R$10^$R$11,1) -> 71.1 | F11: =ROUND(6.1*$R$8*($R$5+$R$6)*$R$10^$R$11,1) -> 74.8 | G11: =ROUND(6.3*$R$8*($R$5+$R$6)*$R$10^$R$11,1) -> 77.2 | H11: =ROUND(6.6*$R$8*($R$5+$R$6)*$R$10^$R$11,1) -> 80.9 | I11: =ROUND(6.8*$R$8*($R$5+$R$6)*$R$10^$R$11,1) -> 83.3 | J11: =ROUND(7.1*$R$8*($R$5+$R$6)*$R$10^$R$11,1) -> 87 | K11: =ROUND(7.4*$R$8*($R$5+$R$6)*$R$10^$R$11,1) -> 90.7 | L11: =ROUND(7.7*$R$8*($R$5+$R$6)*$R$10^$R$11,1) -> 94.4 | M11: =ROUND(7.9*$R$8*($R$5+$R$6)*$R$10^$R$11,1) -> 96.8 | N11: =ROUND(8.2*$R$8*($R$5+$R$6)*$R$10^$R$11,1) -> 100.5 | P11: =ROUND(((2321842.77+2995668+2056861.6)/3)*$R$10^4/1000000,1) -> 2.6 | Q11: Number of years to bring forward to 2020: | R11: 6
A12: North Surrey Secondary | B12: =ROUND(5*$R$8*($R$5+$R$6)*$R$10^$R$11,1) -> 61.3 | C12: =ROUND(5.3*$R$8*($R$5+$R$6)*$R$10^$R$11,1) -> 65 | D12: =ROUND(5.6*$R$8*($R$5+$R$6)*$R$10^$R$11,1) -> 68.6 | E12: =ROUND(5.8*$R$8*($R$5+$R$6)*$R$10^$R$11,1) -> 71.1 | F12: =ROUND(6.1*$R$8*($R$5+$R$6)*$R$10^$R$11,1) -> 74.8 | G12: =ROUND(6.3*$R$8*($R$5+$R$6)*$R$10^$R$11,1) -> 77.2 | H12: =ROUND(6.6*$R$8*($R$5+$R$6)*$R$10^$R$11,1) -> 80.9 | I12: =ROUND(6.8*$R$8*($R$5+$R$6)*$R$10^$R$11,1) -> 83.3 | J12: =ROUND(7.1*$R$8*($R$5+$R$6)*$R$10^$R$11,1) -> 87 | K12: =ROUND(7.4*$R$8*($R$5+$R$6)*$R$10^$R$11,1) -> 90.7 | L12: =ROUND(7.7*$R$8*($R$5+$R$6)*$R$10^$R$11,1) -> 94.4 | M12: =ROUND(7.9*$R$8*($R$5+$R$6)*$R$10^$R$11,1) -> 96.8 | N12: =ROUND(8.2*$R$8*($R$5+$R$6)*$R$10^$R$11,1) -> 100.5 | P12: =ROUND(((2321842.77+2995668+2056861.6)/3)*$R$10^4/1000000,1) -> 2.6
A13: Ecole Fraser Heights | B13: =ROUND(5*$R$8*($R$5+$R$6)*$R$10^$R$11,1) -> 61.3 | C13: =ROUND(5.3*$R$8*($R$5+$R$6)*$R$10^$R$11,1) -> 65 | D13: =ROUND(5.6*$R$8*($R$5+$R$6)*$R$10^$R$11,1) -> 68.6 | E13: =ROUND(5.8*$R$8*($R$5+$R$6)*$R$10^$R$11,1) -> 71.1 | F13: =ROUND(6.1*$R$8*($R$5+$R$6)*$R$10^$R$11,1) -> 74.8 | G13: =ROUND(6.3*$R$8*($R$5+$R$6)*$R$10^$R$11,1) -> 77.2 | H13: =ROUND(6.6*$R$8*($R$5+$R$6)*$R$10^$R$11,1) -> 80.9 | I13: =ROUND(6.8*$R$8*($R$5+$R$6)*$R$10^$R$11,1) -> 83.3 | J13: =ROUND(7.1*$R$8*($R$5+$R$6)*$R$10^$R$11,1) -> 87 | K13: =ROUND(7.4*$R$8*($R$5+$R$6)*$R$10^$R$11,1) -> 90.7 | L13: =ROUND(7.7*$R$8*($R$5+$R$6)*$R$10^$R$11,1) -> 94.4 | M13: =ROUND(7.9*$R$8*($R$5+$R$6)*$R$10^$R$11,1) -> 96.8 | N13: =ROUND(8.2*$R$8*($R$5+$R$6)*$R$10^$R$11,1) -> 100.5 | P13: =ROUND(((2321842.77+2995668+2056861.6)/3)*$R$10^4/1000000,1) -> 2.6
A14: Ecole Panorama Ridge | B14: =ROUND(5*$R$8*($R$5+$R$6)*$R$10^$R$11,1) -> 61.3 | C14: =ROUND(5.3*$R$8*($R$5+$R$6)*$R$10^$R$11,1) -> 65 | D14: =ROUND(5.6*$R$8*($R$5+$R$6)*$R$10^$R$11,1) -> 68.6 | E14: =ROUND(5.8*$R$8*($R$5+$R$6)*$R$10^$R$11,1) -> 71.1 | F14: =ROUND(6.1*$R$8*($R$5+$R$6)*$R$10^$R$11,1) -> 74.8 | G14: =ROUND(6.3*$R$8*($R$5+$R$6)*$R$10^$R$11,1) -> 77.2 | H14: =ROUND(6.6*$R$8*($R$5+$R$6)*$R$10^$R$11,1) -> 80.9 | I14: =ROUND(6.8*$R$8*($R$5+$R$6)*$R$10^$R$11,1) -> 83.3 | J14: =ROUND(7.1*$R$8*($R$5+$R$6)*$R$10^$R$11,1) -> 87 | K14: =ROUND(7.4*$R$8*($R$5+$R$6)*$R$10^$R$11,1) -> 90.7 | L14: =ROUND(7.7*$R$8*($R$5+$R$6)*$R$10^$R$11,1) -> 94.4 | M14: =ROUND(7.9*$R$8*($R$5+$R$6)*$R$10^$R$11,1) -> 96.8 | N14: =ROUND(8.2*$R$8*($R$5+$R$6)*$R$10^$R$11,1) -> 100.5 | P14: =ROUND(((2321842.77+2995668+2056861.6)/3)*$R$10^4/1000000,1) -> 2.6
A15: Frank Hurt Secondary | B15: =ROUND(5*$R$8*($R$5+$R$6)*$R$10^$R$11,1) -> 61.3 | C15: =ROUND(5.3*$R$8*($R$5+$R$6)*$R$10^$R$11,1) -> 65 | D15: =ROUND(5.6*$R$8*($R$5+$R$6)*$R$10^$R$11,1) -> 68.6 | E15: =ROUND(5.8*$R$8*($R$5+$R$6)*$R$10^$R$11,1) -> 71.1 | F15: =ROUND(6.1*$R$8*($R$5+$R$6)*$R$10^$R$11,1) -> 74.8 | G15: =ROUND(6.3*$R$8*($R$5+$R$6)*$R$10^$R$11,1) -> 77.2 | H15: =ROUND(6.6*$R$8*($R$5+$R$6)*$R$10^$R$11,1) -> 80.9 | I15: =ROUND(6.8*$R$8*($R$5+$R$6)*$R$10^$R$11,1) -> 83.3 | J15: =ROUND(7.1*$R$8*($R$5+$R$6)*$R$10^$R$11,1) -> 87 | K15: =ROUND(7.4*$R$8*($R$5+$R$6)*$R$10^$R$11,1) -> 90.7 | L15: =ROUND(7.7*$R$8*($R$5+$R$6)*$R$10^$R$11,1) -> 94.4 | M15: =ROUND(7.9*$R$8*($R$5+$R$6)*$R$10^$R$11,1) -> 96.8 | N15: =ROUND(8.2*$R$8*($R$5+$R$6)*$R$10^$R$11,1) -> 100.5 | P15: =ROUND(((2321842.77+2995668+2056861.6)/3)*$R$10^4/1000000,1) -> 2.6
A16: Ecole Elgin Park | B16: =ROUND(5*$R$8*($R$5+$R$6)*$R$10^$R$11,1) -> 61.3 | C16: =ROUND(5.3*$R$8*($R$5+$R$6)*$R$10^$R$11,1) -> 65 | D16: =ROUND(5.6*$R$8*($R$5+$R$6)*$R$10^$R$11,1) -> 68.6 | E16: =ROUND(5.8*$R$8*($R$5+$R$6)*$R$10^$R$11,1) -> 71.1 | F16: =ROUND(6.1*$R$8*($R$5+$R$6)*$R$10^$R$11,1) -> 74.8 | G16: =ROUND(6.3*$R$8*($R$5+$R$6)*$R$10^$R$11,1) -> 77.2 | H16: =ROUND(6.6*$R$8*($R$5+$R$6)*$R$10^$R$11,1) -> 80.9 | I16: =ROUND(6.8*$R$8*($R$5+$R$6)*$R$10^$R$11,1) -> 83.3 | J16: =ROUND(7.1*$R$8*($R$5+$R$6)*$R$10^$R$11,1) -> 87 | K16: =ROUND(7.4*$R$8*($R$5+$R$6)*$R$10^$R$11,1) -> 90.7 | L16: =ROUND(7.7*$R$8*($R$5+$R$6)*$R$10^$R$11,1) -> 94.4 | M16: =ROUND(7.9*$R$8*($R$5+$R$6)*$R$10^$R$11,1) -> 96.8 | N16: =ROUND(8.2*$R$8*($R$5+$R$6)*$R$10^$R$11,1) -> 100.5 | P16: =ROUND(((2321842.77+2995668+2056861.6)/3)*$R$10^4/1000000,1) -> 2.6
A17: Enver Creek Secondary | B17: =ROUND(5*$R$8*($R$5+$R$6)*$R$10^$R$11,1) -> 61.3 | C17: =ROUND(5.3*$R$8*($R$5+$R$6)*$R$10^$R$11,1) -> 65 | D17: =ROUND(5.6*$R$8*($R$5+$R$6)*$R$10^$R$11,1) -> 68.6 | E17: =ROUND(5.8*$R$8*($R$5+$R$6)*$R$10^$R$11,1) -> 71.1 | F17: =ROUND(6.1*$R$8*($R$5+$R$6)*$R$10^$R$11,1) -> 74.8 | G17: =ROUND(6.3*$R$8*($R$5+$R$6)*$R$10^$R$11,1) -> 77.2 | H17: =ROUND(6.6*$R$8*($R$5+$R$6)*$R$10^$R$11,1) -> 80.9 | I17: =ROUND(6.8*$R$8*($R$5+$R$6)*$R$10^$R$11,1) -> 83.3 | J17: =ROUND(7.1*$R$8*($R$5+$R$6)*$R$10^$R$11,1) -> 87 | K17: =ROUND(7.4*$R$8*($R$5+$R$6)*$R$10^$R$11,1) -> 90.7 | L17: =ROUND(7.7*$R$8*($R$5+$R$6)*$R$10^$R$11,1) -> 94.4 | M17: =ROUND(7.9*$R$8*($R$5+$R$6)*$R$10^$R$11,1) -> 96.8 | N17: =ROUND(8.2*$R$8*($R$5+$R$6)*$R$10^$R$11,1) -> 100.5 | P17: =ROUND(((2321842.77+2995668+2056861.6)/3)*$R$10^4/1000000,1) -> 2.6
A18: Johnston Heights Secondary | B18: =ROUND(5*$R$8*($R$5+$R$6)*$R$10^$R$11,1) -> 61.3 | C18: =ROUND(5.3*$R$8*($R$5+$R$6)*$R$10^$R$11,1) -> 65 | D18: =ROUND(5.6*$R$8*($R$5+$R$6)*$R$10^$R$11,1) -> 68.6 | E18: =ROUND(5.8*$R$8*($R$5+$R$6)*$R$10^$R$11,1) -> 71.1 | F18: =ROUND(6.1*$R$8*($R$5+$R$6)*$R$10^$R$11,1) -> 74.8 | G18: =ROUND(6.3*$R$8*($R$5+$R$6)*$R$10^$R$11,1) -> 77.2 | H18: =ROUND(6.6*$R$8*($R$5+$R$6)*$R$10^$R$11,1) -> 80.9 | I18: =ROUND(6.8*$R$8*($R$5+$R$6)*$R$10^$R$11,1) -> 83.3 | J18: =ROUND(7.1*$R$8*($R$5+$R$6)*$R$10^$R$11,1) -> 87 | K18: =ROUND(7.4*$R$8*($R$5+$R$6)*$R$10^$R$11,1) -> 90.7 | L18: =ROUND(7.7*$R$8*($R$5+$R$6)*$R$10^$R$11,1) -> 94.4 | M18: =ROUND(7.9*$R$8*($R$5+$R$6)*$R$10^$R$11,1) -> 96.8 | N18: =ROUND(8.2*$R$8*($R$5+$R$6)*$R$10^$R$11,1) -> 100.5 | P18: =ROUND(((2321842.77+2995668+2056861.6)/3)*$R$10^4/1000000,1) -> 2.6
A19: Queen Elizabeth Secondary | B19: =ROUND(5*$R$8*($R$5+$R$6)*$R$10^$R$11,1) -> 61.3 | C19: =ROUND(5.3*$R$8*($R$5+$R$6)*$R$10^$R$11,1) -> 65 | D19: =ROUND(5.6*$R$8*($R$5+$R$6)*$R$10^$R$11,1) -> 68.6 | E19: =ROUND(5.8*$R$8*($R$5+$R$6)*$R$10^$R$11,1) -> 71.1 | F19: =ROUND(6.1*$R$8*($R$5+$R$6)*$R$10^$R$11,1) -> 74.8 | G19: =ROUND(6.3*$R$8*($R$5+$R$6)*$R$10^$R$11,1) -> 77.2 | H19: =ROUND(6.6*$R$8*($R$5+$R$6)*$R$10^$R$11,1) -> 80.9 | I19: =ROUND(6.8*$R$8*($R$5+$R$6)*$R$10^$R$11,1) -> 83.3 | J19: =ROUND(7.1*$R$8*($R$5+$R$6)*$R$10^$R$11,1) -> 87 | K19: =ROUND(7.4*$R$8*($R$5+$R$6)*$R$10^$R$11,1) -> 90.7 | L19: =ROUND(7.7*$R$8*($R$5+$R$6)*$R$10^$R$11,1) -> 94.4 | M19: =ROUND(7.9*$R$8*($R$5+$R$6)*$R$10^$R$11,1) -> 96.8 | N19: =ROUND(8.2*$R$8*($R$5+$R$6)*$R$10^$R$11,1) -> 100.5 | P19: =ROUND(((2321842.77+2995668+2056861.6)/3)*$R$10^4/1000000,1) -> 2.6
A20: Princess Margaret Secondary | B20: =ROUND(5*$R$8*($R$5+$R$6)*$R$10^$R$11,1) -> 61.3 | C20: =ROUND(5.3*$R$8*($R$5+$R$6)*$R$10^$R$11,1) -> 65 | D20: =ROUND(5.6*$R$8*($R$5+$R$6)*$R$10^$R$11,1) -> 68.6 | E20: =ROUND(5.8*$R$8*($R$5+$R$6)*$R$10^$R$11,1) -> 71.1 | F20: =ROUND(6.1*$R$8*($R$5+$R$6)*$R$10^$R$11,1) -> 74.8 | G20: =ROUND(6.3*$R$8*($R$5+$R$6)*$R$10^$R$11,1) -> 77.2 | H20: =ROUND(6.6*$R$8*($R$5+$R$6)*$R$10^$R$11,1) -> 80.9 | I20: =ROUND(6.8*$R$8*($R$5+$R$6)*$R$10^$R$11,1) -> 83.3 | J20: =ROUND(7.1*$R$8*($R$5+$R$6)*$R$10^$R$11,1) -> 87 | K20: =ROUND(7.4*$R$8*($R$5+$R$6)*$R$10^$R$11,1) -> 90.7 | L20: =ROUND(7.7*$R$8*($R$5+$R$6)*$R$10^$R$11,1) -> 94.4 | M20: =ROUND(7.9*$R$8*($R$5+$R$6)*$R$10^$R$11,1) -> 96.8 | N20: =ROUND(8.2*$R$8*($R$5+$R$6)*$R$10^$R$11,1) -> 100.5 | P20: =ROUND(((2321842.77+2995668+2056861.6)/3)*$R$10^4/1000000,1) -> 2.6
A21: L. A. Matheson Secondary | B21: =ROUND(5*$R$8*($R$5+$R$6)*$R$10^$R$11,1) -> 61.3 | C21: =ROUND(5.3*$R$8*($R$5+$R$6)*$R$10^$R$11,1) -> 65 | D21: =ROUND(5.6*$R$8*($R$5+$R$6)*$R$10^$R$11,1) -> 68.6 | E21: =ROUND(5.8*$R$8*($R$5+$R$6)*$R$10^$R$11,1) -> 71.1 | F21: =ROUND(6.1*$R$8*($R$5+$R$6)*$R$10^$R$11,1) -> 74.8 | G21: =ROUND(6.3*$R$8*($R$5+$R$6)*$R$10^$R$11,1) -> 77.2 | H21: =ROUND(6.6*$R$8*($R$5+$R$6)*$R$10^$R$11,1) -> 80.9 | I21: =ROUND(6.8*$R$8*($R$5+$R$6)*$R$10^$R$11,1) -> 83.3 | J21: =ROUND(7.1*$R$8*($R$5+$R$6)*$R$10^$R$11,1) -> 87 | K21: =ROUND(7.4*$R$8*($R$5+$R$6)*$R$10^$R$11,1) -> 90.7 | L21: =ROUND(7.7*$R$8*($R$5+$R$6)*$R$10^$R$11,1) -> 94.4 | M21: =ROUND(7.9*$R$8*($R$5+$R$6)*$R$10^$R$11,1) -> 96.8 | N21: =ROUND(8.2*$R$8*($R$5+$R$6)*$R$10^$R$11,1) -> 100.5 | P21: =ROUND(((2321842.77+2995668+2056861.6)/3)*$R$10^4/1000000,1) -> 2.6
B22: =$P$22/100*B2 -> 46 | C22: =$P$22/100*C2 -> 50.6 | D22: =$P$22/100*D2 -> 55.2 | E22: =$P$22/100*E2 -> 59.8 | F22: =$P$22/100*F2 -> 64.4 | G22: =$P$22/100*G2 -> 69 | H22: =$P$22/100*H2 -> 73.6 | I22: =$P$22/100*I2 -> 78.2 | ... N22: =$P$22/100*N2 -> 101.2 | P22: 4.6
A23: ELEMENTARY SCHOOL | B23: 200 | C23: 250 | D23: 300 | E23: 350 | F23: 400 | G23: 450 | H23: 500 | I23: 550 | J23: 600 | K23: 650 | L23: 700 | M23: 750 | N23: 800
A24: A. H. P. Matthew Elementary | B24: =ROUND(1.5*$R$9*($R$5+$R$7)*$R$10^$R$11,1) -> 13.9 | C24: =ROUND(1.6*$R$9*($R$5+$R$7)*$R$10^$R$11,1) -> 14.8 | D24: =ROUND(1.8*$R$9*($R$5+$R$7)*$R$10^$R$11,1) -> 16.7 | E24: =ROUND(1.9*$R$9*($R$5+$R$7)*$R$10^$R$11,1) -> 17.6 | F24: =ROUND(2.3*$R$9*($R$5+$R$7)*$R$10^$R$11,1) -> 21.3 | G24: =ROUND(2.5*$R$9*($R$5+$R$7)*$R$10^$R$11,1) -> 23.2 | H24: =ROUND(2.7*$R$9*($R$5+$R$7)*$R$10^$R$11,1) -> 25.1 | I24: =ROUND(2.8*$R$9*($R$5+$R$7)*$R$10^$R$11,1) -> 26 | J24: =ROUND(3*$R$9*($R$5+$R$7)*$R$10^$R$11,1) -> 27.8 | K24: =ROUND(3.1*$R$9*($R$5+$R$7)*$R$10^$R$11,1) -> 28.8 | L24: =ROUND(3.3*$R$9*($R$5+$R$7)*$R$10^$R$11,1) -> 30.6 | M24: =ROUND(3.5*$R$9*($R$5+$R$7)*$R$10^$R$11,1) -> 32.5 | N24: =ROUND(3.7*$R$9*($R$5+$R$7)*$R$10^$R$11,1) -> 34.3 | P24: =ROUND((((1769627.56+2356492.31)/2)/1000000)*$R$10^4,1) -> 2.2
A25: K - 7 A. J. McLellan Elementary | B25: =ROUND(1.5*$R$9*($R$5+$R$7)*$R$10^$R$11,1) -> 13.9 | C25: =ROUND(1.6*$R$9*($R$5+$R$7)*$R$10^$R$11,1) -> 14.8 | D25: =ROUND(1.8*$R$9*($R$5+$R$7)*$R$10^$R$11,1) -> 16.7 | E25: =ROUND(1.9*$R$9*($R$5+$R$7)*$R$10^$R$11,1) -> 17.6 | F25: =ROUND(2.3*$R$9*($R$5+$R$7)*$R$10^$R$11,1) -> 21.3 | G25: =ROUND(2.5*$R$9*($R$5+$R$7)*$R$10^$R$11,1) -> 23.2 | H25: =ROUND(2.7*$R$9*($R$5+$R$7)*$R$10^$R$11,1) -> 25.1 | I25: =ROUND(2.8*$R$9*($R$5+$R$7)*$R$10^$R$11,1) -> 26 | J25: =ROUND(3*$R$9*($R$5+$R$7)*$R$10^$R$11,1) -> 27.8 | K25: =ROUND(3.1*$R$9*($R$5+$R$7)*$R$10^$R$11,1) -> 28.8 | L25: =ROUND(3.3*$R$9*($R$5+$R$7)*$R$10^$R$11,1) -> 30.6 | M25: =ROUND(3.5*$R$9*($R$5+$R$7)*$R$10^$R$11,1) -> 32.5 | N25: =ROUND(3.7*$R$9*($R$5+$R$7)*$R$10^$R$11,1) -> 34.3 | P25: =ROUND((((1769627.56+2356492.31)/2)/1000000)*$R$10^4,1) -> 2.2
A26: K - 7 Adams Road Elementary | B26: =ROUND(1.5*$R$9*($R$5+$R$7)*$R$10^$R$11,1) -> 13.9 | C26: =ROUND(1.6*$R$9*($R$5+$R$7)*$R$10^$R$11,1) -> 14.8 | D26: =ROUND(1.8*$R$9*($R$5+$R$7)*$R$10^$R$11,1) -> 16.7 | E26: =ROUND(1.9*$R$9*($R$5+$R$7)*$R$10^$R$11,1) -> 17.6 | F26: =ROUND(2.3*$R$9*($R$5+$R$7)*$R$10^$R$11,1) -> 21.3 | G26: =ROUND(2.5*$R$9*($R$5+$R$7)*$R$10^$R$11,1) -> 23.2 | H26: =ROUND(2.7*$R$9*($R$5+$R$7)*$R$10^$R$11,1) -> 25.1 | I26: =ROUND(2.8*$R$9*($R$5+$R$7)*$R$10^$R$11,1) -> 26 | J26: =ROUND(3*$R$9*($R$5+$R$7)*$R$10^$R$11,1) -> 27.8 | K26: =ROUND(3.1*$R$9*($R$5+$R$7)*$R$10^$R$11,1) -> 28.8 | L26: =ROUND(3.3*$R$9*($R$5+$R$7)*$R$10^$R$11,1) -> 30.6 | M26: =ROUND(3.5*$R$9*($R$5+$R$7)*$R$10^$R$11,1) -> 32.5 | N26: =ROUND(3.7*$R$9*($R$5+$R$7)*$R$10^$R$11,1) -> 34.3 | P26: =ROUND((((1769627.56+2356492.31)/2)/1000000)*$R$10^4,1) -> 2.2
A27: K - 7 Bayridge Elementary | B27: =ROUND(1.5*$R$9*($R$5+$R$7)*$R$10^$R$11,1) -> 13.9 | C27: =ROUND(1.6*$R$9*($R$5+$R$7)*$R$10^$R$11,1) -> 14.8 | D27: =ROUND(1.8*$R$9*($R$5+$R$7)*$R$10^$R$11,1) -> 16.7 | E27: =ROUND(1.9*$R$9*($R$5+$R$7)*$R$10^$R$11,1) -> 17.6 | F27: =ROUND(2.3*$R$9*($R$5+$R$7)*$R$10^$R$11,1) -> 21.3 | G27: =ROUND(2.5*$R$9*($R$5+$R$7)*$R$10^$R$11,1) -> 23.2 | H27: =ROUND(2.7*$R$9*($R$5+$R$7)*$R$10^$R$11,1) -> 25.1 | I27: =ROUND(2.8*$R$9*($R$5+$R$7)*$R$10^$R$11,1) -> 26 | J27: =ROUND(3*$R$9*($R$5+$R$7)*$R$10^$R$11,1) -> 27.8 | K27: =ROUND(3.1*$R$9*($R$5+$R$7)*$R$10^$R$11,1) -> 28.8 | L27: =ROUND(3.3*$R$9*($R$5+$R$7)*$R$10^$R$11,1) -> 30.6 | M27: =ROUND(3.5*$R$9*($R$5+$R$7)*$R$10^$R$11,1) -> 32.5 | N27: =ROUND(3.7*$R$9*($R$5+$R$7)*$R$10^$R$11,1) -> 34.3 | P27: =ROUND((((1769627.56+2356492.31)/2)/1000000)*$R$10^4,1) -> 2.2
A28: K - 7 Bear Creek Elementary | B28: =ROUND(1.5*$R$9*($R$5+$R$7)*$R$10^$R$11,1) -> 13.9 | C28: =ROUND(1.6*$R$9*($R$5+$R$7)*$R$10^$R$11,1) -> 14.8 | D28: =ROUND(1.8*$R$9*($R$5+$R$7)*$R$10^$R$11,1) -> 16.7 | E28: =ROUND(1.9*$R$9*($R$5+$R$7)*$R$10^$R$11,1) -> 17.6 | F28: =ROUND(2.3*$R$9*($R$5+$R$7)*$R$10^$R$11,1) -> 21.3 | G28: =ROUND(2.5*$R$9*($R$5+$R$7)*$R$10^$R$11,1) -> 23.2 | H28: =ROUND(2.7*$R$9*($R$5+$R$7)*$R$10^$R$11,1) -> 25.1 | I28: =ROUND(2.8*$R$9*($R$5+$R$7)*$R$10^$R$11,1) -> 26 | J28: =ROUND(3*$R$9*($R$5+$R$7)*$R$10^$R$11,1) -> 27.8 | K28: =ROUND(3.1*$R$9*($R$5+$R$7)*$R$10^$R$11,1) -> 28.8 | L28: =ROUND(3.3*$R$9*($R$5+$R$7)*$R$10^$R$11,1) -> 30.6 | M28: =ROUND(3.5*$R$9*($R$5+$R$7)*$R$10^$R$11,1) -> 32.5 | N28: =ROUND(3.7*$R$9*($R$5+$R$7)*$R$10^$R$11,1) -> 34.3 | P28: =ROUND((((1769627.56+2356492.31)/2)/1000000)*$R$10^4,1) -> 2.2
A29: K - 7 Beaver Creek Elementary | B29: =ROUND(1.5*$R$9*($R$5+$R$7)*$R$10^$R$11,1) -> 13.9 | C29: =ROUND(1.6*$R$9*($R$5+$R$7)*$R$10^$R$11,1) -> 14.8 | D29: =ROUND(1.8*$R$9*($R$5+$R$7)*$R$10^$R$11,1) -> 16.7 | E29: =ROUND(1.9*$R$9*($R$5+$R$7)*$R$10^$R$11,1) -> 17.6 | F29: =ROUND(2.3*$R$9*($R$5+$R$7)*$R$10^$R$11,1) -> 21.3 | G29: =ROUND(2.5*$R$9*($R$5+$R$7)*$R$10^$R$11,1) -> 23.2 | H29: =ROUND(2.7*$R$9*($R$5+$R$7)*$R$10^$R$11,1) -> 25.1 | I29: =ROUND(2.8*$R$9*($R$5+$R$7)*$R$10^$R$11,1) -> 26 | J29: =ROUND(3*$R$9*($R$5+$R$7)*$R$10^$R$11,1) -> 27.8 | K29: =ROUND(3.1*$R$9*($R$5+$R$7)*$R$10^$R$11,1) -> 28.8 | L29: =ROUND(3.3*$R$9*($R$5+$R$7)*$R$10^$R$11,1) -> 30.6 | M29: =ROUND(3.5*$R$9*($R$5+$R$7)*$R$10^$R$11,1) -> 32.5 | N29: =ROUND(3.7*$R$9*($R$5+$R$7)*$R$10^$R$11,1) -> 34.3 | P29: =ROUND((((1769627.56+2356492.31)/2)/1000000)*$R$10^4,1) -> 2.2
A30: K - 7 Berkshire Park Elementary | B30: =ROUND(1.5*$R$9*($R$5+$R$7)*$R$10^$R$11,1) -> 13.9 | C30: =ROUND(1.6*$R$9*($R$5+$R$7)*$R$10^$R$11,1) -> 14.8 | D30: =ROUND(1.8*$R$9*($R$5+$R$7)*$R$10^$R$11,1) -> 16.7 | E30: =ROUND(1.9*$R$9*($R$5+$R$7)*$R$10^$R$11,1) -> 17.6 | F30: =ROUND(2.3*$R$9*($R$5+$R$7)*$R$10^$R$11,1) -> 21.3 | G30: =ROUND(2.5*$R$9*($R$5+$R$7)*$R$10^$R$11,1) -> 23.2 | H30: =ROUND(2.7*$R$9*($R$5+$R$7)*$R$10^$R$11,1) -> 25.1 | I30: =ROUND(2.8*$R$9*($R$5+$R$7)*$R$10^$R$11,1) -> 26 | J30: =ROUND(3*$R$9*($R$5+$R$7)*$R$10^$R$11,1) -> 27.8 | K30: =ROUND(3.1*$R$9*($R$5+$R$7)*$R$10^$R$11,1) -> 28.8 | L30: =ROUND(3.3*$R$9*($R$5+$R$7)*$R$10^$R$11,1) -> 30.6 | M30: =ROUND(3.5*$R$9*($R$5+$R$7)*$R$10^$R$11,1) -> 32.5 | N30: =ROUND(3.7*$R$9*($R$5+$R$7)*$R$10^$R$11,1) -> 34.3 | P30: =ROUND((((1769627.56+2356492.31)/2)/1000000)*$R$10^4,1) -> 2.2
A31: K - 7 Betty Huff Elementary | B31: =ROUND(1.5*$R$9*($R$5+$R$7)*$R$10^$R$11,1) -> 13.9 | C31: =ROUND(1.6*$R$9*($R$5+$R$7)*$R$10^$R$11,1) -> 14.8 | D31: =ROUND(1.8*$R$9*($R$5+$R$7)*$R$10^$R$11,1) -> 16.7 | E31: =ROUND(1.9*$R$9*($R$5+$R$7)*$R$10^$R$11,1) -> 17.6 | F31: =ROUND(2.3*$R$9*($R$5+$R$7)*$R$10^$R$11,1) -> 21.3 | G31: =ROUND(2.5*$R$9*($R$5+$R$7)*$R$10^$R$11,1) -> 23.2 | H31: =ROUND(2.7*$R$9*($R$5+$R$7)*$R$10^$R$11,1) -> 25.1 | I31: =ROUND(2.8*$R$9*($R$5+$R$7)*$R$10^$R$11,1) -> 26 | J31: =ROUND(3*$R$9*($R$5+$R$7)*$R$10^$R$11,1) -> 27.8 | K31: =ROUND(3.1*$R$9*($R$5+$R$7)*$R$10^$R$11,1) -> 28.8 | L31: =ROUND(3.3*$R$9*($R$5+$R$7)*$R$10^$R$11,1) -> 30.6 | M31: =ROUND(3.5*$R$9*($R$5+$R$7)*$R$10^$R$11,1) -> 32.5 | N31: =ROUND(3.7*$R$9*($R$5+$R$7)*$R$10^$R$11,1) -> 34.3 | P31: =ROUND((((1769627.56+2356492.31)/2)/1000000)*$R$10^4,1) -> 2.2
A32: K - 7 Bonaccord Elementary | B32: =ROUND(1.5*$R$9*($R$5+$R$7)*$R$10^$R$11,1) -> 13.9 | C32: =ROUND(1.6*$R$9*($R$5+$R$7)*$R$10^$R$11,1) -> 14.8 | D32: =ROUND(1.8*$R$9*($R$5+$R$7)*$R$10^$R$11,1) -> 16.7 | E32: =ROUND(1.9*$R$9*($R$5+$R$7)*$R$10^$R$11,1) -> 17.6 | F32: =ROUND(2.3*$R$9*($R$5+$R$7)*$R$10^$R$11,1) -> 21.3 | G32: =ROUND(2.5*$R$9*($R$5+$R$7)*$R$10^$R$11,1) -> 23.2 | H32: =ROUND(2.7*$R$9*($R$5+$R$7)*$R$10^$R$11,1) -> 25.1 | I32: =ROUND(2.8*$R$9*($R$5+$R$7)*$R$10^$R$11,1) -> 26 | J32: =ROUND(3*$R$9*($R$5+$R$7)*$R$10^$R$11,1) -> 27.8 | K32: =ROUND(3.1*$R$9*($R$5+$R$7)*$R$10^$R$11,1) -> 28.8 | L32: =ROUND(3.3*$R$9*($R$5+$R$7)*$R$10^$R$11,1) -> 30.6 | M32: =ROUND(3.5*$R$9*($R$5+$R$7)*$R$10^$R$11,1) -> 32.5 | N32: =ROUND(3.7*$R$9*($R$5+$R$7)*$R$10^$R$11,1) -> 34.3 | P32: =ROUND((((1769627.56+2356492.31)/2)/1000000)*$R$10^4,1) -> 2.2
A33: K - 7 Bothwell Elementary | B33: =ROUND(1.5*$R$9*($R$5+$R$7)*$R$10^$R$11,1) -> 13.9 | C33: =ROUND(1.6*$R$9*($R$5+$R$7)*$R$10^$R$11,1) -> 14.8 | D33: =ROUND(1.8*$R$9*($R$5+$R$7)*$R$10^$R$11,1) -> 16.7 | E33: =ROUND(1.9*$R$9*($R$5+$R$7)*$R$10^$R$11,1) -> 17.6 | F33: =ROUND(2.3*$R$9*($R$5+$R$7)*$R$10^$R$11,1) -> 21.3 | G33: =ROUND(2.5*$R$9*($R$5+$R$7)*$R$10^$R$11,1) -> 23.2 | H33: =ROUND(2.7*$R$9*($R$5+$R$7)*$R$10^$R$11,1) -> 25.1 | I33: =ROUND(2.8*$R$9*($R$5+$R$7)*$R$10^$R$11,1) -> 26 | J33: =ROUND(3*$R$9*($R$5+$R$7)*$R$10^$R$11,1) -> 27.8 | K33: =ROUND(3.1*$R$9*($R$5+$R$7)*$R$10^$R$11,1) -> 28.8 | L33: =ROUND(3.3*$R$9*($R$5+$R$7)*$R$10^$R$11,1) -> 30.6 | M33: =ROUND(3.5*$R$9*($R$5+$R$7)*$R$10^$R$11,1) -> 32.5 | N33: =ROUND(3.7*$R$9*($R$5+$R$7)*$R$10^$R$11,1) -> 34.3 | P33: =ROUND((((1769627.56+2356492.31)/2)/1000000)*$R$10^4,1) -> 2.2
A34: K - 7 Boundary Park Elementary | B34: =ROUND(1.5*$R$9*($R$5+$R$7)*$R$10^$R$11,1) -> 13.9 | C34: =ROUND(1.6*$R$9*($R$5+$R$7)*$R$10^$R$11,1) -> 14.8 | D34: =ROUND(1.8*$R$9*($R$5+$R$7)*$R$10^$R$11,1) -> 16.7 | E34: =ROUND(1.9*$R$9*($R$5+$R$7)*$R$10^$R$11,1) -> 17.6 | F34: =ROUND(2.3*$R$9*($R$5+$R$7)*$R$10^$R$11,1) -> 21.3 | G34: =ROUND(2.5*$R$9*($R$5+$R$7)*$R$10^$R$11,1) -> 23.2 | H34: =ROUND(2.7*$R$9*($R$5+$R$7)*$R$10^$R$11,1) -> 25.1 | I34: =ROUND(2.8*$R$9*($R$5+$R$7)*$R$10^$R$11,1) -> 26 | J34: =ROUND(3*$R$9*($R$5+$R$7)*$R$10^$R$11,1) -> 27.8 | K34: =ROUND(3.1*$R$9*($R$5+$R$7)*$R$10^$R$11,1) -> 28.8 | L34: =ROUND(3.3*$R$9*($R$5+$R$7)*$R$10^$R$11,1) -> 30.6 | M34: =ROUND(3.5*$R$9*($R$5+$R$7)*$R$10^$R$11,1) -> 32.5 | N34: =ROUND(3.7*$R$9*($R$5+$R$7)*$R$10^$R$11,1) -> 34.3 | P34: =ROUND((((1769627.56+2356492.31)/2)/1000000)*$R$10^4,1) -> 2.2
A35: K - 7 Bridgeview Elementary | B35: =ROUND(1.5*$R$9*($R$5+$R$7)*$R$10^$R$11,1) -> 13.9 | C35: =ROUND(1.6*$R$9*($R$5+$R$7)*$R$10^$R$11,1) -> 14.8 | D35: =ROUND(1.8*$R$9*($R$5+$R$7)*$R$10^$R$11,1) -> 16.7 | E35: =ROUND(1.9*$R$9*($R$5+$R$7)*$R$10^$R$11,1) -> 17.6 | F35: =ROUND(2.3*$R$9*($R$5+$R$7)*$R$10^$R$11,1) -> 21.3 | G35: =ROUND(2.5*$R$9*($R$5+$R$7)*$R$10^$R$11,1) -> 23.2 | H35: =ROUND(2.7*$R$9*($R$5+$R$7)*$R$10^$R$11,1) -> 25.1 | I35: =ROUND(2.8*$R$9*($R$5+$R$7)*$R$10^$R$11,1) -> 26 | J35: =ROUND(3*$R$9*($R$5+$R$7)*$R$10^$R$11,1) -> 27.8 | K35: =ROUND(3.1*$R$9*($R$5+$R$7)*$R$10^$R$11,1) -> 28.8 | L35: =ROUND(3.3*$R$9*($R$5+$R$7)*$R$10^$R$11,1) -> 30.6 | M35: =ROUND(3.5*$R$9*($R$5+$R$7)*$R$10^$R$11,1) -> 32.5 | N35: =ROUND(3.7*$R$9*($R$5+$R$7)*$R$10^$R$11,1) -> 34.3 | P35: =ROUND((((1769627.56+2356492.31)/2)/1000000)*$R$10^4,1) -> 2.2
... A119: K - 7 Woodland Park Elementary | B119: =ROUND(1.5*$R$9*($R$5+$R$7)*$R$10^$R$11,1) -> 13.9 | C119: =ROUND(1.6*$R$9*($R$5+$R$7)*$R$10^$R$11,1) -> 14.8 | D119: =ROUND(1.8*$R$9*($R$5+$R$7)*$R$10^$R$11,1) -> 16.7 | E119: =ROUND(1.9*$R$9*($R$5+$R$7)*$R$10^$R$11,1) -> 17.6 | F119: =ROUND(2.3*$R$9*($R$5+$R$7)*$R$10^$R$11,1) -> 21.3 | G119: =ROUND(2.5*$R$9*($R$5+$R$7)*$R$10^$R$11,1) -> 23.2 | H119: =ROUND(2.7*$R$9*($R$5+$R$7)*$R$10^$R$11,1) -> 25.1 | I119: =ROUND(2.8*$R$9*($R$5+$R$7)*$R$10^$R$11,1) -> 26 | J119: =ROUND(3*$R$9*($R$5+$R$7)*$R$10^$R$11,1) -> 27.8 | K119: =ROUND(3.1*$R$9*($R$5+$R$7)*$R$10^$R$11,1) -> 28.8 | L119: =ROUND(3.3*$R$9*($R$5+$R$7)*$R$10^$R$11,1) -> 30.6 | M119: =ROUND(3.5*$R$9*($R$5+$R$7)*$R$10^$R$11,1) -> 32.5 | N119: =ROUND(3.7*$R$9*($R$5+$R$7)*$R$10^$R$11,1) -> 34.3 | P119: =ROUND((((1769627.56+2356492.31)/2)/1000000)*$R$10^4,1) -> 2.2
B120: =$P$120/100*B23 -> 8.6 | C120: =$P$120/100*C23 -> 10.75 | D120: =$P$120/100*D23 -> 12.9 | E120: =$P$120/100*E23 -> 15.05 | F120: =$P$120/100*F23 -> 17.2 | G120: =$P$120/100*G23 -> 19.35 | H120: =$P$120/100*H23 -> 21.5 | I120: =$P$120/100*I23 -> 23.65 | ... N120: =$P$120/100*N23 -> 34.4 | P120: 4.3

Sheet Capacity
A1: School Name | B1: Location | E1: Grade | F1: Enrollment －2016/17 | G1: Capacity | H1: Overcapacity | J1: Expand (5-year)
A2: Ecole Lord Tweedsmuir | B2: 6151 - 180 St., Surrey, BC V3S 4L5 | E2: 42959 | F2: 2055 | G2: 1400 | H2: =F2-G2 -> 655 | O2: 1 | P2: 1400 | R2: 1 | S2: 2000
A3: Sullivan Heights Secondary | B3: 6248 - 144 St., Surrey, BC V3X 1A1 | E3: 42959 | F3: 1518 | G3: 1000 | H3: =F3-G3 -> 518 | J3: 700 | K3: =G3+J3 -> 1700 | O3: 2 | P3: 1700 | R3: 2 | S3: 2000
A4: Ecole Earl Marriott | B4: 15751 - 16 Ave., Surrey, BC V4A 1S1 | E4: 42959 | F4: 1856 | G4: 1500 | H4: =F4-G4 -> 356 | K4: =G4+1500 -> 3000 | O4: 3 | P4: 1500 | R4: 3 | S4: 2000
A5: Ecole Kwantlen Park | B5: 10441 - 132 St., Surrey, BC V3T 3V3 | E5: 42959 | F5: 1531 | G5: 1200 | H5: =F5-G5 -> 331 | O5: 4 | P5: 1200 | R5: 4 | S5: 2000
A6: Semiahmoo Secondary | B6: 1785 - 148 St., Surrey, BC V4A 4M6 | E6: 42959 | F6: 1623 | G6: 1300 | H6: =F6-G6 -> 323 | O6: 5 | P6: 1300 | R6: 5 | S6: 2000
A7: Tamanawis Secondary | B7: 12600 - 66 Ave., Surrye, BC V3W 2A8 | E7: 42959 | F7: 1446 | G7: 1125 | H7: =F7-G7 -> 321 | J7: 375 | K7: =G7+J7 -> 1500 | O7: 6 | P7: 1500 | R7: 6 | S7: 2000
A8: Clayton Heights Secondary | B8: 7003 - 188 St., Surrey, BC V4N 3G6 | E8: 42959 | F8: 1359 | G8: 1080 | H8: =F8-G8 -> 279 | K8: =G8+1500 -> 2580 | O8: 7 | P8: 1080 | R8: 7 | S8: 2000
A9: Fleetwood Park Secondary | B9: 7940 - 156 St., Surrey, BC V3S 3R3 | E9: 42959 | F9: 1465 | G9: 1200 | H9: =F9-G9 -> 265 | O9: 8 | P9: 1200 | R9: 8 | S9: 2000
A10: Guildford Park Secondary | B10: 10707 - 146 St., Surrey, BC V3R 1T5 | E10: 42959 | F10: 1262 | G10: 1050 | H10: =F10-G10 -> 212 | O10: 9 | P10: 1050 | R10: 9 | S10: 2000
A11: North Surrey Secondary | B11: 15945 - 96 Ave., Surrey, BC V4N 2R8 | E11: 42959 | F11: 1348 | G11: 1175 | H11: =F11-G11 -> 173 | J11: 325 | K11: =G11+J11 -> 1500 | O11: 10 | P11: 1500 | R11: 10 | S11: 2000
A12: Ecole Fraser Heights | B12: 16060 - 108 Ave., Surrey, BC V4N 1M1 | E12: 42959 | F12: 1405 | G12: 1300 | H12: =F12-G12 -> 105 | O12: 11 | P12: 1300 | R12: 11 | S12: 2000
A13: Ecole Panorama Ridge | B13: 13220 - 64 Ave., Surrey, BC V3W 1X9 | E13: 42959 | F13: 1603 | G13: 1525 | H13: =F13-G13 -> 78 | O13: 12 | P13: 1525 | R13: 12 | S13: 2000
A14: Frank Hurt Secondary | B14: 13940 - 77 Ave., Surrey, BC V3W 5Z4 | E14: 42959 | F14: 1215 | G14: 1200 | H14: =F14-G14 -> 15 | O14: 13 | P14: 1200 | R14: 13 | S14: 2000
A15: Ecole Elgin Park | B15: 13484 - 24 Ave., Surrey, BC V4A 2G5 | E15: 42959 | F15: 1206 | G15: 1200 | H15: =F15-G15 -> 6 | O15: 14 | P15: 1200 | R15: 14 | S15: 2000
A16: Enver Creek Secondary | B16: 14505 - 84 Ave., Surrey, BC V3S 8X2 | E16: 42959 | F16: 1347 | G16: 1400 | H16: =F16-G16 -> -53 | O16: 15 | P16: 1400 | R16: 15 | S16: 2000
A17: Johnston Heights Secondary | B17: 15350 - 99 Ave., Surrey, BC V3R 0R9 | E17: 42959 | F17: 1395 | G17: 1450 | H17: =F17-G17 -> -55 | O17: 16 | P17: 1450 | R17: 16 | S17: 2000
A18: Queen Elizabeth Secondary | B18: 9457 - King George Blvd., Surrey, BC V3V 5W4 | E18: 42959 | F18: 1237 | G18: 1400 | H18: =F18-G18 -> -163 | O18: 17 | P18: 1400 | R18: 17 | S18: 2000
A19: Princess Margaret Secondary | B19: 12870 - 72 Ave., Surrey, BC V3W 2M9 | E19: 42959 | F19: 1308 | G19: 1500 | H19: =F19-G19 -> -192 | O19: 18 | P19: 1500 | R19: 18 | S19: 2000
A20: L. A. Matheson Secondary | B20: 9484 - 122 St., Surrey, BC V3V 4M1 | E20: 42959 | F20: 1121 | G20: 1400 | H20: =F20-G20 -> -279 | O20: 19 | P20: 1400 | R20: 19 | S20: 2000
A21: Total | F21: =SUM(F2:F20) -> 27300 | G21: =SUM(G2:G20) -> 24405 | H21: =SUM(H2:H20) -> 2895 | O21: 20 | P21: 1500 | R21: 20 | S21: 2000
O22: 21 | P22: 1500 | R22: 21 | S22: 2000
A23: City Central Learning Centre | B23: 13104 - 109 Ave., Surrey, BC V3T 2N7 | E23: 43020 | F23: 177 | G23: N/A | J23: School | K23: Index | L23: Capacity
A24: Cloverdale Learning Centre | B24: 5658 - 176 St., Surrey, BC V3S 4C6 | E24: 43020 | F24: 151 | G24: N/A | J24: Clayton Heights Secondary | K24: 1 | L24: 2580 | N24: 1 | O24: 3400
A25: Guildford Learning Centre | B25: 10183- 152A St., Surrey, BC V3R 4H6 | E25: 43020 | F25: 149 | G25: N/A | J25: Ecole Earl Marriott | K25: 2 | L25: 3000 | N25: 2 | O25: 3400
A26: North Surrey Learning Centre | B26: 9260 - 140 St., Surrey, BC V3V 5Z4 | E26: 42959 | F26: 176 | G26: N/A | J26: Ecole Elgin Park | K26: 3 | L26: 1200 | N26: 3 | O26: 1700
A27: South Surrey/White Rock Learning Centre | B27: #13 2320 King George Hwy., Surrey, BC V4A 5A5 | E27: 43020 | F27: 142 | G27: N/A | J27: Ecole Fraser Heights | K27: 4 | L27: 1300 | N27: 4 | O27: 1700
A28: Surrey Academy of Innovative Learning | B28: 14033 - 92 Avenue, V3V 0B7 | E28: 43020 | F28: 235 | G28: N/A | J28: Ecole Kwantlen Park | K28: 5 | L28: 1200 | N28: 5 | O28: 1700
J29: Ecole Lord Tweedsmuir | K29: 6 | L29: 1400 | N29: 6 | O29: 1700
J30: Ecole Panorama Ridge | K30: 7 | L30: 1525 | N30: 7 | O30: 1700
A31: K - 7 Katzie Elementary | B31: 6887 194A St., Surrey, BC V4N 1N2 | E31: K-7 | F31: 804 | G31: 605 | H31: =F31-G31 -> 199 | J31: Enver Creek Secondary | K31: 8 | L31: 1400 | N31: 8 | O31: 1700
A32: K - 7 École Woodward Hill | B32: 6082-142 St., Surrey, BC V3X 1C1 | E32: K-7 | F32: 678 | G32: 510 | H32: =F32-G32 -> 168 | J32: Fleetwood Park Secondary | K32: 9 | L32: 1200 | N32: 9 | O32: 1700
A33: K - 7 Cambridge Elementary | B33: 6115 - 150 St., Surrey, BC V3S 3H7 | E33: K-7 | F33: 690 | G33: 530 | H33: =F33-G33 -> 160 | J33: Frank Hurt Secondary | K33: 10 | L33: 1200 | N33: 10 | O33: 1700
A34: K - 7 Sunnyside Elementary | B34: 2828 159 St., Surrey, BC V3S 0E5 | E34: K-7 | F34: 579 | G34: 450 | H34: =F34-G34 -> 129 | J34: Guildford Park Secondary | K34: 11 | L34: 1050 | N34: 11 | O34: 1700
A35: K - 7 Hillcrest Elementary | B35: 18599 - 65 Ave., Surrey, BC V3S 8T2 | E35: K-7 | F35: 595 | G35: 480 | H35: =F35-G35 -> 115 | J35: Johnston Heights Secondary | K35: 12 | L35: 1450 | N35: 12 | O35: 1700
A36: K - 7 Hazelgrove Elementary | B36: 7057 - 191 St., Surrey, BC V4N 6E5 | E36: K-7 | F36: 644 | G36: 530 | H36: =F36-G36 -> 114 | J36: L. A. Matheson Secondary | K36: 13 | L36: 1400 | N36: 13 | O36: 1700
A37: K - 7 École Erma Stephenson | B37: 10929 - 160 St., Surrey, BC V4N 1P3 | E37: K-7 | F37: 461 | G37: 365 | H37: =F37-G37 -> 96 | J37: North Surrey Secondary | K37: 14 | L37: 1500 | N37: 14 | O37: 1700
A38: K - 7 Panorama Park Elementary | B38: 12878 - 62 Ave., Surrey, BC V3X 2E8 | E38: K-7 | F38: 400 | G38: 315 | H38: =F38-G38 -> 85 | J38: Princess Margaret Secondary | K38: 15 | L38: 1500 | N38: 15 | O38: 1700
A39: K - 7 École Frost Road | B39: 8606 - 162 St., Surrey, BC V4N 1B4 | E39: K-7 | F39: 614 | G39: 530 | H39: =F39-G39 -> 84 | J39: Queen Elizabeth Secondary | K39: 16 | L39: 1400 | N39: 16 | O39: 1700
A40: K - 7 Walnut Road Elementary | B40: 16152 - 82 Ave., Surrey, BC V4N 0N5 | E40: K-7 | F40: 663 | G40: 580 | H40: =F40-G40 -> 83 | J40: Semiahmoo Secondary | K40: 17 | L40: 1300 | N40: 17 | O40: 1700
A41: K - 7 T. E. Scott Elementary | B41: 7079 - 148 St., Surrey, BC V3S 3E5 | E41: K-7 | F41: 557 | G41: 475 | H41: =F41-G41 -> 82 | J41: Sullivan Heights Secondary | K41: 18 | L41: 1700 | N41: 18 | O41: 1700
A42: K - 7 École K.B. Woodward | B42: 13130 - 106 Ave., Surrey, BC V3T 2C3 | E42: K-7 | F42: 536 | G42: 465 | H42: =F42-G42 -> 71 | J42: Tamanawis Secondary | K42: 19 | L42: 1500 | N42: 19 | O42: 1700
A43: K - 7 Sullivan Elementary | B43: 6016 - 152 St., Surrey, BC V3S 3K6 | E43: K-7 | F43: 283 | G43: 215 | H43: =F43-G43 -> 68 | L43: =SUM(L24:L42) -> 28805
A44: K - 7 Clayton Elementary | B44: 7541 - 184 St., Surrey, BC V4N 3G5 | E44: K-7 | F44: 223 | G44: 160 | H44: =F44-G44 -> 63 | J44: =525-G44 -> 365 | K44: =G44+J44 -> 525
A45: K - 7 South Meridian Elementary | B45: 16244 - 13 Ave., Surrey, BC V4A 8E6 | E45: K-7 | F45: 325 | G45: 265 | H45: =F45-G45 -> 60
A46: K - 7 École Ocean Cliff | B46: 12550 - 20 Ave., Surrey, BC V4A 1Y6 | E46: K-7 | F46: 348 | G46: 290 | H46: =F46-G46 -> 58
A47: K - 7 Surrey Centre Elementary | B47: 16670 Old McLellan Rd., Surrey, BC V3S 1K3 | E47: K-7 | F47: 455 | G47: 405 | H47: =F47-G47 -> 50
A48: K - 7 Goldstone Park Elementary | B48: 6287 146 St., Surrey, BC V3S 3A3 | E48: K-7 | F48: 593 | G48: 555 | H48: =F48-G48 -> 38
A49: K - 7 Rosemary Heights Elementary | B49: 15516 - 36 Ave., Surrey, BC V3S 0J5 | E49: K-7 | F49: 546 | G49: 510 | H49: =F49-G49 -> 36
A50: K - 7 Old Yale Road Elementary | B50: 10135 - 132 St., Surrey, BC V3T 3T6 | E50: K-7 | F50: 450 | G50: 415 | H50: =F50-G50 -> 35
A51: K - 7 Semiahmoo Trail Elementary | B51: 3040 - 145A St., Surrey, BC V4P 1P8 | E51: K-7 | F51: 328 | G51: 295 | H51: =F51-G51 -> 33
A52: K - 7 Chimney Hill Elementary | B52: 14755 - 74 Ave., Surrey, BC V3S 8Y8 | E52: K-7 | F52: 686 | G52: 655 | H52: =F52-G52 -> 31
A53: K - 7 École Fraser Wood | B53: 10650 - 164 St., Surrey, BC V4N 1W8 | E53: K-7 | F53: 520 | G53: 490 | H53: =F53-G53 -> 30
A54: K - 7 Adams Road Elementary | B54: 18228 - 68 Ave., Surrey, BC V3S9H5 | E54: K-7 | F54: 551 | G54: 530 | H54: =F54-G54 -> 21
A55: K - 7 Hall's Prairie Elementary | B55: 18035 - 8 Ave., Surrey, BC V3S 9R9 | E55: K-7 | F55: 139 | G55: 120 | H55: =F55-G55 -> 19
A56: K - 7 Pacific Heights Elementary | B56: 17148 - 26 Ave., Surrey, BC V3S 0A4 | E56: K-7 | F56: 347 | G56: 330 | H56: =F56-G56 -> 17 | J56: 120 | K56: =G56+J56 -> 450
A57: K - 7 White Rock Elementary | B57: 1273 Fir St., White Rock, BC V4B 5A6 | E57: K-7 | F57: 477 | G57: 460 | H57: =F57-G57 -> 17
A58: K - 7 George Greenaway Elementary | B58: 17285 - 61A Ave., Surrey, BC V3S 1W3 | E58: K-7 | F58: 455 | G58: 440 | H58: =F58-G58 -> 15
A59: K - 7 H. T. Thrift Elementary | B59: 1739 - 148 St., Surrey, BC V4A 4M6 | E59: K-7 | F59: 258 | G59: 245 | H59: =F59-G59 -> 13
A60: K - 7 William Watson Elementary | B60: 16450 - 80 Ave., Surrey, BC V4N 0H3 | E60: K-7 | F60: 356 | G60: 345 | H60: =F60-G60 -> 11 | J60: 163 | K60: =G60+J60 -> 508
A61: K - 7 Holly Elementary | B61: 10719 - 150 St., Surrey, BC V3R 4C8 | E61: K-7 | F61: 575 | G61: 565 | H61: =F61-G61 -> 10
A62: K - 7 École Riverdale | B62: 14835 - 108A Ave., Surrey, BC V3R 1W9 | E62: K-7 | F62: 463 | G62: 455 | H62: =F62-G62 -> 8
A63: K - 7 A. J. McLellan Elementary | B63: 13368 - 97 Ave., Surrey, BC V3T 1A4 | E63: K-7 | F63: 511 | G63: 505 | H63: =F63-G63 -> 6
A64: K - 7 Hjorth Road Elementary | B64: 14781 - 104 Ave., Surrey, BC V3R 5X4 | E64: K-7 | F64: 245 | G64: 240 | H64: =F64-G64 -> 5
A65: K - 7 École Peace Arch | B65: 15877 Roper Ave., White Rock, BC V4B 2H5 | E65: K-7 | F65: 544 | G65: 540 | H65: =F65-G65 -> 4
A66: K - 7 Bayridge Elementary | B66: 1730 - 142 St., Surrey, BC V4A 6G7 | E66: K-7 | F66: 321 | G66: 320 | H66: =F66-G66 -> 1
A67: K - 7 École Sunrise Ridge | B67: 18690 - 60 Ave., Surrey, BC V3S 8L8 | E67: K-7 | F67: 305 | G67: 305 | H67: =F67-G67 -> 0
A68: K - 7 Forsyth Road Elementary | B68: 10730 - 139 St., Surrey, BC V3T 4L9 | E68: K-7 | F68: 288 | G68: 295 | H68: =F68-G68 -> -7 | J68: 162 | K68: =G68+J68 -> 457
A69: K - 7 Morgan Elementary | B69: 3366 - 156A St., Surrey, BC V3S 9Y7 | E69: K-7 | F69: 428 | G69: 435 | H69: =F69-G69 -> -7
A70: A. H. P. Matthew Elementary | B70: 13367 - 97 Ave., Surrey, BC V3T 1A4 | E70: K-7 | F70: 398 | G70: 410 | H70: =F70-G70 -> -12
A71: K - 7 Kennedy Trail Elementary | B71: 8305 - 122A St., Surrey, BC V3W 9P8 | E71: K-7 | F71: 300 | G71: 315 | H71: =F71-G71 -> -15
A72: K - 7 Don Christian Elementary | B72: 6256 - 184 St., Surrey, BC V3S 8E6 | E72: K-7 | F72: 348 | G72: 365 | H72: =F72-G72 -> -17
A73: K - 7 Beaver Creek Elementary | B73: 6505 - 123A St., Surrey, BC V3W 5Y5 | E73: K-7 | F73: 495 | G73: 515 | H73: =F73-G73 -> -20
A74: K - 7 École Martha Currie | B74: 5811 - 184 St. Surrey, BC V3S 4N2 | E74: K-7 | F74: 590 | G74: 610 | H74: =F74-G74 -> -20
A75: K - 7 Chantrell Creek Elementary | B75: 2575 - 137 St., Surrey, BC V4P 2K5 | E75: K-7 | F75: 349 | G75: 370 | H75: =F75-G75 -> -21
A76: K - 7 Coyote Creek Elementary | B76: 8131 - 156 St., Surrey, BC V3S 3R4 | E76: K-7 | F76: 644 | G76: 665 | H76: =F76-G76 -> -21
A77: K - 7 Coast Meridian Elementary | B77: 8222 - 168A St., Surrey, BC V4N 4T8 | E77: K-7 | F77: 308 | G77: 330 | H77: =F77-G77 -> -22
A78: K - 7 J. T. Brown Elementary | B78: 12530 - 60 Ave., Surrey, BC V3X 2K8 | E78: K-7 | F78: 268 | G78: 295 | H78: =F78-G78 -> -27
A79: K - 7 Hyland Elementary | B79: 6677 - 140 St., Surrey, BC V3W 5J3 | E79: K-7 | F79: 409 | G79: 440 | H79: =F79-G79 -> -31
A80: K - 7 Martha Jane Norris Elementary | B80: 12928 - 66A Ave., Surrey, BC V3W 8Z7 | E80: K-7 | F80: 434 | G80: 465 | H80: =F80-G80 -> -31
... A126: K - 7 Royal Heights Elementary | B126: 11665 - 97 Ave., Surrey, BC V3V 2B9 | E126: K-7 | F126: 172 | G126: 390 | H126: =F126-G126 -> -218
A127: Total | F127: =SUM(F31:F126) -> 40016 | G127: =SUM(G31:G126) -> 42679 | H127: =SUM(H31:H126) -> -2663
A129: New Elementary Schools | E129: Priority
A130: Clayton North Area #1 Site 184 | B130: https://www.surreyschools.ca/departments/BMGS/Announcements/DispForm.aspx?ID=17&ContentTypeId=0x010400E3077DC437C8FF4CBD86FC235CD8E173 | E130: Approved | G130: 525
A131: Clayton Village NW Area Site 218 | B131: https://www.surreyschools.ca/departments/BMGS/Documents/Community%20Forum%20Feb%202014%20-%20Capital%20Slides.pdf | E131: Approved | G131: 525
A132: Grandview Heights South #2 Site 206 | B132: http://www.surrey.ca/images/pageImages/MapofStudyArea.jpg | E132: High | G132: 525
A133: New South Newton Site 4Ha | E133: High | F133: Not yet acquire | G133: 525
A134: New Grandview Area Site 3Ha | E134: High | F134: Not yet acquire | G134: 525
A135: New Douglas Area Site 180 | B135: http://surrey.ca/files/Douglas_Industrial_Brochure_LOWRES.pdf | E135: High | G135: 525
A136: Grandview Centre Site 208 2.9Ha | B136: https://www.surreyschools.ca/departments/BMGS/Documents/Community%20Forum%20Feb%202014%20-%20Capital%20Slides.pdf | E136: High | F136: Not yet acquire | G136: 525
A137: Clayton Village Site 217 | B137: https://www.surreyschools.ca/departments/BMGS/Documents/Community%20Forum%20Feb%202014%20-%20Capital%20Slides.pdf | E137: Mid | G137: 525
A138: New Clayton NE Area Site 204 | B138: https://www.surreyschools.ca/departments/BMGS/Documents/Community%20Forum%20Feb%202014%20-%20Capital%20Slides.pdf | E138: Mid | G138: 525
A139: Port Kells Site 216 | B139: https://www.surreyschools.ca/departments/BMGS/Documents/Community%20Forum%20Feb%202014%20-%20Capital%20Slides.pdf | E139: Mid | F139: Not yet acquire | G139: 525
A140: Port Kells Site 209 | B140: https://www.surreyschools.ca/departments/BMGS/Documents/Community%20Forum%20Feb%202014%20-%20Capital%20Slides.pdf | E140: Low | G140: 525
A142: New Secondary Schools
A143: Grandview Heights | B143: 168th Street 28th Avenue | E143: Approved | G143: 1500
A144: Salish (New Clayton) | B144: 7278 184th Street | E144: Approved | G144: 1500
A146: Map with new schools' exact locations | B146: https://drive.google.com/file/d/0BzR8mZZxWsQ1RFItN1BKYTY4SzA/view?usp=sharing
A148: A. H. P. Matthew Elementary | B148: 1 | C148: 410 | E148: 1 | F148: 700
A149: A. J. McLellan Elementary | B149: 2 | C149: 505 | E149: 2 | F149: 700
...

Sheet linear projection elementary
B1: geocode | C1: proportion | D1: population | E1: geocode | F1: proportion | G1: population | H1: geocode | I1: proportion | J1: population | K1: geocode | L1: proportion | M1: population | N1: TOTAL | P1: ppl for elem | Q1: ppl for sec | S1: ppl for elem | T1: ppl for sec | V1: ppl for elem | W1: ppl for sec | Y1: ppl for elem | Z1: ppl for sec
A2: H. T. Thrift Elementary | B2: 170.03 | C2: 0.25 | D2: 21 | E2: 170.04 | F2: 0.25 | G2: 87 | H2: 181.11 | I2: 1 | J2: 226 | K2: 181.1 | L2: 0.5 | M2: 167 | N2: =$D2+$G2+$J2+$M2 -> 501 | O2: 170.03 | P2: 85 | Q2: 86 | R2: 170.04 | S2: 347 | T2: 273 | U2: 181.11 | V2: 226 | W2: 222 | X2: 181.1 | Y2: 333 | Z2: 306
A3: École Peace Arch | B3: 170.07 | C3: 0.5 | D3: 167 | E3: 170.08 | F3: 0.5 | G3: 102 | J3: 0 | M3: 0 | N3: =$D3+$G3+$J3+$M3 -> 269 | O3: 170.07 | P3: 333 | Q3: 225 | R3: 170.08 | S3: 203 | T3: 162
A4: White Rock Elementary | B4: 170.08 | C4: 0.5 | D4: 102 | E4: 170.07 | F4: 0.5 | G4: 167 | H4: 170.05 | I4: 1 | J4: 73 | K4: 170.03 | L4: 0.75 | M4: 64 | N4: =$D4+$G4+$J4+$M4 -> 406 | O4: 170.08 | P4: 203 | Q4: 162 | R4: 170.07 | S4: 333 | T4: 225 | U4: 170.05 | V4: 73 | W4: 54 | X4: 170.03 | Y4: 85 | Z4: 86
A5: Rosemary Heights Elementary | B5: 180.01 | C5: 0.5 | D5: 676 | G5: 0 | J5: 0 | M5: 0 | N5: =$D5+$G5+$J5+$M5 -> 676 | O5: 180.01 | P5: 1351 | Q5: 742
A6: Hall's Prairie Elementary | B6: 180.03 | C6: 0.25 | D6: 247 | G6: 0 | J6: 0 | M6: 0 | N6: =$D6+$G6+$J6+$M6 -> 247 | O6: 180.03 | P6: 987 | Q6: 747
A7: Pacific Heights Elementary | B7: 180.03 | C7: 0.5 | D7: 494 | G7: 0 | J7: 0 | M7: 0 | N7: =$D7+$G7+$J7+$M7 -> 494 | O7: 180.03 | P7: 987 | Q7: 747
A8: East Kensington Elementary | B8: 180.03 | C8: 0.25 | D8: 247 | G8: 0 | J8: 0 | M8: 0 | N8: =$D8+$G8+$J8+$M8 -> 247 | O8: 180.03 | P8: 987 | Q8: 747
A9: Sunnyside Elementary | B9: 180.04 | C9: 1 | D9: 1058 | G9: 0 | J9: 0 | M9: 0 | N9: =$D9+$G9+$J9+$M9 -> 1058 | O9: 180.04 | P9: 1058 | Q9: 803
A10: École Crescent Park | B10: 181.03 | C10: 0.5 | D10: 244 | G10: 0 | J10: 0 | M10: 0 | N10: =$D10+$G10+$J10+$M10 -> 244 | O10: 181.03 | P10: 488 | Q10: 410
A11: École Ocean Cliff | B11: 181.07 | C11: 1 | D11: 336 | G11: 0 | J11: 0 | M11: 0 | N11: =$D11+$G11+$J11+$M11 -> 336 | O11: 181.07 | P11: 336 | Q11: 266
A12: Ray Shepherd Elementary | B12: 181.08 | C12: 1 | D12: 248 | E12: 181.09 | F12: 1 | G12: 614 | J12: 0 | M12: 0 | N12: =$D12+$G12+$J12+$M12 -> 862 | O12: 181.08 | P12: 248 | Q12: 169 | R12: 181.09 | S12: 614 | T12: 540
A13: Bayridge Elementary | B13: 181.1 | C13: 0.5 | D13: 167 | E13: 170.04 | F13: 0.75 | G13: 260 | J13: 0 | M13: 0 | N13: =$D13+$G13+$J13+$M13 -> 427 | O13: 181.1 | P13: 333 | Q13: 306 | R13: 170.04 | S13: 347 | T13: 273
A14: Chantrell Creek Elementary | B14: 181.12 | C14: 0.5 | D14: 156 | E14: 181.03 | F14: 0.5 | G14: 244 | J14: 0 | M14: 0 | N14: =$D14+$G14+$J14+$M14 -> 400 | O14: 181.12 | P14: 311 | Q14: 237 | R14: 181.03 | S14: 488 | T14: 410
A15: Semiahmoo Trail Elementary | B15: 181.13 | C15: 1 | D15: 341 | E15: 181.12 | F15: 0.5 | G15: 156 | H15: 181.14 | I15: 0.5 | J15: 196 | M15: 0 | N15: =$D15+$G15+$J15+$M15 -> 693 | O15: 181.13 | P15: 341 | Q15: 275 | R15: 181.12 | S15: 311 | T15: 237 | U15: 181.14 | V15: 391 | W15: 281
A16: École Jessie Lee | B16: 181.14 | C16: 0.5 | D16: 196 | E16: 181.05 | F16: 1 | G16: 524 | J16: 0 | M16: 0 | N16: =$D16+$G16+$J16+$M16 -> 720 | O16: 181.14 | P16: 391 | Q16: 281 | R16: 181.05 | S16: 524 | T16: 399
A17: South Meridian Elementary | B17: 181.16 | C17: 1 | D17: 270 | E17: 181.15 | F17: 1 | G17: 524 | J17: 0 | M17: 0 | N17: =$D17+$G17+$J17+$M17 -> 794 | O17: 181.16 | P17: 270 | Q17: 200 | R17: 181.05 | S17: 524 | T17: 399
A18: École Sunrise Ridge | B18: 182.01 | C18: 0.25 | D18: 163 | E18: 183.07 | F18: 0.3 | G18: 194 | J18: 0 | M18: 0 | N18: =$D18+$G18+$J18+$M18 -> 357 | O18: 182.01 | P18: 652 | Q18: 462 | R18: 183.07 | S18: 646 | T18: 482
A19: Morgan Elementary | B19: 182.01 | C19: 0.25 | D19: 163 | E19: 180.01 | F19: 0.5 | G19: 676 | J19: 0 | M19: 0 | N19: =$D19+$G19+$J19+$M19 -> 839 | O19: 182.01 | P19: 652 | Q19: 462 | R19: 180.01 | S19: 1351 | T19: 742
A20: Surrey Centre Elementary | B20: 182.02 | C20: 0.5 | D20: 816 | G20: 0 | J20: 0 | M20: 0 | N20: =$D20+$G20+$J20+$M20 -> 816 | O20: 182.02 | P20: 1632 | Q20: 741
A21: A. J. McLellan Elementary | B21: 182.02 | C21: 0.5 | D21: 816 | G21: 0 | J21: 0 | M21: 0 | N21: =$D21+$G21+$J21+$M21 -> 816 | O21: 182.02 | P21: 1632 | Q21: 741
A22: William Watson Elementary | B22: 182.04 | C22: 1 | D22: 208 | E22: 187.16 | F22: 0.667 | G22: 266 | J22: 0 | M22: 0 | N22: =$D22+$G22+$J22+$M22 -> 474 | O22: 182.04 | P22: 208 | Q22: 182 | R22: 187.16 | S22: 399 | T22: 298
A23: Coast Meridian Elementary | B23: 182.05 | C23: 1 | D23: 1010 | G23: 0 | J23: 0 | M23: 0 | N23: =$D23+$G23+$J23+$M23 -> 1010 | O23: 182.05 | P23: 1010 | Q23: 686
A24: George Greenaway Elementary | B24: 183.01 | C24: 1 | D24: 771 | G24: 0 | J24: 0 | M24: 0 | N24: =$D24+$G24+$J24+$M24 -> 771 | O24: 183.01 | P24: 771 | Q24: 533
A25: Don Christian Elementary | B25: 183.03 | C25: 0.5 | D25: 287 | E25: 183.07 | F25: 0.2 | G25: 129 | J25: 0 | M25: 0 | N25: =$D25+$G25+$J25+$M25 -> 416 | O25: 183.03 | P25: 573 | Q25: 398 | R25: 183.07 | S25: 646 | T25: 482
A26: École Martha Currie | B26: 183.03 | C26: 0.5 | D26: 287 | E26: 183.07 | F26: 0.1 | G26: 65 | H26: 182.01 | I26: 0.25 | J26: 163 | M26: 0 | N26: =$D26+$G26+$J26+$M26 -> 515 | O26: 183.03 | P26: 573 | Q26: 398 | R26: 183.07 | S26: 646 | T26: 482 | U26: 182.01 | V26: 652 | W26: 462
A27: Hillcrest Elementary | B27: 183.05 | C27: 0.5 | D27: 980 | G27: 0 | J27: 0 | M27: 0 | N27: =$D27+$G27+$J27+$M27 -> 980 | O27: 183.05 | P27: 1960 | Q27: 1040
A28: Adams Road Elementary | B28: 183.05 | C28: 0.5 | D28: 980 | G28: 0 | J28: 0 | M28: 0 | N28: =$D28+$G28+$J28+$M28 -> 980 | O28: 183.05 | P28: 1960 | Q28: 1040
A29: Latimer Road Elementary | B29: 183.07 | C29: 0.4 | D29: 258 | E29: 183.06 | F29: 1 | G29: 222 | H29: 182.01 | I29: 0.25 | J29: 163 | M29: 0 | N29: =$D29+$G29+$J29+$M29 -> 643 | O29: 183.07 | P29: 646 | Q29: 482 | R29: 183.06 | S29: 222 | T29: 138 | U29: 182.01 | V29: 652 | W29: 462
A30: Katzie Elementary | B30: 183.08 | C30: 1 | D30: 1038 | G30: 0 | J30: 0 | M30: 0 | N30: =$D30+$G30+$J30+$M30 -> 1038 | O30: 183.08 | P30: 1038 | Q30: 556
A31: Hazelgrove Elementary | B31: 183.09 | C31: 0.5 | D31: 1187 | G31: 0 | J31: 0 | M31: 0 | N31: =$D31+$G31+$J31+$M31 -> 1187 | O31: 183.09 | P31: 2374 | Q31: 1406
A32: Clayton Elementary | B32: 183.09 | C32: 0.5 | D32: 1187 | G32: 0 | J32: 0 | M32: 0 | N32: =$D32+$G32+$J32+$M32 -> 1187 | O32: 183.09 | P32: 2374 | Q32: 1406
A33: Bear Creek Elementary | B33: 184.02 | C33: 1 | D33: 869 | E33: 184.16 | F33: 0.25 | G33: 167 | J33: 0 | M33: 0 | N33: =$D33+$G33+$J33+$M33 -> 1036 | O33: 184.02 | P33: 869 | Q33: 521 | R33: 184.16 | S33: 667 | T33: 457
A34: T. E. Scott Elementary | B34: 184.06 | C34: 0.667 | D34: 1433 | E34: 182.03 | F34: 0.2 | G34: 72 | J34: 0 | M34: 0 | N34: =$D34+$G34+$J34+$M34 -> 1505 | O34: 184.06 | P34: 2149 | Q34: 1146 | R34: 182.03 | S34: 361 | T34: 357
A35: Georges Vanier Elementary | B35: 184.06 | C35: 0.333 | D35: 716 | E35: 184.07 | F35: 1 | G35: 562 | J35: 0 | M35: 0 | N35: =$D35+$G35+$J35+$M35 -> 1278 | O35: 184.06 | P35: 2149 | Q35: 1146 | R35: 184.07 | S35: 562 | T35: 359
A36: Hyland Elementary | B36: 184.08 | C36: 1 | D36: 872 | G36: 0 | J36: 0 | M36: 0 | N36: =$D36+$G36+$J36+$M36 -> 872 | O36: 184.08 | P36: 872 | Q36: 570
A37: Maple Green Elementary | B37: 184.09 | C37: 0.5 | D37: 291 | E37: 184.1 | F37: 0.5 | G37: 389 | J37: 0 | M37: 0 | N37: =$D37+$G37+$J37+$M37 -> 680 | O37: 184.09 | P37: 581 | Q37: 386 | R37: 184.1 | S37: 778 | T37: 575
A38: Janice Churchill Elementary | B38: 184.1 | C38: 0.5 | D38: 389 | G38: 0 | J38: 0 | M38: 0 | N38: =$D38+$G38+$J38+$M38 -> 389 | O38: 184.1 | P38: 778 | Q38: 575
A39: Chimney Hill Elementary | B39: 184.11 | C39: 1 | D39: 1598 | G39: 0 | J39: 0 | M39: 0 | N39: =$D39+$G39+$J39+$M39 -> 1598 | O39: 184.11 | P39: 1598 | Q39: 1016
A40: Goldstone Park Elementary | B40: 184.12 | C40: 0.5 | D40: 517 | E40: 184.13 | F40: 0.1 | G40: 66 | H40: 184.14 | I40: 0.2 | J40: 319 | M40: 0 | N40: =$D40+$G40+$J40+$M40 -> 902 | O40: 184.12 | P40: 1034 | Q40: 673 | R40: 184.13 | S40: 659 | T40: 417 | U40: 184.14 | V40: 1595 | W40: 717
A41: École Woodward Hill | B41: 184.13 | C41: 0.3 | D41: 198 | E41: 184.12 | F41: 0.3 | G41: 310 | J41: 0 | M41: 0 | N41: =$D41+$G41+$J41+$M41 -> 508 | O41: 184.13 | P41: 659 | Q41: 417 | R41: 184.12 | S41: 1034 | T41: 673
A42: Sullivan Elementary | B42: 184.13 | C42: 0.2 | D42: 132 | E42: 182.03 | F42: 0.4 | G42: 144 | J42: 0 | M42: 0 | N42: =$D42+$G42+$J42+$M42 -> 276 | O42: 184.13 | P42: 659 | Q42: 417 | R42: 182.03 | S42: 361 | T42: 357
A43: Cambridge Elementary | B43: 184.14 | C43: 0.8 | D43: 1276 | E43: 184.13 | F43: 0.2 | G43: 132 | J43: 0 | M43: 0 | N43: =$D43+$G43+$J43+$M43 -> 1408 | O43: 184.14 | P43: 1595 | Q43: 717 | R43: 184.13 | S43: 659 | T43: 417
A44: M. B. Sanford Elementary | B44: 184.16 | C44: 0.6 | D44: 400 | G44: 0 | J44: 0 | M44: 0 | N44: =$D44+$G44+$J44+$M44 -> 400 | O44: 184.16 | P44: 667 | Q44: 457
A45: Brookside Elementary | B45: 184.16 | C45: 0.15 | D45: 100 | E45: 184.15 | F45: 1 | G45: 347 | H45: 184.09 | I45: 0.5 | J45: 291 | M45: 0 | N45: =$D45+$G45+$J45+$M45 -> 738 | O45: 184.16 | P45: 667 | Q45: 457 | R45: 184.15 | S45: 347 | T45: 305 | U45: 184.09 | V45: 581 | W45: 386
A46: W. E. Kinvig Elementary | B46: 185.05 | C46: 0.8 | D46: 644 | G46: 0 | J46: 0 | M46: 0 | N46: =$D46+$G46+$J46+$M46 -> 644 | O46: 185.05 | P46: 805 | Q46: 587
A47: Panorama Park Elementary | B47: 185.07 | C47: 0.333 | D47: 459 | G47: 0 | J47: 0 | M47: 0 | N47: =$D47+$G47+$J47+$M47 -> 459 | O47: 185.07 | P47: 1379 | Q47: 919
A48: North Ridge Elementary | B48: 185.07 | C48: 0.333 | D48: 459 | E48: 184.12 | F48: 0.2 | G48: 207 | H48: 184.13 | I48: 0.2 | J48: 132 | M48: 0 | N48: =$D48+$G48+$J48+$M48 -> 798 | O48: 185.07 | P48: 1379 | Q48: 919 | R48: 184.12 | S48: 1034 | T48: 673 | U48: 184.13 | V48: 659 | W48: 417
A49: Kennedy Trail Elementary | B49: 185.09 | C49: 0.667 | D49: 402 | G49: 0 | J49: 0 | M49: 0 | N49: =$D49+$G49+$J49+$M49 -> 402 | O49: 185.09 | P49: 602 | Q49: 356
A50: Strawberry Hill Elementary | B50: 185.1 | C50: 0.5 | D50: 423 | E50: 185.11 | F50: 0.333 | G50: 367 | J50: 0 | M50: 0 | N50: =$D50+$G50+$J50+$M50 -> 790 | O50: 185.1 | P50: 845 | Q50: 477 | R50: 185.11 | S50: 1103 | T50: 589
A51: Westerman Elementary | B51: 185.11 | C51: 0.667 | D51: 736 | G51: 0 | J51: 0 | M51: 0 | N51: =$D51+$G51+$J51+$M51 -> 736 | O51: 185.11 | P51: 1103 | Q51: 589
A52: Martha Jane Norris Elementary | B52: 185.12 | C52: 0.5 | D52: 433 | G52: 0 | J52: 0 | M52: 0 | N52: =$D52+$G52+$J52+$M52 -> 433 | O52: 185.12 | P52: 865 | Q52: 532
A53: École Henry Bose | B53: 185.12 | C53: 0.5 | D53: 433 | E53: 185.05 | F53: 0.2 | G53: 161 | J53: 0 | M53: 0 | N53: =$D53+$G53+$J53+$M53 -> 594 | O53: 185.12 | P53: 865 | Q53: 532 | R53: 185.05 | S53: 805 | T53: 587
A54: Newton Elementary | B54: 185.15 | C54: 0.667 | D54: 472 | E54: 185.16 | F54: 0.5 | G54: 332 | J54: 0 | M54: 0 | N54: =$D54+$G54+$J54+$M54 -> 804 | O54: 185.15 | P54: 708 | Q54: 397 | R54: 185.16 | S54: 664 | T54: 418
A55: Dr. F. D. Sinclair Elementary | B55: 185.16 | C55: 0.5 | D55: 332 | E55: 185.1 | F55: 0.5 | G55: 423 | J55: 0 | M55: 0 | N55: =$D55+$G55+$J55+$M55 -> 755 | O55: 185.16 | P55: 664 | Q55: 418 | R55: 185.1 | S55: 845 | T55: 477
A56: Boundary Park Elementary | B56: 185.17 | C56: 1 | D56: 341 | G56: 0 | J56: 0 | M56: 0 | N56: =$D56+$G56+$J56+$M56 -> 341 | O56: 185.17 | P56: 341 | Q56: 267
A57: J. T. Brown Elementary | B57: 185.18 | C57: 0.667 | D57: 370 | G57: 0 | J57: 0 | M57: 0 | N57: =$D57+$G57+$J57+$M57 -> 370 | O57: 185.18 | P57: 554 | Q57: 385
A58: Colebrook Elementary | B58: 185.18 | C58: 0.333 | D58: 184 | E58: 185.08 | F58: 1 | G58: 147 | H58: 185.07 | I58: 0.333 | J58: 459 | M58: 0 | N58: =$D58+$G58+$J58+$M58 -> 790 | O58: 185.18 | P58: 554 | Q58: 385 | R58: 185.08 | S58: 147 | T58: 124 | U58: 185.07 | V58: 1379 | W58: 919
A59: Beaver Creek Elementary | B59: 185.19 | C59: 1 | D59: 874 | E59: 185.2 | F59: 1 | G59: 823 | J59: 0 | M59: 0 | N59: =$D59+$G59+$J59+$M59 -> 1697 | O59: 185.19 | P59: 874 | Q59: 546 | R59: 185.2 | S59: 823 | T59: 490
A60: Cougar Creek Elementary | B60: 185.21 | C60: 1 | D60: 466 | E60: 185.22 | F60: 1 | G60: 494 | J60: 0 | M60: 0 | N60: =$D60+$G60+$J60+$M60 -> 960 | O60: 185.21 | P60: 466 | Q60: 278 | R60: 185.22 | S60: 494 | T60: 302
A61: Cedar Hills Elementary | B61: 186.01 | C61: 0.25 | D61: 202 | E61: 186.02 | F61: 0.25 | G61: 163 | J61: 0 | M61: 0 | N61: =$D61+$G61+$J61+$M61 -> 365 | O61: 186.01 | P61: 809 | Q61: 549 | R61: 186.02 | S61: 653 | T61: 437
A62: Prince Charles Elementary | B62: 186.01 | C62: 0.25 | D62: 202 | E62: 186.02 | F62: 0.75 | G62: 490 | H62: 192 | I62: 0.33 | J62: 137 | M62: 0 | N62: =$D62+$G62+$J62+$M62 -> 829 | O62: 186.01 | P62: 809 | Q62: 549 | R62: 186.02 | S62: 653 | T62: 437 | U62: 192 | V62: 415 | W62: 278
A63: Royal Heights Elementary | B63: 186.01 | C63: 0.5 | D63: 405 | G63: 0 | J63: 0 | M63: 0 | N63: =$D63+$G63+$J63+$M63 -> 405 | O63: 186.01 | P63: 809 | Q63: 549
A64: Kirkbride Elementary | B64: 186.05 | C64: 0.5 | D64: 527 | E64: 186.06 | F64: 0.5 | G64: 273 | J64: 0 | M64: 0 | N64: =$D64+$G64+$J64+$M64 -> 800 | O64: 186.05 | P64: 1053 | Q64: 670 | R64: 186.06 | S64: 546 | T64: 317
A65: Senator Reid Elementary | B65: 186.05 | C65: 0.5 | D65: 527 | E65: 186.06 | F65: 0.25 | G65: 137 | J65: 0 | M65: 0 | N65: =$D65+$G65+$J65+$M65 -> 664 | O65: 186.05 | P65: 1053 | Q65: 670 | R65: 186.06 | S65: 546 | T65: 317
A66: Betty Huff Elementary | B66: 186.05 | C66: 0.5 | D66: 527 | E66: 186.06 | F66: 0.25 | G66: 137 | J66: 0 | M66: 0 | N66: =$D66+$G66+$J66+$M66 -> 664 | O66: 186.05 | P66: 1053 | Q66: 670 | R66: 186.06 | S66: 546 | T66: 317
A67: David Brankin Elementary | B67: 186.06 | C67: 0.25 | D67: 137 | E67: 185.09 | F67: 0.333 | G67: 182 | H67: 186.07 | I67: 0.5 | J67: 403 | K67: 185.15 | L67: 0.333 | M67: 90 | N67: =$D67+$G67+$J67+$M67 -> 812 | O67: 186.06 | P67: 546 | Q67: 317 | R67: 186.06 | S67: 546 | T67: 317 | U67: 186.07 | V67: 805 | W67: 484 | X67: 181.15 | Y67: 270 | Z67: 200
A68: Cindrich Elementary | B68: 186.08 | C68: 0.5 | D68: 448 | E68: 186.07 | F68: 0.5 | G68: 403 | J68: 0 | M68: 0 | N68: =$D68+$G68+$J68+$M68 -> 851 | O68: 186.08 | P68: 896 | Q68: 575 | R68: 186.07 | S68: 805 | T68: 484
A69: Green Timbers Elementary | B69: 187.03 | C69: 0.5 | D69: 447 | E69: 187.05 | F69: 0.25 | G69: 240 | J69: 0 | M69: 0 | N69: =$D69+$G69+$J69+$M69 -> 687 | O69: 187.03 | P69: 894 | Q69: 582 | R69: 187.05 | S69: 961 | T69: 577
A70: Bonaccord Elementary | B70: 187.03 | C70: 0.25 | D70: 224 | E70: 189.05 | F70: 0.667 | G70: 470 | J70: 0 | M70: 0 | N70: =$D70+$G70+$J70+$M70 -> 694 | O70: 187.03 | P70: 894 | Q70: 582 | R70: 189.05 | S70: 704 | T70: 479
A71: École Simon Cunningham | B71: 187.04 | C71: 1 | D71: 186 | E71: 187.05 | F71: 0.25 | G71: 240 | H71: 190.01 | I71: 0.25 | J71: 204 | M71: 0 | N71: =$D71+$G71+$J71+$M71 -> 630 | O71: 187.04 | P71: 186 | Q71: 113 | R71: 187.05 | S71: 961 | T71: 577 | U71: 190.01 | V71: 814 | W71: 540
A72: Creekside Elementary | B72: 187.05 | C72: 0.5 | D72: 481 | G72: 0 | J72: 0 | M72: 0 | N72: =$D72+$G72+$J72+$M72 -> 481 | O72: 187.05 | P72: 961 | Q72: 577
A73: Woodland Park Elementary | B73: 187.06 | C73: 0.5 | D73: 490 | E73: 187.11 | F73: 0.333 | G73: 336 | J73: 0 | M73: 0 | N73: =$D73+$G73+$J73+$M73 -> 826 | O73: 187.06 | P73: 979 | Q73: 737 | R73: 187.11 | S73: 1010 | T73: 618
A74: Serpentine Heights Elementary | B74: 187.06 | C74: 0.5 | D74: 490 | E74: 188.04 | F74: 1 | G74: 552 | J74: 0 | M74: 0 | N74: =$D74+$G74+$J74+$M74 -> 1042 | O74: 187.06 | P74: 979 | Q74: 737 | R74: 188.04 | S74: 552 | T74: 446
A75: École Frost Road | B75: 187.11 | C75: 0.667 | D75: 674 | E75: 187.07 | F75: 1 | G75: 247 | J75: 0 | M75: 0 | N75: =$D75+$G75+$J75+$M75 -> 921 | O75: 187.11 | P75: 1010 | Q75: 618 | R75: 187.07 | S75: 247 | T75: 203
A76: Berkshire Park Elementary | B76: 187.12 | C76: 1 | D76: 503 | G76: 0 | J76: 0 | M76: 0 | N76: =$D76+$G76+$J76+$M76 -> 503 | O76: 187.12 | P76: 503 | Q76: 353
A77: Coyote Creek Elementary | B77: 187.13 | C77: 1 | D77: 262 | E77: 182.03 | F77: 0.4 | G77: 144 | J77: 0 | M77: 0 | N77: =$D77+$G77+$J77+$M77 -> 406 | O77: 187.13 | P77: 262 | Q77: 199 | R77: 182.03 | S77: 361 | T77: 357
A78: Walnut Road Elementary | B78: 187.16 | C78: 0.333 | D78: 133 | E78: 187.14 | F78: 1 | G78: 443 | H78: 187.15 | I78: 1 | J78: 540 | M78: 0 | N78: =$D78+$G78+$J78+$M78 -> 1116 | O78: 187.16 | P78: 399 | Q78: 298 | R78: 187.14 | S78: 443 | T78: 265 | U78: 187.15 | V78: 540 | W78: 390
A79: Dogwood Elementary | B79: 188.01 | C79: 1 | D79: 436 | E79: 188.02 | F79: 0.75 | G79: 311 | J79: 0 | M79: 0 | N79: =$D79+$G79+$J79+$M79 -> 747 | O79: 188.01 | P79: 436 | Q79: 337 | R79: 188.02 | S79: 414 | T79: 350
A80: École Erma Stephenson | B80: 188.02 | C80: 0.25 | D80: 104 | E80: 188.08 | F80: 0.5 | G80: 303 | H80: 188.07 | I80: 0.25 | J80: 119 | M80: 0 | N80: =$D80+$G80+$J80+$M80 -> 526 | O80: 188.02 | P80: 414 | Q80: 350 | R80: 188.08 | S80: 606 | T80: 556 | U80: 188.07 | V80: 474 | W80: 463
A81: Bothwell Elementary | B81: 188.05 | C81: 1 | D81: 332 | E81: 188.06 | F81: 0.8 | G81: 152 | J81: 0 | M81: 0 | N81: =$D81+$G81+$J81+$M81 -> 484 | O81: 188.05 | P81: 332 | Q81: 298 | R81: 188.06 | S81: 190 | T81: 138
A82: Port Kells Elementary | B82: 188.06 | C82: 0.2 | D82: 38 | E82: 182.06 | F82: 1 | G82: 120 | J82: 0 | M82: 0 | N82: =$D82+$G82+$J82+$M82 -> 158 | O82: 188.06 | P82: 190 | Q82: 138 | R82: 182.06 | S82: 120 | T82: 92
A83: École Fraser Wood | B83: 188.07 | C83: 0.75 | D83: 356 | E83: 188.08 | F83: 0.5 | G83: 303 | J83: 0 | M83: 0 | N83: =$D83+$G83+$J83+$M83 -> 659 | O83: 188.07 | P83: 474 | Q83: 463 | R83: 188.08 | S83: 606 | T83: 556
A84: École Riverdale | B84: 189.03 | C84: 0.75 | D84: 280 | G84: 0 | J84: 0 | M84: 0 | N84: =$D84+$G84+$J84+$M84 -> 280 | O84: 189.03 | P84: 373 | Q84: 272
A85: Hjorth Road Elementary | B85: 189.05 | C85: 0.333 | D85: 234 | E85: 190.03 | F85: 0.2 | G85: 161 | J85: 0 | M85: 0 | N85: =$D85+$G85+$J85+$M85 -> 395 | O85: 189.05 | P85: 704 | Q85: 479 | R85: 190.03 | S85: 803 | T85: 584
A86: Harold Bishop Elementary | B86: 189.07 | C86: 1 | D86: 393 | E86: 189.1 | F86: 0.5 | G86: 452 | H86: 189.09 | I86: 0.5 | J86: 222 | M86: 0 | N86: =$D86+$G86+$J86+$M86 -> 1067 | O86: 189.07 | P86: 393 | Q86: 239 | R86: 189.1 | S86: 903 | T86: 710 | U86: 189.09 | V86: 443 | W86: 368
A87: Holly Elementary | B87: 189.08 | C87: 1 | D87: 826 | G87: 0 | J87: 0 | M87: 0 | N87: =$D87+$G87+$J87+$M87 -> 826 | O87: 189.08 | P87: 826 | Q87: 511
A88: William F. Davidson Elementary | B88: 189.1 | C88: 0.5 | D88: 452 | E88: 189.09 | F88: 0.5 | G88: 222 | J88: 0 | M88: 0 | N88: =$D88+$G88+$J88+$M88 -> 674 | O88: 189.1 | P88: 903 | Q88: 710 | R88: 189.09 | S88: 443 | T88: 368
A89: Lena Shaw Elementary | B89: 190.01 | C89: 0.75 | D89: 611 | E89: 189.06 | F89: 1 | G89: 348 | H89: 187.03 | I89: 0.25 | J89: 224 | M89: 0 | N89: =$D89+$G89+$J89+$M89 -> 1183 | O89: 190.01 | P89: 814 | Q89: 540 | R89: 189.06 | S89: 348 | T89: 238 | U89: 187.03 | V89: 894 | W89: 582
A90: Mary Jane Shannon Elementary | B90: 190.03 | C90: 0.8 | D90: 642 | E90: 190.04 | F90: 0.1 | G90: 75 | J90: 0 | M90: 0 | N90: =$D90+$G90+$J90+$M90 -> 717 | O90: 190.03 | P90: 803 | Q90: 584 | R90: 190.04 | S90: 750 | T90: 541
A91: Ellendale Elementary | B91: 190.04 | C91: 0.3 | D91: 225 | E91: 189.03 | F91: 0.25 | G91: 93 | J91: 0 | M91: 0 | N91: =$D91+$G91+$J91+$M91 -> 318 | O91: 190.04 | P91: 750 | Q91: 541 | R91: 189.03 | S91: 373 | T91: 272
A92: James Ardiel Elementary | B92: 190.04 | C92: 0.6 | D92: 450 | G92: 0 | J92: 0 | M92: 0 | N92: =$D92+$G92+$J92+$M92 -> 450 | O92: 190.04 | P92: 750 | Q92: 541
A93: Old Yale Road Elementary | B93: 191.03 | C93: 0.5 | D93: 333 | E93: 191.04 | F93: 0.5 | G93: 307 | J93: 0 | M93: 0 | N93: =$D93+$G93+$J93+$M93 -> 640 | O93: 191.03 | P93: 665 | Q93: 434 | R93: 191.04 | S93: 614 | T93: 405
A94: A. H. P. Matthew Elementary | B94: 191.03 | C94: 0.5 | D94: 333 | E94: 191.04 | F94: 0.5 | G94: 307 | J94: 0 | M94: 0 | N94: =$D94+$G94+$J94+$M94 -> 640 | O94: 191.03 | P94: 665 | Q94: 434 | R94: 191.04 | S94: 614 | T94: 405
A95: École K.B. Woodward | B95: 191.05 | C95: 1 | D95: 400 | E95: 191.07 | F95: 1 | G95: 311 | H95: 191.06 | I95: 0.5 | J95: 95 | M95: 0 | N95: =$D95+$G95+$J95+$M95 -> 806 | O95: 191.05 | P95: 400 | Q95: 295 | R95: 191.07 | S95: 311 | T95: 245 | U95: 191.06 | V95: 190 | W95: 143
A96: Forsyth Road Elementary | B96: 191.06 | C96: 0.5 | D96: 95 | E96: 190.05 | F96: 1 | G96: 202 | H96: 190.03 | I96: 0.333 | J96: 267 | M96: 0 | N96: =$D96+$G96+$J96+$M96 -> 564 | O96: 191.06 | P96: 190 | Q96: 143 | R96: 190.05 | S96: 202 | T96: 139 | U96: 190.03 | V96: 803 | W96: 584
A97: Bridgeview Elementary | B97: 192 | C97: 0.667 | D97: 277 | G97: 0 | J97: 0 | M97: 0 | N97: =$D97+$G97+$J97+$M97 -> 277 | O97: 192 | P97: 415 | Q97: 278
N98: =SUM(N2:N97) -> 66673
A99: SORTED ALPHABETICALLY
A100: School | B100: Index | C100: Population | D100: Capacity | E100: Overcap | F100: Max | G100: Can Expand | I100: %
...

Sheet linear projection secondary
B1: geocode | C1: proportion | D1: population | E1: geocode | F1: proportion | G1: population | H1: geocode | I1: proportion | J1: population | K1: geocode | L1: proportion | M1: population | N1: TOTAL | P1: ppl for elem | Q1: ppl for sec | S1: ppl for elem | T1: ppl for sec | V1: ppl for elem | W1: ppl for sec | Y1: ppl for elem | Z1: ppl for sec
A2: H. T. Thrift Elementary | B2: 170.03 | C2: 0.25 | D2: 22 | E2: 170.04 | F2: 0.25 | G2: 68 | H2: 181.11 | I2: 1 | J2: 222 | K2: 181.1 | L2: 0.5 | M2: 153 | N2: =$D2+$G2+$J2+$M2 -> 465 | O2: 170.03 | P2: 85 | Q2: 86 | R2: 170.04 | S2: 347 | T2: 273 | U2: 181.11 | V2: 226 | W2: 222 | X2: 181.1 | Y2: 333 | Z2: 306
A3: École Peace Arch | B3: 170.07 | C3: 0.5 | D3: 113 | E3: 170.08 | F3: 0.5 | G3: 81 | J3: 0 | M3: 0 | N3: =$D3+$G3+$J3+$M3 -> 194 | O3: 170.07 | P3: 333 | Q3: 225 | R3: 170.08 | S3: 203 | T3: 162
A4: White Rock Elementary | B4: 170.08 | C4: 0.5 | D4: 81 | E4: 170.07 | F4: 0.5 | G4: 113 | H4: 170.05 | I4: 1 | J4: 54 | K4: 170.03 | L4: 0.75 | M4: 65 | N4: =$D4+$G4+$J4+$M4 -> 313 | O4: 170.08 | P4: 203 | Q4: 162 | R4: 170.07 | S4: 333 | T4: 225 | U4: 170.05 | V4: 73 | W4: 54 | X4: 170.03 | Y4: 85 | Z4: 86
A5: Rosemary Heights Elementary | B5: 180.01 | C5: 0.5 | D5: 371 | G5: 0 | J5: 0 | M5: 0 | N5: =$D5+$G5+$J5+$M5 -> 371 | O5: 180.01 | P5: 1351 | Q5: 742
A6: Hall's Prairie Elementary | B6: 180.03 | C6: 0.25 | D6: 187 | G6: 0 | J6: 0 | M6: 0 | N6: =$D6+$G6+$J6+$M6 -> 187 | O6: 180.03 | P6: 987 | Q6: 747
A7: Pacific Heights Elementary | B7: 180.03 | C7: 0.5 | D7: 374 | G7: 0 | J7: 0 | M7: 0 | N7: =$D7+$G7+$J7+$M7 -> 374 | O7: 180.03 | P7: 987 | Q7: 747
A8: East Kensington Elementary | B8: 180.03 | C8: 0.25 | D8: 187 | G8: 0 | J8: 0 | M8: 0 | N8: =$D8+$G8+$J8+$M8 -> 187 | O8: 180.03 | P8: 987 | Q8: 747
A9: Sunnyside Elementary | B9: 180.04 | C9: 1 | D9: 803 | G9: 0 | J9: 0 | M9: 0 | N9: =$D9+$G9+$J9+$M9 -> 803 | O9: 180.04 | P9: 1058 | Q9: 803
A10: École Crescent Park | B10: 181.03 | C10: 0.5 | D10: 205 | G10: 0 | J10: 0 | M10: 0 | N10: =$D10+$G10+$J10+$M10 -> 205 | O10: 181.03 | P10: 488 | Q10: 410
A11: École Ocean Cliff | B11: 181.07 | C11: 1 | D11: 266 | G11: 0 | J11: 0 | M11: 0 | N11: =$D11+$G11+$J11+$M11 -> 266 | O11: 181.07 | P11: 336 | Q11: 266
A12: Ray Shepherd Elementary | B12: 181.08 | C12: 1 | D12: 169 | E12: 181.09 | F12: 1 | G12: 540 | J12: 0 | M12: 0 | N12: =$D12+$G12+$J12+$M12 -> 709 | O12: 181.08 | P12: 248 | Q12: 169 | R12: 181.09 | S12: 614 | T12: 540
A13: Bayridge Elementary | B13: 181.1 | C13: 0.5 | D13: 153 | E13: 170.04 | F13: 0.75 | G13: 205 | J13: 0 | M13: 0 | N13: =$D13+$G13+$J13+$M13 -> 358 | O13: 181.1 | P13: 333 | Q13: 306 | R13: 170.04 | S13: 347 | T13: 273
A14: Chantrell Creek Elementary | B14: 181.12 | C14: 0.5 | D14: 119 | E14: 181.03 | F14: 0.5 | G14: 205 | J14: 0 | M14: 0 | N14: =$D14+$G14+$J14+$M14 -> 324 | O14: 181.12 | P14: 311 | Q14: 237 | R14: 181.03 | S14: 488 | T14: 410
A15: Semiahmoo Trail Elementary | B15: 181.13 | C15: 1 | D15: 275 | E15: 181.12 | F15: 0.5 | G15: 119 | H15: 181.14 | I15: 0.5 | J15: 141 | M15: 0 | N15: =$D15+$G15+$J15+$M15 -> 535 | O15: 181.13 | P15: 341 | Q15: 275 | R15: 181.12 | S15: 311 | T15: 237 | U15: 181.14 | V15: 391 | W15: 281
A16: École Jessie Lee | B16: 181.14 | C16: 0.5 | D16: 141 | E16: 181.05 | F16: 1 | G16: 399 | J16: 0 | M16: 0 | N16: =$D16+$G16+$J16+$M16 -> 540 | O16: 181.14 | P16: 391 | Q16: 281 | R16: 181.05 | S16: 524 | T16: 399
A17: South Meridian Elementary | B17: 181.16 | C17: 1 | D17: 200 | E17: 181.15 | F17: 1 | G17: 399 | J17: 0 | M17: 0 | N17: =$D17+$G17+$J17+$M17 -> 599 | O17: 181.16 | P17: 270 | Q17: 200 | R17: 181.05 | S17: 524 | T17: 399
A18: École Sunrise Ridge | B18: 182.01 | C18: 0.25 | D18: 116 | E18: 183.07 | F18: 0.3 | G18: 145 | J18: 0 | M18: 0 | N18: =$D18+$G18+$J18+$M18 -> 261 | O18: 182.01 | P18: 652 | Q18: 462 | R18: 183.07 | S18: 646 | T18: 482
A19: Morgan Elementary | B19: 182.01 | C19: 0.25 | D19: 116 | E19: 180.01 | F19: 0.5 | G19: 371 | J19: 0 | M19: 0 | N19: =$D19+$G19+$J19+$M19 -> 487 | O19: 182.01 | P19: 652 | Q19: 462 | R19: 180.01 | S19: 1351 | T19: 742
A20: Surrey Centre Elementary | B20: 182.02 | C20: 0.5 | D20: 371 | G20: 0 | J20: 0 | M20: 0 | N20: =$D20+$G20+$J20+$M20 -> 371 | O20: 182.02 | P20: 1632 | Q20: 741
A21: A. J. McLellan Elementary | B21: 182.02 | C21: 0.5 | D21: 371 | G21: 0 | J21: 0 | M21: 0 | N21: =$D21+$G21+$J21+$M21 -> 371 | O21: 182.02 | P21: 1632 | Q21: 741
A22: William Watson Elementary | B22: 182.04 | C22: 1 | D22: 182 | E22: 187.16 | F22: 0.667 | G22: 199 | J22: 0 | M22: 0 | N22: =$D22+$G22+$J22+$M22 -> 381 | O22: 182.04 | P22: 208 | Q22: 182 | R22: 187.16 | S22: 399 | T22: 298
A23: Coast Meridian Elementary | B23: 182.05 | C23: 1 | D23: 686 | G23: 0 | J23: 0 | M23: 0 | N23: =$D23+$G23+$J23+$M23 -> 686 | O23: 182.05 | P23: 1010 | Q23: 686
A24: George Greenaway Elementary | B24: 183.01 | C24: 1 | D24: 533 | G24: 0 | J24: 0 | M24: 0 | N24: =$D24+$G24+$J24+$M24 -> 533 | O24: 183.01 | P24: 771 | Q24: 533
A25: Don Christian Elementary | B25: 183.03 | C25: 0.5 | D25: 199 | E25: 183.07 | F25: 0.2 | G25: 96 | J25: 0 | M25: 0 | N25: =$D25+$G25+$J25+$M25 -> 295 | O25: 183.03 | P25: 573 | Q25: 398 | R25: 183.07 | S25: 646 | T25: 482
A26: École Martha Currie | B26: 183.03 | C26: 0.5 | D26: 199 | E26: 183.07 | F26: 0.1 | G26: 48 | H26: 182.01 | I26: 0.25 | J26: 116 | M26: 0 | N26: =$D26+$G26+$J26+$M26 -> 363 | O26: 183.03 | P26: 573 | Q26: 398 | R26: 183.07 | S26: 646 | T26: 482 | U26: 182.01 | V26: 652 | W26: 462
A27: Hillcrest Elementary | B27: 183.05 | C27: 0.5 | D27: 520 | G27: 0 | J27: 0 | M27: 0 | N27: =$D27+$G27+$J27+$M27 -> 520 | O27: 183.05 | P27: 1960 | Q27: 1040
A28: Adams Road Elementary | B28: 183.05 | C28: 0.5 | D28: 520 | G28: 0 | J28: 0 | M28: 0 | N28: =$D28+$G28+$J28+$M28 -> 520 | O28: 183.05 | P28: 1960 | Q28: 1040
A29: Latimer Road Elementary | B29: 183.07 | C29: 0.4 | D29: 193 | E29: 183.06 | F29: 1 | G29: 138 | H29: 182.01 | I29: 0.25 | J29: 116 | M29: 0 | N29: =$D29+$G29+$J29+$M29 -> 447 | O29: 183.07 | P29: 646 | Q29: 482 | R29: 183.06 | S29: 222 | T29: 138 | U29: 182.01 | V29: 652 | W29: 462
A30: Katzie Elementary | B30: 183.08 | C30: 1 | D30: 556 | G30: 0 | J30: 0 | M30: 0 | N30: =$D30+$G30+$J30+$M30 -> 556 | O30: 183.08 | P30: 1038 | Q30: 556
A31: Hazelgrove Elementary | B31: 183.09 | C31: 0.5 | D31: 703 | G31: 0 | J31: 0 | M31: 0 | N31: =$D31+$G31+$J31+$M31 -> 703 | O31: 183.09 | P31: 2374 | Q31: 1406
A32: Clayton Elementary | B32: 183.09 | C32: 0.5 | D32: 703 | G32: 0 | J32: 0 | M32: 0 | N32: =$D32+$G32+$J32+$M32 -> 703 | O32: 183.09 | P32: 2374 | Q32: 1406
A33: Bear Creek Elementary | B33: 184.02 | C33: 1 | D33: 521 | E33: 184.16 | F33: 0.25 | G33: 114 | J33: 0 | M33: 0 | N33: =$D33+$G33+$J33+$M33 -> 635 | O33: 184.02 | P33: 869 | Q33: 521 | R33: 184.16 | S33: 667 | T33: 457
A34: T. E. Scott Elementary | B34: 184.06 | C34: 0.667 | D34: 764 | E34: 182.03 | F34: 0.2 | G34: 71 | J34: 0 | M34: 0 | N34: =$D34+$G34+$J34+$M34 -> 835 | O34: 184.06 | P34: 2149 | Q34: 1146 | R34: 182.03 | S34: 361 | T34: 357
A35: Georges Vanier Elementary | B35: 184.06 | C35: 0.333 | D35: 382 | E35: 184.07 | F35: 1 | G35: 359 | J35: 0 | M35: 0 | N35: =$D35+$G35+$J35+$M35 -> 741 | O35: 184.06 | P35: 2149 | Q35: 1146 | R35: 184.07 | S35: 562 | T35: 359
A36: Hyland Elementary | B36: 184.08 | C36: 1 | D36: 570 | G36: 0 | J36: 0 | M36: 0 | N36: =$D36+$G36+$J36+$M36 -> 570 | O36: 184.08 | P36: 872 | Q36: 570
A37: Maple Green Elementary | B37: 184.09 | C37: 0.5 | D37: 193 | E37: 184.1 | F37: 0.5 | G37: 288 | J37: 0 | M37: 0 | N37: =$D37+$G37+$J37+$M37 -> 481 | O37: 184.09 | P37: 581 | Q37: 386 | R37: 184.1 | S37: 778 | T37: 575
A38: Janice Churchill Elementary | B38: 184.1 | C38: 0.5 | D38: 288 | G38: 0 | J38: 0 | M38: 0 | N38: =$D38+$G38+$J38+$M38 -> 288 | O38: 184.1 | P38: 778 | Q38: 575
A39: Chimney Hill Elementary | B39: 184.11 | C39: 1 | D39: 1016 | G39: 0 | J39: 0 | M39: 0 | N39: =$D39+$G39+$J39+$M39 -> 1016 | O39: 184.11 | P39: 1598 | Q39: 1016
A40: Goldstone Park Elementary | B40: 184.12 | C40: 0.5 | D40: 337 | E40: 184.13 | F40: 0.1 | G40: 42 | H40: 184.14 | I40: 0.2 | J40: 143 | M40: 0 | N40: =$D40+$G40+$J40+$M40 -> 522 | O40: 184.12 | P40: 1034 | Q40: 673 | R40: 184.13 | S40: 659 | T40: 417 | U40: 184.14 | V40: 1595 | W40: 717
A41: École Woodward Hill | B41: 184.13 | C41: 0.3 | D41: 125 | E41: 184.12 | F41: 0.3 | G41: 202 | J41: 0 | M41: 0 | N41: =$D41+$G41+$J41+$M41 -> 327 | O41: 184.13 | P41: 659 | Q41: 417 | R41: 184.12 | S41: 1034 | T41: 673
A42: Sullivan Elementary | B42: 184.13 | C42: 0.2 | D42: 83 | E42: 182.03 | F42: 0.4 | G42: 143 | J42: 0 | M42: 0 | N42: =$D42+$G42+$J42+$M42 -> 226 | O42: 184.13 | P42: 659 | Q42: 417 | R42: 182.03 | S42: 361 | T42: 357
A43: Cambridge Elementary | B43: 184.14 | C43: 0.8 | D43: 574 | E43: 184.13 | F43: 0.2 | G43: 83 | J43: 0 | M43: 0 | N43: =$D43+$G43+$J43+$M43 -> 657 | O43: 184.14 | P43: 1595 | Q43: 717 | R43: 184.13 | S43: 659 | T43: 417
A44: M. B. Sanford Elementary | B44: 184.16 | C44: 0.6 | D44: 274 | G44: 0 | J44: 0 | M44: 0 | N44: =$D44+$G44+$J44+$M44 -> 274 | O44: 184.16 | P44: 667 | Q44: 457
A45: Brookside Elementary | B45: 184.16 | C45: 0.15 | D45: 69 | E45: 184.15 | F45: 1 | G45: 305 | H45: 184.09 | I45: 0.5 | J45: 193 | M45: 0 | N45: =$D45+$G45+$J45+$M45 -> 567 | O45: 184.16 | P45: 667 | Q45: 457 | R45: 184.15 | S45: 347 | T45: 305 | U45: 184.09 | V45: 581 | W45: 386
A46: W. E. Kinvig Elementary | B46: 185.05 | C46: 0.8 | D46: 470 | G46: 0 | J46: 0 | M46: 0 | N46: =$D46+$G46+$J46+$M46 -> 470 | O46: 185.05 | P46: 805 | Q46: 587
A47: Panorama Park Elementary | B47: 185.07 | C47: 0.333 | D47: 306 | G47: 0 | J47: 0 | M47: 0 | N47: =$D47+$G47+$J47+$M47 -> 306 | O47: 185.07 | P47: 1379 | Q47: 919
A48: North Ridge Elementary | B48: 185.07 | C48: 0.333 | D48: 306 | E48: 184.12 | F48: 0.2 | G48: 135 | H48: 184.13 | I48: 0.2 | J48: 83 | M48: 0 | N48: =$D48+$G48+$J48+$M48 -> 524 | O48: 185.07 | P48: 1379 | Q48: 919 | R48: 184.12 | S48: 1034 | T48: 673 | U48: 184.13 | V48: 659 | W48: 417
A49: Kennedy Trail Elementary | B49: 185.09 | C49: 0.667 | D49: 237 | G49: 0 | J49: 0 | M49: 0 | N49: =$D49+$G49+$J49+$M49 -> 237 | O49: 185.09 | P49: 602 | Q49: 356
A50: Strawberry Hill Elementary | B50: 185.1 | C50: 0.5 | D50: 239 | E50: 185.11 | F50: 0.333 | G50: 196 | J50: 0 | M50: 0 | N50: =$D50+$G50+$J50+$M50 -> 435 | O50: 185.1 | P50: 845 | Q50: 477 | R50: 185.11 | S50: 1103 | T50: 589
A51: Westerman Elementary | B51: 185.11 | C51: 0.667 | D51: 393 | G51: 0 | J51: 0 | M51: 0 | N51: =$D51+$G51+$J51+$M51 -> 393 | O51: 185.11 | P51: 1103 | Q51: 589
A52: Martha Jane Norris Elementary | B52: 185.12 | C52: 0.5 | D52: 266 | G52: 0 | J52: 0 | M52: 0 | N52: =$D52+$G52+$J52+$M52 -> 266 | O52: 185.12 | P52: 865 | Q52: 532
A53: École Henry Bose | B53: 185.12 | C53: 0.5 | D53: 266 | E53: 185.05 | F53: 0.2 | G53: 117 | J53: 0 | M53: 0 | N53: =$D53+$G53+$J53+$M53 -> 383 | O53: 185.12 | P53: 865 | Q53: 532 | R53: 185.05 | S53: 805 | T53: 587
A54: Newton Elementary | B54: 185.15 | C54: 0.667 | D54: 265 | E54: 185.16 | F54: 0.5 | G54: 209 | J54: 0 | M54: 0 | N54: =$D54+$G54+$J54+$M54 -> 474 | O54: 185.15 | P54: 708 | Q54: 397 | R54: 185.16 | S54: 664 | T54: 418
A55: Dr. F. D. Sinclair Elementary | B55: 185.16 | C55: 0.5 | D55: 209 | E55: 185.1 | F55: 0.5 | G55: 239 | J55: 0 | M55: 0 | N55: =$D55+$G55+$J55+$M55 -> 448 | O55: 185.16 | P55: 664 | Q55: 418 | R55: 185.1 | S55: 845 | T55: 477
A56: Boundary Park Elementary | B56: 185.17 | C56: 1 | D56: 267 | G56: 0 | J56: 0 | M56: 0 | N56: =$D56+$G56+$J56+$M56 -> 267 | O56: 185.17 | P56: 341 | Q56: 267
A57: J. T. Brown Elementary | B57: 185.18 | C57: 0.667 | D57: 257 | G57: 0 | J57: 0 | M57: 0 | N57: =$D57+$G57+$J57+$M57 -> 257 | O57: 185.18 | P57: 554 | Q57: 385
A58: Colebrook Elementary | B58: 185.18 | C58: 0.333 | D58: 128 | E58: 185.08 | F58: 1 | G58: 124 | H58: 185.07 | I58: 0.333 | J58: 306 | M58: 0 | N58: =$D58+$G58+$J58+$M58 -> 558 | O58: 185.18 | P58: 554 | Q58: 385 | R58: 185.08 | S58: 147 | T58: 124 | U58: 185.07 | V58: 1379 | W58: 919
A59: Beaver Creek Elementary | B59: 185.19 | C59: 1 | D59: 546 | E59: 185.2 | F59: 1 | G59: 490 | J59: 0 | M59: 0 | N59: =$D59+$G59+$J59+$M59 -> 1036 | O59: 185.19 | P59: 874 | Q59: 546 | R59: 185.2 | S59: 823 | T59: 490
A60: Cougar Creek Elementary | B60: 185.21 | C60: 1 | D60: 278 | E60: 185.22 | F60: 1 | G60: 302 | J60: 0 | M60: 0 | N60: =$D60+$G60+$J60+$M60 -> 580 | O60: 185.21 | P60: 466 | Q60: 278 | R60: 185.22 | S60: 494 | T60: 302
A61: Cedar Hills Elementary | B61: 186.01 | C61: 0.25 | D61: 137 | E61: 186.02 | F61: 0.25 | G61: 109 | J61: 0 | M61: 0 | N61: =$D61+$G61+$J61+$M61 -> 246 | O61: 186.01 | P61: 809 | Q61: 549 | R61: 186.02 | S61: 653 | T61: 437
A62: Prince Charles Elementary | B62: 186.01 | C62: 0.25 | D62: 137 | E62: 186.02 | F62: 0.75 | G62: 328 | H62: 192 | I62: 0.33 | J62: 92 | M62: 0 | N62: =$D62+$G62+$J62+$M62 -> 557 | O62: 186.01 | P62: 809 | Q62: 549 | R62: 186.02 | S62: 653 | T62: 437 | U62: 192 | V62: 415 | W62: 278
A63: Royal Heights Elementary | B63: 186.01 | C63: 0.5 | D63: 275 | G63: 0 | J63: 0 | M63: 0 | N63: =$D63+$G63+$J63+$M63 -> 275 | O63: 186.01 | P63: 809 | Q63: 549
A64: Kirkbride Elementary | B64: 186.05 | C64: 0.5 | D64: 335 | E64: 186.06 | F64: 0.5 | G64: 159 | J64: 0 | M64: 0 | N64: =$D64+$G64+$J64+$M64 -> 494 | O64: 186.05 | P64: 1053 | Q64: 670 | R64: 186.06 | S64: 546 | T64: 317
A65: Senator Reid Elementary | B65: 186.05 | C65: 0.5 | D65: 335 | E65: 186.06 | F65: 0.25 | G65: 79 | J65: 0 | M65: 0 | N65: =$D65+$G65+$J65+$M65 -> 414 | O65: 186.05 | P65: 1053 | Q65: 670 | R65: 186.06 | S65: 546 | T65: 317
A66: Betty Huff Elementary | B66: 186.05 | C66: 0.5 | D66: 335 | E66: 186.06 | F66: 0.25 | G66: 79 | J66: 0 | M66: 0 | N66: =$D66+$G66+$J66+$M66 -> 414 | O66: 186.05 | P66: 1053 | Q66: 670 | R66: 186.06 | S66: 546 | T66: 317
A67: David Brankin Elementary | B67: 186.06 | C67: 0.25 | D67: 79 | E67: 185.09 | F67: 0.333 | G67: 106 | H67: 186.07 | I67: 0.5 | J67: 242 | K67: 185.15 | L67: 0.333 | M67: 67 | N67: =$D67+$G67+$J67+$M67 -> 494 | O67: 186.06 | P67: 546 | Q67: 317 | R67: 186.06 | S67: 546 | T67: 317 | U67: 186.07 | V67: 805 | W67: 484 | X67: 181.15 | Y67: 270 | Z67: 200
A68: Cindrich Elementary | B68: 186.08 | C68: 0.5 | D68: 288 | E68: 186.07 | F68: 0.5 | G68: 242 | J68: 0 | M68: 0 | N68: =$D68+$G68+$J68+$M68 -> 530 | O68: 186.08 | P68: 896 | Q68: 575 | R68: 186.07 | S68: 805 | T68: 484
A69: Green Timbers Elementary | B69: 187.03 | C69: 0.5 | D69: 291 | E69: 187.05 | F69: 0.25 | G69: 144 | J69: 0 | M69: 0 | N69: =$D69+$G69+$J69+$M69 -> 435 | O69: 187.03 | P69: 894 | Q69: 582 | R69: 187.05 | S69: 961 | T69: 577
A70: Bonaccord Elementary | B70: 187.03 | C70: 0.25 | D70: 146 | E70: 189.05 | F70: 0.667 | G70: 319 | J70: 0 | M70: 0 | N70: =$D70+$G70+$J70+$M70 -> 465 | O70: 187.03 | P70: 894 | Q70: 582 | R70: 189.05 | S70: 704 | T70: 479
A71: École Simon Cunningham | B71: 187.04 | C71: 1 | D71: 113 | E71: 187.05 | F71: 0.25 | G71: 144 | H71: 190.01 | I71: 0.25 | J71: 135 | M71: 0 | N71: =$D71+$G71+$J71+$M71 -> 392 | O71: 187.04 | P71: 186 | Q71: 113 | R71: 187.05 | S71: 961 | T71: 577 | U71: 190.01 | V71: 814 | W71: 540
A72: Creekside Elementary | B72: 187.05 | C72: 0.5 | D72: 289 | G72: 0 | J72: 0 | M72: 0 | N72: =$D72+$G72+$J72+$M72 -> 289 | O72: 187.05 | P72: 961 | Q72: 577
A73: Woodland Park Elementary | B73: 187.06 | C73: 0.5 | D73: 369 | E73: 187.11 | F73: 0.333 | G73: 206 | J73: 0 | M73: 0 | N73: =$D73+$G73+$J73+$M73 -> 575 | O73: 187.06 | P73: 979 | Q73: 737 | R73: 187.11 | S73: 1010 | T73: 618
A74: Serpentine Heights Elementary | B74: 187.06 | C74: 0.5 | D74: 369 | E74: 188.04 | F74: 1 | G74: 446 | J74: 0 | M74: 0 | N74: =$D74+$G74+$J74+$M74 -> 815 | O74: 187.06 | P74: 979 | Q74: 737 | R74: 188.04 | S74: 552 | T74: 446
A75: École Frost Road | B75: 187.11 | C75: 0.667 | D75: 412 | E75: 187.07 | F75: 1 | G75: 203 | J75: 0 | M75: 0 | N75: =$D75+$G75+$J75+$M75 -> 615 | O75: 187.11 | P75: 1010 | Q75: 618 | R75: 187.07 | S75: 247 | T75: 203
A76: Berkshire Park Elementary | B76: 187.12 | C76: 1 | D76: 353 | G76: 0 | J76: 0 | M76: 0 | N76: =$D76+$G76+$J76+$M76 -> 353 | O76: 187.12 | P76: 503 | Q76: 353
A77: Coyote Creek Elementary | B77: 187.13 | C77: 1 | D77: 199 | E77: 182.03 | F77: 0.4 | G77: 143 | J77: 0 | M77: 0 | N77: =$D77+$G77+$J77+$M77 -> 342 | O77: 187.13 | P77: 262 | Q77: 199 | R77: 182.03 | S77: 361 | T77: 357
A78: Walnut Road Elementary | B78: 187.16 | C78: 0.333 | D78: 99 | E78: 187.14 | F78: 1 | G78: 265 | H78: 187.15 | I78: 1 | J78: 390 | M78: 0 | N78: =$D78+$G78+$J78+$M78 -> 754 | O78: 187.16 | P78: 399 | Q78: 298 | R78: 187.14 | S78: 443 | T78: 265 | U78: 187.15 | V78: 540 | W78: 390
A79: Dogwood Elementary | B79: 188.01 | C79: 1 | D79: 337 | E79: 188.02 | F79: 0.75 | G79: 263 | J79: 0 | M79: 0 | N79: =$D79+$G79+$J79+$M79 -> 600 | O79: 188.01 | P79: 436 | Q79: 337 | R79: 188.02 | S79: 414 | T79: 350
A80: École Erma Stephenson | B80: 188.02 | C80: 0.25 | D80: 88 | E80: 188.08 | F80: 0.5 | G80: 278 | H80: 188.07 | I80: 0.25 | J80: 116 | M80: 0 | N80: =$D80+$G80+$J80+$M80 -> 482 | O80: 188.02 | P80: 414 | Q80: 350 | R80: 188.08 | S80: 606 | T80: 556 | U80: 188.07 | V80: 474 | W80: 463
A81: Bothwell Elementary | B81: 188.05 | C81: 1 | D81: 298 | E81: 188.06 | F81: 0.8 | G81: 110 | J81: 0 | M81: 0 | N81: =$D81+$G81+$J81+$M81 -> 408 | O81: 188.05 | P81: 332 | Q81: 298 | R81: 188.06 | S81: 190 | T81: 138
A82: Port Kells Elementary | B82: 188.06 | C82: 0.2 | D82: 28 | E82: 182.06 | F82: 1 | G82: 92 | J82: 0 | M82: 0 | N82: =$D82+$G82+$J82+$M82 -> 120 | O82: 188.06 | P82: 190 | Q82: 138 | R82: 182.06 | S82: 120 | T82: 92
A83: École Fraser Wood | B83: 188.07 | C83: 0.75 | D83: 347 | E83: 188.08 | F83: 0.5 | G83: 278 | J83: 0 | M83: 0 | N83: =$D83+$G83+$J83+$M83 -> 625 | O83: 188.07 | P83: 474 | Q83: 463 | R83: 188.08 | S83: 606 | T83: 556
A84: École Riverdale | B84: 189.03 | C84: 0.75 | D84: 204 | G84: 0 | J84: 0 | M84: 0 | N84: =$D84+$G84+$J84+$M84 -> 204 | O84: 189.03 | P84: 373 | Q84: 272
A85: Hjorth Road Elementary | B85: 189.05 | C85: 0.333 | D85: 160 | E85: 190.03 | F85: 0.2 | G85: 117 | J85: 0 | M85: 0 | N85: =$D85+$G85+$J85+$M85 -> 277 | O85: 189.05 | P85: 704 | Q85: 479 | R85: 190.03 | S85: 803 | T85: 584
A86: Harold Bishop Elementary | B86: 189.07 | C86: 1 | D86: 239 | E86: 189.1 | F86: 0.5 | G86: 355 | H86: 189.09 | I86: 0.5 | J86: 184 | M86: 0 | N86: =$D86+$G86+$J86+$M86 -> 778 | O86: 189.07 | P86: 393 | Q86: 239 | R86: 189.1 | S86: 903 | T86: 710 | U86: 189.09 | V86: 443 | W86: 368
A87: Holly Elementary | B87: 189.08 | C87: 1 | D87: 511 | G87: 0 | J87: 0 | M87: 0 | N87: =$D87+$G87+$J87+$M87 -> 511 | O87: 189.08 | P87: 826 | Q87: 511
A88: William F. Davidson Elementary | B88: 189.1 | C88: 0.5 | D88: 355 | E88: 189.09 | F88: 0.5 | G88: 184 | J88: 0 | M88: 0 | N88: =$D88+$G88+$J88+$M88 -> 539 | O88: 189.1 | P88: 903 | Q88: 710 | R88: 189.09 | S88: 443 | T88: 368
A89: Lena Shaw Elementary | B89: 190.01 | C89: 0.75 | D89: 405 | E89: 189.06 | F89: 1 | G89: 238 | H89: 187.03 | I89: 0.25 | J89: 146 | M89: 0 | N89: =$D89+$G89+$J89+$M89 -> 789 | O89: 190.01 | P89: 814 | Q89: 540 | R89: 189.06 | S89: 348 | T89: 238 | U89: 187.03 | V89: 894 | W89: 582
A90: Mary Jane Shannon Elementary | B90: 190.03 | C90: 0.8 | D90: 467 | E90: 190.04 | F90: 0.1 | G90: 54 | J90: 0 | M90: 0 | N90: =$D90+$G90+$J90+$M90 -> 521 | O90: 190.03 | P90: 803 | Q90: 584 | R90: 190.04 | S90: 750 | T90: 541
A91: Ellendale Elementary | B91: 190.04 | C91: 0.3 | D91: 162 | E91: 189.03 | F91: 0.25 | G91: 68 | J91: 0 | M91: 0 | N91: =$D91+$G91+$J91+$M91 -> 230 | O91: 190.04 | P91: 750 | Q91: 541 | R91: 189.03 | S91: 373 | T91: 272
A92: James Ardiel Elementary | B92: 190.04 | C92: 0.6 | D92: 325 | G92: 0 | J92: 0 | M92: 0 | N92: =$D92+$G92+$J92+$M92 -> 325 | O92: 190.04 | P92: 750 | Q92: 541
A93: Old Yale Road Elementary | B93: 191.03 | C93: 0.5 | D93: 217 | E93: 191.04 | F93: 0.5 | G93: 203 | J93: 0 | M93: 0 | N93: =$D93+$G93+$J93+$M93 -> 420 | O93: 191.03 | P93: 665 | Q93: 434 | R93: 191.04 | S93: 614 | T93: 405
A94: A. H. P. Matthew Elementary | B94: 191.03 | C94: 0.5 | D94: 217 | E94: 191.04 | F94: 0.5 | G94: 203 | J94: 0 | M94: 0 | N94: =$D94+$G94+$J94+$M94 -> 420 | O94: 191.03 | P94: 665 | Q94: 434 | R94: 191.04 | S94: 614 | T94: 405
A95: École K.B. Woodward | B95: 191.05 | C95: 1 | D95: 295 | E95: 191.07 | F95: 1 | G95: 245 | H95: 191.06 | I95: 0.5 | J95: 72 | M95: 0 | N95: =$D95+$G95+$J95+$M95 -> 612 | O95: 191.05 | P95: 400 | Q95: 295 | R95: 191.07 | S95: 311 | T95: 245 | U95: 191.06 | V95: 190 | W95: 143
A96: Forsyth Road Elementary | B96: 191.06 | C96: 0.5 | D96: 72 | E96: 190.05 | F96: 1 | G96: 139 | H96: 190.03 | I96: 0.333 | J96: 194 | M96: 0 | N96: =$D96+$G96+$J96+$M96 -> 405 | O96: 191.06 | P96: 190 | Q96: 143 | R96: 190.05 | S96: 202 | T96: 139 | U96: 190.03 | V96: 803 | W96: 584
A97: Bridgeview Elementary | B97: 192 | C97: 0.667 | D97: 185 | G97: 0 | J97: 0 | M97: 0 | N97: =$D97+$G97+$J97+$M97 -> 185 | O97: 192 | P97: 415 | Q97: 278
N98: =SUM(N2:N97) -> 44310
G100: School | I100: Population | K100: Index | L100: Population | M100: Capacity | N100: Overcap | O100: Max | P100: Can Expand
A101: Ecole Earl Marriott | B101: Tract | C101: Proportion | D101: Population | G101: Clayton Heights Secondary | I101: 3049 | K101: 1 | L101: 3049 | M101: 2580 | N101: =L101-M101 -> 469 | O101: 3000 | P101: =O101-M101 -> 420 | Q101: 4 | R101: 18
...

Sheet Elementary Adj Matrix
B1: {=TRANSPOSE(A2:A97)} -> Katzie Elementary | C1: École Woodward Hill | D1: Cambridge Elementary | E1: Sunnyside Elementary | F1: Hillcrest Elementary | G1: Hazelgrove Elementary | H1: École Erma Stephenson | I1: Panorama Park Elementary | J1: École Frost Road | K1: Walnut Road Elementary | L1: T. E. Scott Elementary | M1: École K.B. Woodward | N1: Sullivan Elementary | O1: Clayton Elementary | P1: South Meridian Elementary | Q1: École Ocean Cliff | R1: Surrey Centre Elementary | S1: Goldstone Park Elementary | T1: Rosemary Heights Elementary | U1: Old Yale Road Elementary | V1: Semiahmoo Trail Elementary | W1: Chimney Hill Elementary | X1: École Fraser Wood | Y1: Adams Road Elementary | Z1: Hall's Prairie Elementary | AA1: Pacific Heights Elementary | AB1: White Rock Elementary | AC1: George Greenaway Elementary | AD1: H. T. Thrift Elementary | AE1: William Watson Elementary | AF1: Holly Elementary | AG1: École Riverdale | AH1: A. J. McLellan Elementary | AI1: Hjorth Road Elementary | AJ1: École Peace Arch | AK1: Bayridge Elementary | AL1: École Sunrise Ridge | AM1: Forsyth Road Elementary | AN1: Morgan Elementary | AO1: A. H. P. Matthew Elementary | AP1: Kennedy Trail Elementary | AQ1: Don Christian Elementary | AR1: Beaver Creek Elementary | AS1: École Martha Currie | AT1: Chantrell Creek Elementary | AU1: Coyote Creek Elementary | AV1: Coast Meridian Elementary | AW1: J. T. Brown Elementary | AX1: Hyland Elementary | AY1: Martha Jane Norris Elementary | AZ1: Cindrich Elementary | BA1: Ellendale Elementary | BB1: École Henry Bose | BC1: M. B. Sanford Elementary | BD1: Woodland Park Elementary | BE1: École Simon Cunningham | BF1: École Crescent Park | BG1: North Ridge Elementary | BH1: David Brankin Elementary | BI1: Port Kells Elementary | BJ1: Bridgeview Elementary | BK1: Mary Jane Shannon Elementary | BL1: Georges Vanier Elementary | BM1: Dr. F. D. Sinclair Elementary | BN1: Boundary Park Elementary | BO1: Maple Green Elementary | BP1: Colebrook Elementary | BQ1: East Kensington Elementary | BR1: Ray Shepherd Elementary | BS1: Green Timbers Elementary | BT1: Berkshire Park Elementary | BU1: Bonaccord Elementary | BV1: Cedar Hills Elementary | BW1: Kirkbride Elementary | BX1: Bear Creek Elementary | BY1: Lena Shaw Elementary | BZ1: Prince Charles Elementary | CA1: James Ardiel Elementary | CB1: Westerman Elementary | CC1: Bothwell Elementary | CD1: Serpentine Heights Elementary | CE1: Latimer Road Elementary | CF1: École Jessie Lee | CG1: Dogwood Elementary | CH1: Harold Bishop Elementary | CI1: Strawberry Hill Elementary | CJ1: W. E. Kinvig Elementary | CK1: Creekside Elementary | CL1: Janice Churchill Elementary | CM1: William F. Davidson Elementary | CN1: Brookside Elementary | CO1: Senator Reid Elementary | CP1: Betty Huff Elementary | CQ1: Newton Elementary | CR1: Cougar Creek Elementary | CS1: Royal Heights Elementary
A2: Katzie Elementary | B2: 1 | C2: 0 | D2: 0 | E2: 0 | F2: 0 | G2: 1 | H2: 0 | I2: 0 | J2: 0 | K2: 0 | L2: 0 | M2: 0 | N2: 0 | O2: 0 | P2: 0 | Q2: 0 | R2: 0 | S2: 0 | T2: 0 | U2: 0 | V2: 0 | W2: 0 | X2: 0 | Y2: 0 | Z2: 0 | AA2: 0 | AB2: 0 | AC2: 0 | AD2: 0 | AE2: 0 | AF2: 0 | AG2: 0 | AH2: 0 | AI2: 0 | AJ2: 0 | AK2: 0 | AL2: 0 | AM2: 0 | AN2: 0 | AO2: 0 | AP2: 0 | AQ2: 0 | AR2: 0 | AS2: 0 | AT2: 0 | AU2: 0 | AV2: 0 | AW2: 0 | AX2: 0 | AY2: 0 | AZ2: 0 | BA2: 0 | BB2: 0 | BC2: 0 | BD2: 0 | BE2: 0 | BF2: 0 | BG2: 0 | BH2: 0 | BI2: 0 | BJ2: 0 | BK2: 0 | BL2: 0 | BM2: 0 | BN2: 0 | BO2: 0 | BP2: 0 | BQ2: 0 | BR2: 0 | BS2: 0 | BT2: 0 | BU2: 0 | BV2: 0 | BW2: 0 | BX2: 0 | BY2: 0 | BZ2: 0 | CA2: 0 | CB2: 0 | CC2: 0 | CD2: 0 | CE2: 1 | CF2: 0 | CG2: 0 | CH2: 0 | CI2: 0 | CJ2: 0 | CK2: 0 | CL2: 0 | CM2: 0 | CN2: 0 | CO2: 0 | CP2: 0 | CQ2: 0 | CR2: 0 | CS2: 0 | CT2: =SUM(A2:CS2) -> 3
A3: École Woodward Hill | B3: 0 | C3: 1 | D3: 1 | E3: 0 | F3: 0 | G3: 0 | H3: 0 | I3: 0 | J3: 0 | K3: 0 | L3: 0 | M3: 0 | N3: 0 | O3: 0 | P3: 0 | Q3: 0 | R3: 0 | S3: 1 | T3: 0 | U3: 0 | V3: 0 | W3: 0 | X3: 0 | Y3: 0 | Z3: 0 | AA3: 0 | AB3: 0 | AC3: 0 | AD3: 0 | AE3: 0 | AF3: 0 | AG3: 0 | AH3: 0 | AI3: 0 | AJ3: 0 | AK3: 0 | AL3: 0 | AM3: 0 | AN3: 0 | AO3: 0 | AP3: 0 | AQ3: 0 | AR3: 0 | AS3: 0 | AT3: 0 | AU3: 0 | AV3: 0 | AW3: 0 | AX3: 1 | AY3: 0 | AZ3: 0 | BA3: 0 | BB3: 0 | BC3: 0 | BD3: 0 | BE3: 0 | BF3: 0 | BG3: 1 | BH3: 0 | BI3: 0 | BJ3: 0 | BK3: 0 | BL3: 0 | BM3: 0 | BN3: 0 | BO3: 0 | BP3: 1 | BQ3: 0 | BR3: 0 | BS3: 0 | BT3: 0 | BU3: 0 | BV3: 0 | BW3: 0 | BX3: 0 | BY3: 0 | BZ3: 0 | CA3: 0 | CB3: 0 | CC3: 0 | CD3: 0 | CE3: 0 | CF3: 0 | CG3: 0 | CH3: 0 | CI3: 0 | CJ3: 0 | CK3: 0 | CL3: 0 | CM3: 0 | CN3: 0 | CO3: 0 | CP3: 0 | CQ3: 0 | CR3: 0 | CS3: 0 | CT3: =SUM(A3:CS3) -> 6
A4: Cambridge Elementary | B4: 0 | C4: 1 | D4: 1 | E4: 0 | F4: 0 | G4: 0 | H4: 0 | I4: 0 | J4: 0 | K4: 0 | L4: 1 | M4: 0 | N4: 1 | O4: 0 | P4: 0 | Q4: 0 | R4: 0 | S4: 1 | T4: 0 | U4: 0 | V4: 0 | W4: 0 | X4: 0 | Y4: 0 | Z4: 0 | AA4: 0 | AB4: 0 | AC4: 0 | AD4: 0 | AE4: 0 | AF4: 0 | AG4: 0 | AH4: 0 | AI4: 0 | AJ4: 0 | AK4: 0 | AL4: 0 | AM4: 0 | AN4: 0 | AO4: 0 | AP4: 0 | AQ4: 0 | AR4: 1 | AS4: 0 | AT4: 0 | AU4: 0 | AV4: 0 | AW4: 0 | AX4: 1 | AY4: 0 | AZ4: 0 | BA4: 0 | BB4: 0 | BC4: 0 | BD4: 0 | BE4: 0 | BF4: 0 | BG4: 1 | BH4: 0 | BI4: 0 | BJ4: 0 | BK4: 0 | BL4: 0 | BM4: 0 | BN4: 0 | BO4: 0 | BP4: 1 | BQ4: 0 | BR4: 0 | BS4: 0 | BT4: 0 | BU4: 0 | BV4: 0 | BW4: 0 | BX4: 0 | BY4: 0 | BZ4: 0 | CA4: 0 | CB4: 0 | CC4: 0 | CD4: 0 | CE4: 0 | CF4: 0 | CG4: 0 | CH4: 0 | CI4: 0 | CJ4: 0 | CK4: 0 | CL4: 0 | CM4: 0 | CN4: 0 | CO4: 0 | CP4: 0 | CQ4: 0 | CR4: 0 | CS4: 0 | CT4: =SUM(A4:CS4) -> 9
A5: Sunnyside Elementary | B5: 0 | C5: 0 | D5: 0 | E5: 1 | F5: 0 | G5: 0 | H5: 0 | I5: 0 | J5: 0 | K5: 0 | L5: 0 | M5: 0 | N5: 0 | O5: 0 | P5: 0 | Q5: 0 | R5: 0 | S5: 0 | T5: 0 | U5: 0 | V5: 0 | W5: 0 | X5: 0 | Y5: 0 | Z5: 0 | AA5: 1 | AB5: 0 | AC5: 0 | AD5: 0 | AE5: 0 | AF5: 0 | AG5: 0 | AH5: 0 | AI5: 0 | AJ5: 0 | AK5: 0 | AL5: 0 | AM5: 0 | AN5: 1 | AO5: 0 | AP5: 0 | AQ5: 0 | AR5: 0 | AS5: 0 | AT5: 0 | AU5: 0 | AV5: 0 | AW5: 0 | AX5: 0 | AY5: 0 | AZ5: 0 | BA5: 0 | BB5: 0 | BC5: 0 | BD5: 0 | BE5: 0 | BF5: 0 | BG5: 0 | BH5: 0 | BI5: 0 | BJ5: 0 | BK5: 0 | BL5: 0 | BM5: 0 | BN5: 0 | BO5: 0 | BP5: 0 | BQ5: 0 | BR5: 0 | BS5: 0 | BT5: 0 | BU5: 0 | BV5: 0 | BW5: 0 | BX5: 0 | BY5: 0 | BZ5: 0 | CA5: 0 | CB5: 0 | CC5: 0 | CD5: 0 | CE5: 0 | CF5: 1 | CG5: 0 | CH5: 0 | CI5: 0 | CJ5: 0 | CK5: 0 | CL5: 0 | CM5: 0 | CN5: 0 | CO5: 0 | CP5: 0 | CQ5: 0 | CR5: 0 | CS5: 0 | CT5: =SUM(A5:CS5) -> 4
A6: Hillcrest Elementary | B6: 0 | C6: 0 | D6: 0 | E6: 0 | F6: 1 | G6: 1 | H6: 0 | I6: 0 | J6: 0 | K6: 0 | L6: 0 | M6: 0 | N6: 0 | O6: 1 | P6: 0 | Q6: 0 | R6: 0 | S6: 0 | T6: 0 | U6: 0 | V6: 0 | W6: 0 | X6: 0 | Y6: 1 | Z6: 0 | AA6: 0 | AB6: 0 | AC6: 0 | AD6: 0 | AE6: 0 | AF6: 0 | AG6: 0 | AH6: 0 | AI6: 0 | AJ6: 0 | AK6: 0 | AL6: 0 | AM6: 0 | AN6: 0 | AO6: 0 | AP6: 0 | AQ6: 1 | AR6: 0 | AS6: 0 | AT6: 0 | AU6: 0 | AV6: 0 | AW6: 0 | AX6: 0 | AY6: 0 | AZ6: 0 | BA6: 0 | BB6: 0 | BC6: 0 | BD6: 0 | BE6: 0 | BF6: 0 | BG6: 0 | BH6: 0 | BI6: 0 | BJ6: 0 | BK6: 0 | BL6: 0 | BM6: 0 | BN6: 0 | BO6: 0 | BP6: 0 | BQ6: 0 | BR6: 0 | BS6: 0 | BT6: 0 | BU6: 0 | BV6: 0 | BW6: 0 | BX6: 0 | BY6: 0 | BZ6: 0 | CA6: 0 | CB6: 0 | CC6: 0 | CD6: 0 | CE6: 1 | CF6: 0 | CG6: 0 | CH6: 0 | CI6: 0 | CJ6: 0 | CK6: 0 | CL6: 0 | CM6: 0 | CN6: 0 | CO6: 0 | CP6: 0 | CQ6: 0 | CR6: 0 | CS6: 0 | CT6: =SUM(A6:CS6) -> 6
A7: Hazelgrove Elementary | B7: 1 | C7: 0 | D7: 0 | E7: 0 | F7: 1 | G7: 1 | H7: 0 | I7: 0 | J7: 0 | K7: 0 | L7: 0 | M7: 0 | N7: 0 | O7: 1 | P7: 0 | Q7: 0 | R7: 0 | S7: 0 | T7: 0 | U7: 0 | V7: 0 | W7: 0 | X7: 0 | Y7: 0 | Z7: 0 | AA7: 0 | AB7: 0 | AC7: 0 | AD7: 0 | AE7: 0 | AF7: 0 | AG7: 0 | AH7: 0 | AI7: 0 | AJ7: 0 | AK7: 0 | AL7: 0 | AM7: 0 | AN7: 0 | AO7: 0 | AP7: 0 | AQ7: 0 | AR7: 0 | AS7: 0 | AT7: 0 | AU7: 0 | AV7: 0 | AW7: 0 | AX7: 0 | AY7: 0 | AZ7: 0 | BA7: 0 | BB7: 0 | BC7: 0 | BD7: 0 | BE7: 0 | BF7: 0 | BG7: 0 | BH7: 0 | BI7: 0 | BJ7: 0 | BK7: 0 | BL7: 0 | BM7: 0 | BN7: 0 | BO7: 0 | BP7: 0 | BQ7: 0 | BR7: 0 | BS7: 0 | BT7: 0 | BU7: 0 | BV7: 0 | BW7: 0 | BX7: 0 | BY7: 0 | BZ7: 0 | CA7: 0 | CB7: 0 | CC7: 0 | CD7: 0 | CE7: 1 | CF7: 0 | CG7: 0 | CH7: 0 | CI7: 0 | CJ7: 0 | CK7: 0 | CL7: 0 | CM7: 0 | CN7: 0 | CO7: 0 | CP7: 0 | CQ7: 0 | CR7: 0 | CS7: 0 | CT7: =SUM(A7:CS7) -> 5
A8: École Erma Stephenson | B8: 0 | C8: 0 | D8: 0 | E8: 0 | F8: 0 | G8: 0 | H8: 1 | I8: 0 | J8: 0 | K8: 0 | L8: 0 | M8: 0 | N8: 0 | O8: 0 | P8: 0 | Q8: 0 | R8: 0 | S8: 0 | T8: 0 | U8: 0 | V8: 0 | W8: 0 | X8: 1 | Y8: 0 | Z8: 0 | AA8: 0 | AB8: 0 | AC8: 0 | AD8: 0 | AE8: 0 | AF8: 0 | AG8: 0 | AH8: 0 | AI8: 0 | AJ8: 0 | AK8: 0 | AL8: 0 | AM8: 0 | AN8: 0 | AO8: 0 | AP8: 0 | AQ8: 0 | AR8: 0 | AS8: 0 | AT8: 0 | AU8: 0 | AV8: 0 | AW8: 0 | AX8: 0 | AY8: 0 | AZ8: 0 | BA8: 0 | BB8: 0 | BC8: 0 | BD8: 0 | BE8: 0 | BF8: 0 | BG8: 0 | BH8: 0 | BI8: 0 | BJ8: 0 | BK8: 0 | BL8: 0 | BM8: 0 | BN8: 0 | BO8: 0 | BP8: 0 | BQ8: 0 | BR8: 0 | BS8: 0 | BT8: 0 | BU8: 0 | BV8: 0 | BW8: 0 | BX8: 0 | BY8: 0 | BZ8: 0 | CA8: 0 | CB8: 0 | CC8: 0 | CD8: 0 | CE8: 0 | CF8: 0 | CG8: 1 | CH8: 0 | CI8: 0 | CJ8: 0 | CK8: 0 | CL8: 0 | CM8: 0 | CN8: 0 | CO8: 0 | CP8: 0 | CQ8: 0 | CR8: 0 | CS8: 0 | CT8: =SUM(A8:CS8) -> 3
A9: Panorama Park Elementary | B9: 0 | C9: 0 | D9: 0 | E9: 0 | F9: 0 | G9: 0 | H9: 0 | I9: 1 | J9: 0 | K9: 0 | L9: 0 | M9: 0 | N9: 0 | O9: 0 | P9: 0 | Q9: 0 | R9: 0 | S9: 0 | T9: 0 | U9: 0 | V9: 0 | W9: 0 | X9: 0 | Y9: 0 | Z9: 0 | AA9: 0 | AB9: 0 | AC9: 0 | AD9: 0 | AE9: 0 | AF9: 0 | AG9: 0 | AH9: 0 | AI9: 0 | AJ9: 0 | AK9: 0 | AL9: 0 | AM9: 0 | AN9: 0 | AO9: 0 | AP9: 0 | AQ9: 0 | AR9: 0 | AS9: 0 | AT9: 0 | AU9: 0 | AV9: 0 | AW9: 1 | AX9: 0 | AY9: 1 | AZ9: 0 | BA9: 0 | BB9: 1 | BC9: 0 | BD9: 0 | BE9: 0 | BF9: 0 | BG9: 1 | BH9: 0 | BI9: 0 | BJ9: 0 | BK9: 0 | BL9: 0 | BM9: 0 | BN9: 0 | BO9: 0 | BP9: 1 | BQ9: 0 | BR9: 0 | BS9: 0 | BT9: 0 | BU9: 0 | BV9: 0 | BW9: 0 | BX9: 0 | BY9: 0 | BZ9: 0 | CA9: 0 | CB9: 0 | CC9: 0 | CD9: 0 | CE9: 0 | CF9: 0 | CG9: 0 | CH9: 0 | CI9: 0 | CJ9: 0 | CK9: 0 | CL9: 0 | CM9: 0 | CN9: 0 | CO9: 0 | CP9: 0 | CQ9: 0 | CR9: 0 | CS9: 0 | CT9: =SUM(A9:CS9) -> 6
A10: École Frost Road | B10: 0 | C10: 0 | D10: 0 | E10: 0 | F10: 0 | G10: 0 | H10: 0 | I10: 0 | J10: 1 | K10: 1 | L10: 0 | M10: 0 | N10: 0 | O10: 0 | P10: 0 | Q10: 0 | R10: 0 | S10: 0 | T10: 0 | U10: 0 | V10: 0 | W10: 0 | X10: 0 | Y10: 0 | Z10: 0 | AA10: 0 | AB10: 0 | AC10: 0 | AD10: 0 | AE10: 1 | AF10: 0 | AG10: 0 | AH10: 0 | AI10: 0 | AJ10: 0 | AK10: 0 | AL10: 0 | AM10: 0 | AN10: 0 | AO10: 0 | AP10: 0 | AQ10: 0 | AR10: 0 | AS10: 0 | AT10: 0 | AU10: 0 | AV10: 1 | AW10: 0 | AX10: 0 | AY10: 0 | AZ10: 0 | BA10: 0 | BB10: 0 | BC10: 0 | BD10: 1 | BE10: 0 | BF10: 0 | BG10: 0 | BH10: 0 | BI10: 0 | BJ10: 0 | BK10: 0 | BL10: 0 | BM10: 0 | BN10: 0 | BO10: 0 | BP10: 0 | BQ10: 0 | BR10: 0 | BS10: 0 | BT10: 0 | BU10: 0 | BV10: 0 | BW10: 0 | BX10: 0 | BY10: 0 | BZ10: 0 | CA10: 0 | CB10: 0 | CC10: 0 | CD10: 1 | CE10: 0 | CF10: 0 | CG10: 0 | CH10: 0 | CI10: 0 | CJ10: 0 | CK10: 0 | CL10: 0 | CM10: 0 | CN10: 0 | CO10: 0 | CP10: 0 | CQ10: 0 | CR10: 0 | CS10: 0 | CT10: =SUM(A10:CS10) -> 6
A11: Walnut Road Elementary | B11: 0 | C11: 0 | D11: 0 | E11: 0 | F11: 0 | G11: 0 | H11: 0 | I11: 0 | J11: 1 | K11: 1 | L11: 0 | M11: 0 | N11: 0 | O11: 0 | P11: 0 | Q11: 0 | R11: 0 | S11: 0 | T11: 0 | U11: 0 | V11: 0 | W11: 0 | X11: 0 | Y11: 0 | Z11: 0 | AA11: 0 | AB11: 0 | AC11: 0 | AD11: 0 | AE11: 1 | AF11: 0 | AG11: 0 | AH11: 0 | AI11: 0 | AJ11: 0 | AK11: 0 | AL11: 0 | AM11: 0 | AN11: 0 | AO11: 0 | AP11: 0 | AQ11: 0 | AR11: 0 | AS11: 0 | AT11: 0 | AU11: 1 | AV11: 0 | AW11: 0 | AX11: 0 | AY11: 0 | AZ11: 0 | BA11: 0 | BB11: 0 | BC11: 0 | BD11: 1 | BE11: 0 | BF11: 0 | BG11: 0 | BH11: 0 | BI11: 0 | BJ11: 0 | BK11: 0 | BL11: 0 | BM11: 0 | BN11: 0 | BO11: 0 | BP11: 0 | BQ11: 0 | BR11: 0 | BS11: 0 | BT11: 1 | BU11: 0 | BV11: 0 | BW11: 0 | BX11: 0 | BY11: 0 | BZ11: 0 | CA11: 0 | CB11: 0 | CC11: 0 | CD11: 0 | CE11: 0 | CF11: 0 | CG11: 0 | CH11: 0 | CI11: 0 | CJ11: 0 | CK11: 0 | CL11: 0 | CM11: 0 | CN11: 0 | CO11: 0 | CP11: 0 | CQ11: 0 | CR11: 0 | CS11: 0 | CT11: =SUM(A11:CS11) -> 6
A12: T. E. Scott Elementary | B12: 0 | C12: 0 | D12: 1 | E12: 0 | F12: 0 | G12: 0 | H12: 0 | I12: 0 | J12: 0 | K12: 0 | L12: 1 | M12: 0 | N12: 1 | O12: 0 | P12: 0 | Q12: 0 | R12: 0 | S12: 1 | T12: 0 | U12: 0 | V12: 0 | W12: 1 | X12: 0 | Y12: 0 | Z12: 0 | AA12: 0 | AB12: 0 | AC12: 0 | AD12: 0 | AE12: 0 | AF12: 0 | AG12: 0 | AH12: 1 | AI12: 0 | AJ12: 0 | AK12: 0 | AL12: 0 | AM12: 0 | AN12: 0 | AO12: 0 | AP12: 0 | AQ12: 0 | AR12: 0 | AS12: 0 | AT12: 0 | AU12: 1 | AV12: 0 | AW12: 0 | AX12: 1 | AY12: 0 | AZ12: 0 | BA12: 0 | BB12: 0 | BC12: 0 | BD12: 0 | BE12: 0 | BF12: 0 | BG12: 0 | BH12: 0 | BI12: 0 | BJ12: 0 | BK12: 0 | BL12: 1 | BM12: 0 | BN12: 0 | BO12: 0 | BP12: 0 | BQ12: 0 | BR12: 0 | BS12: 0 | BT12: 0 | BU12: 0 | BV12: 0 | BW12: 0 | BX12: 0 | BY12: 0 | BZ12: 0 | CA12: 0 | CB12: 0 | CC12: 0 | CD12: 0 | CE12: 0 | CF12: 0 | CG12: 0 | CH12: 0 | CI12: 0 | CJ12: 0 | CK12: 0 | CL12: 0 | CM12: 0 | CN12: 0 | CO12: 0 | CP12: 0 | CQ12: 0 | CR12: 0 | CS12: 0 | CT12: =SUM(A12:CS12) -> 9
A13: École K.B. Woodward | B13: 0 | C13: 0 | D13: 0 | E13: 0 | F13: 0 | G13: 0 | H13: 0 | I13: 0 | J13: 0 | K13: 0 | L13: 0 | M13: 1 | N13: 0 | O13: 0 | P13: 0 | Q13: 0 | R13: 0 | S13: 0 | T13: 0 | U13: 1 | V13: 0 | W13: 0 | X13: 0 | Y13: 0 | Z13: 0 | AA13: 0 | AB13: 0 | AC13: 0 | AD13: 0 | AE13: 0 | AF13: 0 | AG13: 0 | AH13: 0 | AI13: 0 | AJ13: 0 | AK13: 0 | AL13: 0 | AM13: 1 | AN13: 0 | AO13: 0 | AP13: 0 | AQ13: 0 | AR13: 0 | AS13: 0 | AT13: 0 | AU13: 0 | AV13: 0 | AW13: 0 | AX13: 0 | AY13: 0 | AZ13: 0 | BA13: 0 | BB13: 0 | BC13: 0 | BD13: 0 | BE13: 0 | BF13: 0 | BG13: 0 | BH13: 0 | BI13: 0 | BJ13: 1 | BK13: 0 | BL13: 0 | BM13: 0 | BN13: 0 | BO13: 0 | BP13: 0 | BQ13: 0 | BR13: 0 | BS13: 0 | BT13: 0 | BU13: 0 | BV13: 0 | BW13: 0 | BX13: 0 | BY13: 1 | BZ13: 1 | CA13: 1 | CB13: 0 | CC13: 0 | CD13: 0 | CE13: 0 | CF13: 0 | CG13: 0 | CH13: 0 | CI13: 0 | CJ13: 0 | CK13: 0 | CL13: 0 | CM13: 0 | CN13: 0 | CO13: 0 | CP13: 0 | CQ13: 0 | CR13: 0 | CS13: 0 | CT13: =SUM(A13:CS13) -> 7
... A97: Royal Heights Elementary | B97: 0 | C97: 0 | D97: 0 | E97: 0 | F97: 0 | G97: 0 | H97: 0 | I97: 0 | J97: 0 | K97: 0 | L97: 0 | M97: 0 | N97: 0 | O97: 0 | P97: 0 | Q97: 0 | R97: 0 | S97: 0 | T97: 0 | U97: 0 | V97: 0 | W97: 0 | X97: 0 | Y97: 0 | Z97: 0 | AA97: 0 | AB97: 0 | AC97: 0 | AD97: 0 | AE97: 0 | AF97: 0 | AG97: 0 | AH97: 0 | AI97: 0 | AJ97: 0 | AK97: 0 | AL97: 0 | AM97: 0 | AN97: 0 | AO97: 0 | AP97: 0 | AQ97: 0 | AR97: 0 | AS97: 0 | AT97: 0 | AU97: 0 | AV97: 0 | AW97: 0 | AX97: 0 | AY97: 0 | AZ97: 0 | BA97: 0 | BB97: 0 | BC97: 0 | BD97: 0 | BE97: 0 | BF97: 0 | BG97: 0 | BH97: 0 | BI97: 0 | BJ97: 0 | BK97: 0 | BL97: 0 | BM97: 0 | BN97: 0 | BO97: 0 | BP97: 0 | BQ97: 0 | BR97: 0 | BS97: 0 | BT97: 0 | BU97: 0 | BV97: 1 | BW97: 1 | BX97: 0 | BY97: 0 | BZ97: 1 | CA97: 0 | CB97: 0 | CC97: 0 | CD97: 0 | CE97: 0 | CF97: 0 | CG97: 0 | CH97: 0 | CI97: 0 | CJ97: 0 | CK97: 0 | CL97: 0 | CM97: 0 | CN97: 0 | CO97: 0 | CP97: 0 | CQ97: 0 | CR97: 0 | CS97: 1 | CT97: =SUM(A97:CS97) -> 4
B98: =SUM(B2:B97) -> 3 | C98: =SUM(C2:C97) -> 6 | D98: =SUM(D2:D97) -> 8 | E98: =SUM(E2:E97) -> 4 | F98: =SUM(F2:F97) -> 6 | G98: =SUM(G2:G97) -> 5 | H98: =SUM(H2:H97) -> 3 | I98: =SUM(I2:I97) -> 6 | ... CS98: =SUM(CS2:CS97) -> 4
C99: 1 | D99: 2 | E99: 3 | F99: 4 | G99: 5 | H99: 6 | I99: 7 | J99: 8 | K99: 9 | L99: 10 | M99: 11 | N99: 12 | O99: 13 | P99: 14 | Q99: 15 | R99: 16 | S99: 17 | T99: 18 | U99: 19 | V99: 20 | W99: 21 | X99: 22 | Y99: 23 | Z99: 24 | AA99: 25 | AB99: 26 | AC99: 27 | AD99: 28 | AE99: 29 | AF99: 30 | AG99: 31 | AH99: 32 | AI99: 33 | AJ99: 34 | AK99: 35 | AL99: 36 | AM99: 37 | AN99: 38 | AO99: 39 | AP99: 40 | AQ99: 41 | AR99: 42 | AS99: 43 | AT99: 44 | AU99: 45 | AV99: 46 | AW99: 47 | AX99: 48 | AY99: 49 | AZ99: 50 | BA99: 51 | BB99: 52 | BC99: 53 | BD99: 54 | BE99: 55 | BF99: 56 | BG99: 57 | BH99: 58 | BI99: 59 | BJ99: 60 | BK99: 61 | BL99: 62 | BM99: 63 | BN99: 64 | BO99: 65 | BP99: 66 | BQ99: 67 | BR99: 68 | BS99: 69 | BT99: 70 | BU99: 71 | BV99: 72 | BW99: 73 | BX99: 74 | BY99: 75 | BZ99: 76 | CA99: 77 | CB99: 78 | CC99: 79 | CD99: 80 | CE99: 81 | CF99: 82 | CG99: 83 | CH99: 84 | CI99: 85 | CJ99: 86 | CK99: 87 | CL99: 88 | CM99: 89 | CN99: 90 | CO99: 91 | CP99: 92 | CQ99: 93 | CR99: 94 | CS99: 95 | CT99: 105
B100: 1 | C100: 1 | D100: 0 | E100: 0 | F100: 0 | G100: 0 | H100: 1 | I100: 0 | J100: 0 | K100: 0 | L100: 0 | M100: 0 | N100: 0 | O100: 0 | P100: 0 | Q100: 0 | R100: 0 | S100: 0 | T100: 0 | U100: 0 | V100: 0 | W100: 0 | X100: 0 | Y100: 0 | Z100: 0 | AA100: 0 | AB100: 0 | AC100: 0 | AD100: 0 | AE100: 0 | AF100: 0 | AG100: 0 | AH100: 0 | AI100: 0 | AJ100: 0 | AK100: 0 | AL100: 0 | AM100: 0 | AN100: 0 | AO100: 0 | AP100: 0 | AQ100: 0 | AR100: 0 | AS100: 0 | AT100: 0 | AU100: 0 | AV100: 0 | AW100: 0 | AX100: 0 | AY100: 0 | AZ100: 0 | BA100: 0 | BB100: 0 | BC100: 0 | BD100: 0 | BE100: 0 | BF100: 0 | BG100: 0 | BH100: 0 | BI100: 0 | BJ100: 0 | BK100: 0 | BL100: 0 | BM100: 0 | BN100: 0 | BO100: 0 | BP100: 0 | BQ100: 0 | BR100: 0 | BS100: 0 | BT100: 0 | BU100: 0 | BV100: 0 | BW100: 0 | BX100: 0 | BY100: 0 | BZ100: 0 | CA100: 0 | CB100: 0 | CC100: 0 | CD100: 0 | CE100: 0 | CF100: 1 | CG100: 0 | CH100: 0 | CI100: 0 | CJ100: 0 | CK100: 0 | CL100: 0 | CM100: 0 | CN100: 0 | CO100: 0 | CP100: 0 | CQ100: 0 | CR100: 0 | CS100: 0 | CT100: 0
B101: 2 | C101: 0 | D101: 1 | E101: 1 | F101: 0 | G101: 0 | H101: 0 | I101: 0 | J101: 0 | K101: 0 | L101: 0 | M101: 0 | N101: 0 | O101: 0 | P101: 0 | Q101: 0 | R101: 0 | S101: 0 | T101: 1 | U101: 0 | V101: 0 | W101: 0 | X101: 0 | Y101: 0 | Z101: 0 | AA101: 0 | AB101: 0 | AC101: 0 | AD101: 0 | AE101: 0 | AF101: 0 | AG101: 0 | AH101: 0 | AI101: 0 | AJ101: 0 | AK101: 0 | AL101: 0 | AM101: 0 | AN101: 0 | AO101: 0 | AP101: 0 | AQ101: 0 | AR101: 0 | AS101: 0 | AT101: 0 | AU101: 0 | AV101: 0 | AW101: 0 | AX101: 0 | AY101: 1 | AZ101: 0 | BA101: 0 | BB101: 0 | BC101: 0 | BD101: 0 | BE101: 0 | BF101: 0 | BG101: 0 | BH101: 1 | BI101: 0 | BJ101: 0 | BK101: 0 | BL101: 0 | BM101: 0 | BN101: 0 | BO101: 0 | BP101: 0 | BQ101: 1 | BR101: 0 | BS101: 0 | BT101: 0 | BU101: 0 | BV101: 0 | BW101: 0 | BX101: 0 | BY101: 0 | BZ101: 0 | CA101: 0 | CB101: 0 | CC101: 0 | CD101: 0 | CE101: 0 | CF101: 0 | CG101: 0 | CH101: 0 | CI101: 0 | CJ101: 0 | CK101: 0 | CL101: 0 | CM101: 0 | CN101: 0 | CO101: 0 | CP101: 0 | CQ101: 0 | CR101: 0 | CS101: 0 | CT101: 0
B102: 3 | C102: 0 | D102: 1 | E102: 1 | F102: 0 | G102: 0 | H102: 0 | I102: 0 | J102: 0 | K102: 0 | L102: 0 | M102: 1 | N102: 0 | O102: 1 | P102: 0 | Q102: 0 | R102: 0 | S102: 0 | T102: 1 | U102: 0 | V102: 0 | W102: 0 | X102: 0 | Y102: 0 | Z102: 0 | AA102: 0 | AB102: 0 | AC102: 0 | AD102: 0 | AE102: 0 | AF102: 0 | AG102: 0 | AH102: 0 | AI102: 0 | AJ102: 0 | AK102: 0 | AL102: 0 | AM102: 0 | AN102: 0 | AO102: 0 | AP102: 0 | AQ102: 0 | AR102: 0 | AS102: 1 | AT102: 0 | AU102: 0 | AV102: 0 | AW102: 0 | AX102: 0 | AY102: 1 | AZ102: 0 | BA102: 0 | BB102: 0 | BC102: 0 | BD102: 0 | BE102: 0 | BF102: 0 | BG102: 0 | BH102: 1 | BI102: 0 | BJ102: 0 | BK102: 0 | BL102: 0 | BM102: 0 | BN102: 0 | BO102: 0 | BP102: 0 | BQ102: 1 | BR102: 0 | BS102: 0 | BT102: 0 | BU102: 0 | BV102: 0 | BW102: 0 | BX102: 0 | BY102: 0 | BZ102: 0 | CA102: 0 | CB102: 0 | CC102: 0 | CD102: 0 | CE102: 0 | CF102: 0 | CG102: 0 | CH102: 0 | CI102: 0 | CJ102: 0 | CK102: 0 | CL102: 0 | CM102: 0 | CN102: 0 | CO102: 0 | CP102: 0 | CQ102: 0 | CR102: 0 | CS102: 0 | CT102: 0
B103: 4 | C103: 0 | D103: 0 | E103: 0 | F103: 1 | G103: 0 | H103: 0 | I103: 0 | J103: 0 | K103: 0 | L103: 0 | M103: 0 | N103: 0 | O103: 0 | P103: 0 | Q103: 0 | R103: 0 | S103: 0 | T103: 0 | U103: 0 | V103: 0 | W103: 0 | X103: 0 | Y103: 0 | Z103: 0 | AA103: 0 | AB103: 1 | AC103: 0 | AD103: 0 | AE103: 0 | AF103: 0 | AG103: 0 | AH103: 0 | AI103: 0 | AJ103: 0 | AK103: 0 | AL103: 0 | AM103: 0 | AN103: 0 | AO103: 1 | AP103: 0 | AQ103: 0 | AR103: 0 | AS103: 0 | AT103: 0 | AU103: 0 | AV103: 0 | AW103: 0 | AX103: 0 | AY103: 0 | AZ103: 0 | BA103: 0 | BB103: 0 | BC103: 0 | BD103: 0 | BE103: 0 | BF103: 0 | BG103: 0 | BH103: 0 | BI103: 0 | BJ103: 0 | BK103: 0 | BL103: 0 | BM103: 0 | BN103: 0 | BO103: 0 | BP103: 0 | BQ103: 0 | BR103: 0 | BS103: 0 | BT103: 0 | BU103: 0 | BV103: 0 | BW103: 0 | BX103: 0 | BY103: 0 | BZ103: 0 | CA103: 0 | CB103: 0 | CC103: 0 | CD103: 0 | CE103: 0 | CF103: 0 | CG103: 1 | CH103: 0 | CI103: 0 | CJ103: 0 | CK103: 0 | CL103: 0 | CM103: 0 | CN103: 0 | CO103: 0 | CP103: 0 | CQ103: 0 | CR103: 0 | CS103: 0 | CT103: 0
B104: 5 | C104: 0 | D104: 0 | E104: 0 | F104: 0 | G104: 1 | H104: 1 | I104: 0 | J104: 0 | K104: 0 | L104: 0 | M104: 0 | N104: 0 | O104: 0 | P104: 1 | Q104: 0 | R104: 0 | S104: 0 | T104: 0 | U104: 0 | V104: 0 | W104: 0 | X104: 0 | Y104: 0 | Z104: 1 | AA104: 0 | AB104: 0 | AC104: 0 | AD104: 0 | AE104: 0 | AF104: 0 | AG104: 0 | AH104: 0 | AI104: 0 | AJ104: 0 | AK104: 0 | AL104: 0 | AM104: 0 | AN104: 0 | AO104: 0 | AP104: 0 | AQ104: 0 | AR104: 1 | AS104: 0 | AT104: 0 | AU104: 0 | AV104: 0 | AW104: 0 | AX104: 0 | AY104: 0 | AZ104: 0 | BA104: 0 | BB104: 0 | BC104: 0 | BD104: 0 | BE104: 0 | BF104: 0 | BG104: 0 | BH104: 0 | BI104: 0 | BJ104: 0 | BK104: 0 | BL104: 0 | BM104: 0 | BN104: 0 | BO104: 0 | BP104: 0 | BQ104: 0 | BR104: 0 | BS104: 0 | BT104: 0 | BU104: 0 | BV104: 0 | BW104: 0 | BX104: 0 | BY104: 0 | BZ104: 0 | CA104: 0 | CB104: 0 | CC104: 0 | CD104: 0 | CE104: 0 | CF104: 1 | CG104: 0 | CH104: 0 | CI104: 0 | CJ104: 0 | CK104: 0 | CL104: 0 | CM104: 0 | CN104: 0 | CO104: 0 | CP104: 0 | CQ104: 0 | CR104: 0 | CS104: 0 | CT104: 1
B105: 6 | C105: 1 | D105: 0 | E105: 0 | F105: 0 | G105: 1 | H105: 1 | I105: 0 | J105: 0 | K105: 0 | L105: 0 | M105: 0 | N105: 0 | O105: 0 | P105: 1 | Q105: 0 | R105: 0 | S105: 0 | T105: 0 | U105: 0 | V105: 0 | W105: 0 | X105: 0 | Y105: 0 | Z105: 0 | AA105: 0 | AB105: 0 | AC105: 0 | AD105: 0 | AE105: 0 | AF105: 0 | AG105: 0 | AH105: 0 | AI105: 0 | AJ105: 0 | AK105: 0 | AL105: 0 | AM105: 0 | AN105: 0 | AO105: 0 | AP105: 0 | AQ105: 0 | AR105: 0 | AS105: 0 | AT105: 0 | AU105: 0 | AV105: 0 | AW105: 0 | AX105: 0 | AY105: 0 | AZ105: 0 | BA105: 0 | BB105: 0 | BC105: 0 | BD105: 0 | BE105: 0 | BF105: 0 | BG105: 0 | BH105: 0 | BI105: 0 | BJ105: 0 | BK105: 0 | BL105: 0 | BM105: 0 | BN105: 0 | BO105: 0 | BP105: 0 | BQ105: 0 | BR105: 0 | BS105: 0 | BT105: 0 | BU105: 0 | BV105: 0 | BW105: 0 | BX105: 0 | BY105: 0 | BZ105: 0 | CA105: 0 | CB105: 0 | CC105: 0 | CD105: 0 | CE105: 0 | CF105: 1 | CG105: 0 | CH105: 0 | CI105: 0 | CJ105: 0 | CK105: 0 | CL105: 0 | CM105: 0 | CN105: 0 | CO105: 0 | CP105: 0 | CQ105: 0 | CR105: 0 | CS105: 0 | CT105: 1
B106: 7 | C106: 0 | D106: 0 | E106: 0 | F106: 0 | G106: 0 | H106: 0 | I106: 1 | J106: 0 | K106: 0 | L106: 0 | M106: 0 | N106: 0 | O106: 0 | P106: 0 | Q106: 0 | R106: 0 | S106: 0 | T106: 0 | U106: 0 | V106: 0 | W106: 0 | X106: 0 | Y106: 1 | Z106: 0 | AA106: 0 | AB106: 0 | AC106: 0 | AD106: 0 | AE106: 0 | AF106: 0 | AG106: 0 | AH106: 0 | AI106: 0 | AJ106: 0 | AK106: 0 | AL106: 0 | AM106: 0 | AN106: 0 | AO106: 0 | AP106: 0 | AQ106: 0 | AR106: 0 | AS106: 0 | AT106: 0 | AU106: 0 | AV106: 0 | AW106: 0 | AX106: 0 | AY106: 0 | AZ106: 0 | BA106: 0 | BB106: 0 | BC106: 0 | BD106: 0 | BE106: 0 | BF106: 0 | BG106: 0 | BH106: 0 | BI106: 0 | BJ106: 0 | BK106: 0 | BL106: 0 | BM106: 0 | BN106: 0 | BO106: 0 | BP106: 0 | BQ106: 0 | BR106: 0 | BS106: 0 | BT106: 0 | BU106: 0 | BV106: 0 | BW106: 0 | BX106: 0 | BY106: 0 | BZ106: 0 | CA106: 0 | CB106: 0 | CC106: 0 | CD106: 0 | CE106: 0 | CF106: 0 | CG106: 0 | CH106: 1 | CI106: 0 | CJ106: 0 | CK106: 0 | CL106: 0 | CM106: 0 | CN106: 0 | CO106: 0 | CP106: 0 | CQ106: 0 | CR106: 0 | CS106: 0 | CT106: 0
B107: 8 | C107: 0 | D107: 0 | E107: 0 | F107: 0 | G107: 0 | H107: 0 | I107: 0 | J107: 1 | K107: 0 | L107: 0 | M107: 0 | N107: 0 | O107: 0 | P107: 0 | Q107: 0 | R107: 0 | S107: 0 | T107: 0 | U107: 0 | V107: 0 | W107: 0 | X107: 0 | Y107: 0 | Z107: 0 | AA107: 0 | AB107: 0 | AC107: 0 | AD107: 0 | AE107: 0 | AF107: 0 | AG107: 0 | AH107: 0 | AI107: 0 | AJ107: 0 | AK107: 0 | AL107: 0 | AM107: 0 | AN107: 0 | AO107: 0 | AP107: 0 | AQ107: 0 | AR107: 0 | AS107: 0 | AT107: 0 | AU107: 0 | AV107: 0 | AW107: 0 | AX107: 1 | AY107: 0 | AZ107: 1 | BA107: 0 | BB107: 0 | BC107: 1 | BD107: 0 | BE107: 0 | BF107: 0 | BG107: 0 | BH107: 1 | BI107: 0 | BJ107: 0 | BK107: 0 | BL107: 0 | BM107: 0 | BN107: 0 | BO107: 0 | BP107: 0 | BQ107: 1 | BR107: 0 | BS107: 0 | BT107: 0 | BU107: 0 | BV107: 0 | BW107: 0 | BX107: 0 | BY107: 0 | BZ107: 0 | CA107: 0 | CB107: 0 | CC107: 0 | CD107: 0 | CE107: 0 | CF107: 0 | CG107: 0 | CH107: 0 | CI107: 0 | CJ107: 0 | CK107: 0 | CL107: 0 | CM107: 0 | CN107: 0 | CO107: 0 | CP107: 0 | CQ107: 0 | CR107: 0 | CS107: 0 | CT107: 0
